Workbook

Sheet dinamica
A2: Empreendimento | B2: (Tudo)
A3: Situação do Repasse | B3: (Vários itens)
G4: 2025 | H4: 2026
A5: Contagem de Reserva | C5: Data | H5: =D5/3 -> 0
A6: Corretor | B6: Imobiliária | C6: 2024 | D6: 2025 | E6: 2026 | F6: (vazio) | G6: Total Geral | H6: =D6/3 -> 675
A7: ARTHUR PARRIAO NEGOCIOS IMOBILIARIOS | B7: IMOBILIÁRIAS | FSA | D7: 5 | E7: 13 | G7: 18 | H7: =D7/3 -> 1.6666667
A8: ISABELLA PEREIRA FELICIANO | B8: AUTÔNOMOS | FSA | C8: 15 | D8: 19 | E8: 2 | G8: 36 | H8: =D8/3 -> 6.3333333
A9: ISABELLA PEREIRA FELICIANO | B9: AUTÔNOMOS 2 | FSA | D9: 15 | E9: 6 | G9: 21 | H9: =D9/3 -> 5
A10: CLEIDE ALVES DE OLIVEIRA | B10: AUTÔNOMOS | FSA | D10: 8 | E10: 8 | G10: 16 | H10: =D10/3 -> 2.6666667
A11: ANNA LUIZA PEREIRA DE SOUSA | B11: AUTÔNOMOS | FSA | D11: 20 | E11: 7 | G11: 27 | H11: =D11/3 -> 6.6666667
A12: MARIA EDUARDA VIEIRA DAMASCENO - CLT | B12: CANAL VIRTUAL 1 | D12: 3 | E12: 7 | G12: 10 | H12: =D12/3 -> 1
A13: MARIA EDUARDA VIEIRA DAMASCENO - CLT | B13: CANAL VIRTUAL 2 | D13: 12 | G13: 12 | H13: =D13/3 -> 4
A14: GABRIEL DO NASCIMENTO DIAS - CLT | B14: EQUIPE PRÓPRIA |FSA | C14: 27 | D14: 27 | E14: 7 | G14: 61 | H14: =D14/3 -> 9
A15: PASCOAL IMOBILIARIA | B15: IMOBILIÁRIAS | AGL | C15: 34 | D15: 23 | E15: 6 | G15: 63 | H15: =D15/3 -> 7.6666667
A16: LUCIANO PONTES SILVA JUNIOR - CLT | B16: CANAL VIRTUAL 2 | D16: 1 | E16: 6 | G16: 7 | H16: =D16/3 -> 0.33333333
A17: LUCAS PAULO MARQUES PINTO - CLT | B17: EQUIPE PRÓPRIA |FSA | D17: 6 | E17: 6 | G17: 12 | H17: =D17/3 -> 2
A18: FABIANE BEZERRA MOREIRA DOS SANTOS - CLT | B18: EQUIPE PRÓPRIA 2 | AGL | D18: 1 | E18: 5 | F18: 1 | G18: 7 | H18: =D18/3 -> 0.33333333
A19: VITÓRIA IMÓVEIS IMOB | B19: AUTÔNOMOS | FSA | C19: 14 | D19: 1 | G19: 15 | H19: =D19/3 -> 0.33333333
A20: VITÓRIA IMÓVEIS IMOB | B20: IMOBILIÁRIAS | FSA | D20: 17 | E20: 5 | G20: 22 | H20: =D20/3 -> 5.6666667
A21: MARIA EUGENIA MARTINS ALVES - CLT | B21: EQUIPE PRÓPRIA |FSA | D21: 8 | E21: 5 | G21: 13 | H21: =D21/3 -> 2.6666667
A22: 7LM - VENDAS INTERNAS NOVKA | B22: NOVKA| DF | D22: 1 | E22: 5 | F22: 17 | G22: 23 | H22: =D22/3 -> 0.33333333
A23: MARA IMOBILIARIA LTDA | B23: IMOBILIÁRIAS | FSA | D23: 8 | E23: 5 | F23: 1 | G23: 14 | H23: =D23/3 -> 2.6666667
A24: GYOVANA FERNANDES ALMEIDA CASTRO | B24: AUTÔNOMOS 2 | FSA | D24: 4 | E24: 5 | G24: 9 | H24: =D24/3 -> 1.3333333
A25: KEULLY DE SOUSA BRAGA | B25: AUTÔNOMOS | FSA | E25: 2 | G25: 2 | H25: =D25/3 -> 0
A26: KEULLY DE SOUSA BRAGA | B26: AUTÔNOMOS 2 | FSA | E26: 3 | G26: 3 | H26: =D26/3 -> 0
A27: MICAEL DOS SANTOS PIRES - CLT | B27: CANAL VIRTUAL | C27: 13 | D27: 2 | G27: 15 | H27: =D27/3 -> 0.66666667
A28: MICAEL DOS SANTOS PIRES - CLT | B28: CANAL VIRTUAL 1 | D28: 2 | G28: 2 | H28: =D28/3 -> 0.66666667
A29: MICAEL DOS SANTOS PIRES - CLT | B29: EQUIPE PRÓPRIA | AGL | D29: 10 | G29: 10 | H29: =D29/3 -> 3.3333333
A30: MICAEL DOS SANTOS PIRES - CLT | B30: EQUIPE PRÓPRIA 2 | AGL | D30: 6 | E30: 4 | G30: 10 | H30: =D30/3 -> 2
A31: INGRID ALVES D'APARECIDA - CLT | B31: EQUIPE PRÓPRIA |FSA | C31: 21 | D31: 27 | E31: 4 | G31: 52 | H31: =D31/3 -> 9
A32: NATASHA LUCÍLIA BARBOSA - CLT | B32: EQUIPE PRÓPRIA 2 | AGL | D32: 1 | E32: 4 | G32: 5 | H32: =D32/3 -> 0.33333333
A33: JULIANA MARIA DE SOUZA - CLT | B33: EQUIPE PRÓPRIA 2 | AGL | E33: 4 | G33: 4 | H33: =D33/3 -> 0
A34: DAIANA SOARES DA ROCHA | B34: AUTÔNOMOS | FSA | D34: 24 | E34: 4 | G34: 28 | H34: =D34/3 -> 8
A35: WANDERSON ROMERO COELHO DA SILVA - CLT | B35: AUTÔNOMOS | AGL | D35: 8 | E35: 1 | G35: 9 | H35: =D35/3 -> 2.6666667
A36: WANDERSON ROMERO COELHO DA SILVA - CLT | B36: EQUIPE PRÓPRIA | AGL | E36: 3 | G36: 3 | H36: =D36/3 -> 0
A37: MILENE DE ALMEIDA LIMA - CLT | B37: EQUIPE PRÓPRIA | AGL | D37: 3 | E37: 4 | G37: 7 | H37: =D37/3 -> 1
A38: LETÍCIA SANTOS DA SILVA BRITO - CLT | B38: CANAL VIRTUAL 2 | E38: 4 | G38: 4
A39: NAUANE MARTINS DA SILVA OLIVEIRA - CLT | B39: EQUIPE PRÓPRIA |FSA | C39: 16 | D39: 26 | E39: 4 | G39: 46
A40: ERAF CORRETORA DE IMÓVEIS EIRELI | B40: AUTÔNOMOS | FSA | C40: 9 | G40: 9
A41: ERAF CORRETORA DE IMÓVEIS EIRELI | B41: IMOBILIÁRIAS | FSA | D41: 8 | E41: 4 | G41: 12
A42: STEFFANY SILVA PINTO | B42: AUTÔNOMOS | FSA | D42: 2 | E42: 4 | G42: 6
A43: CAMILA FERNANDES DA SILVA | B43: AUTÔNOMOS | FSA | C43: 15 | D43: 19 | E43: 4 | G43: 38
A44: JOÃO VITOR BRITO DE ANDRADE - CLT | B44: EQUIPE PRÓPRIA | AGL | D44: 2 | G44: 2
A45: JOÃO VITOR BRITO DE ANDRADE - CLT | B45: EQUIPE PRÓPRIA 2 | AGL | E45: 4 | G45: 4
A46: MAYSA GABRIELA GONÇALVES OLIVEIRA - CLT | B46: EQUIPE PRÓPRIA | AGL | C46: 13 | D46: 9 | E46: 4 | G46: 26
A47: THAIRINE STEFANNI RODRIGUES DA SILVA | B47: AUTÔNOMOS 2 | FSA | D47: 4 | E47: 3 | F47: 1 | G47: 8
A48: RYAN GOMES CALAZANS - CLT | B48: EQUIPE PRÓPRIA |FSA | C48: 23 | D48: 21 | E48: 3 | G48: 47
A49: MARCELO MIRANDA VIEIRA | B49: BEIRAMAR | DF | E49: 3 | F49: 2 | G49: 5
A50: MORIÁ- DANIEL | B50: IMOBILIÁRIAS | AGL | C50: 1 | D50: 9 | E50: 3 | G50: 13
A51: ANA LUCIA RODRIGUES DE FREITAS | B51: BEIRAMAR | DF | E51: 3 | F51: 1 | G51: 4
A52: DANIEL ANDRADE DOS SANTOS - CLT | B52: CANAL VIRTUAL | C52: 2 | D52: 5 | G52: 7
A53: DANIEL ANDRADE DOS SANTOS - CLT | B53: CANAL VIRTUAL 1 | D53: 23 | E53: 3 | F53: 1 | G53: 27
A54: MICHELE OLIVEIRA ROCHA | B54: BEIRAMAR | DF | E54: 3 | G54: 3
A55: ARIANI MORAIS DE SOUSA PEREIRA - CLT | B55: EQUIPE PRÓPRIA | AGL | D55: 10 | E55: 3 | F55: 1 | G55: 14
A56: JONATAN CASTRO DA SILVA - CLT | B56: AUTÔNOMOS | AGL | C56: 2 | G56: 2
A57: JONATAN CASTRO DA SILVA - CLT | B57: EQUIPE PRÓPRIA | AGL | C57: 6 | D57: 16 | E57: 3 | G57: 25
A58: JOSÉ RIBAMAR DA SILVA FREITAS FILHO - CLT | B58: CANAL VIRTUAL | C58: 3 | D58: 2 | G58: 5
A59: JOSÉ RIBAMAR DA SILVA FREITAS FILHO - CLT | B59: CANAL VIRTUAL 1 | D59: 10 | G59: 10
A60: JOSÉ RIBAMAR DA SILVA FREITAS FILHO - CLT | B60: CANAL VIRTUAL 2 | E60: 3 | G60: 3
A61: MARIA DAIANA DA SILVA BRANDÃO - CLT | B61: EQUIPE PRÓPRIA |FSA | D61: 4 | E61: 2 | F61: 1 | G61: 7
A62: REBECA CRISTHINA PIRES DIAS - CLT | B62: EQUIPE PRÓPRIA 2 | AGL | E62: 2 | G62: 2
A63: ANA CAROLINA FERREIRA DE ANDRADE - CARLOS ANDRADE IMOBILIÁRIA | B63: AUTÔNOMOS | FSA | C63: 29 | D63: 1 | G63: 30
A64: ANA CAROLINA FERREIRA DE ANDRADE - CARLOS ANDRADE IMOBILIÁRIA | B64: IMOBILIÁRIAS | FSA | D64: 14 | E64: 2 | G64: 16
A65: IMOB MINHA CORRETORA | B65: AUTÔNOMOS | FSA | C65: 1 | D65: 2 | G65: 3
A66: IMOB MINHA CORRETORA | B66: IMOBILIÁRIAS | FSA | D66: 5 | E66: 2 | G66: 7
A67: MARCILENE DOS REIS CARVALHO | B67: AUTÔNOMOS | FSA | C67: 1 | D67: 7 | G67: 8
A68: MARCILENE DOS REIS CARVALHO | B68: AUTÔNOMOS 2 | FSA | D68: 2 | E68: 2 | G68: 4
A69: JACILENE FREITAS SANTOS | B69: AUTÔNOMOS | AGL | D69: 6 | E69: 2 | G69: 8
A70: MATHEUS AIRES GUERRA | B70: BEIRAMAR | DF | E70: 2 | F70: 5 | G70: 7
A71: LETICIA LORRANNY SANTOS DOURADO | B71: AUTÔNOMOS 2 | FSA | D71: 2 | E71: 2 | G71: 4
A72: PORTELA IMOBILIARIA | B72: IMOBILIÁRIAS | FSA | D72: 1 | E72: 2 | G72: 3
A73: LINDINALVA ROSA PALMEIRA | B73: BEIRAMAR | DF | E73: 2 | F73: 1 | G73: 3
A74: SANDRA SANTOS - CLT | B74: CANAL VIRTUAL | C74: 1 | D74: 5 | G74: 6
A75: SANDRA SANTOS - CLT | B75: CANAL VIRTUAL 1 | D75: 2 | G75: 2
A76: SANDRA SANTOS - CLT | B76: CANAL VIRTUAL 2 | D76: 9 | E76: 2 | G76: 11
A77: LK IMÓVEIS - LEONARDO APARECIDO | B77: IMOBILIÁRIAS | AGL | C77: 3 | D77: 3 | E77: 2 | G77: 8
A78: LUCAS DE SOUZA RODRIGUES - CLT | B78: CANAL VIRTUAL 1 | E78: 2 | G78: 2
A79: PEDRO HIGOR CANDEIAS | B79: BEIRAMAR | DF | E79: 1 | G79: 1
A80: LEONARD LUIS MOGENA PEREZ - CLT | B80: EQUIPE PRÓPRIA |FSA | D80: 9 | E80: 1 | G80: 10
A81: BYANCA LOPES CLARO DE SOUZA | B81: BEIRAMAR | DF | E81: 1 | G81: 1
A82: CAIO BRENDON LOPES MARTINS - CLT | B82: CANAL VIRTUAL 1 | D82: 2 | E82: 1 | G82: 3
A83: NOVA MORADA IMOBILIARIA | B83: IMOBILIÁRIAS | AGL | E83: 1 | G83: 1
A84: EMMANUELY FERNANDA DO NASCIMENTO | B84: AUTÔNOMOS | FSA | D84: 3 | E84: 1 | G84: 4
A85: PSI NEGOCIOS IMOBILIARIOS LTDA | B85: NOVKA| DF | D85: 6 | E85: 1 | F85: 3 | G85: 10
A86: PSI NEGOCIOS IMOBILIARIOS LTDA | B86: PSI NEGOCIOS IMOBILIARIOS LTDA | D86: 2 | G86: 2
A87: IMOBILIARIA EXPERT IMOVEIS | B87: IMOBILIÁRIAS | AGL | D87: 3 | E87: 1 | G87: 4
A88: S PESTANA NEGOCIOS IMOBILIARIOS LTDA | B88: IMOBILIÁRIAS | AGL | E88: 1 | G88: 1
A89: LUCAS BRAGA DE SOUZA OLIVEIRA - CLT | B89: CANAL VIRTUAL 1 | E89: 1 | G89: 1
A90: FLAVIA SERVIÇOS IMOBILIARIOS | B90: AUTÔNOMOS | FSA | C90: 6 | D90: 1 | G90: 7
A91: FLAVIA SERVIÇOS IMOBILIARIOS | B91: IMOBILIÁRIAS | FSA | D91: 6 | E91: 1 | G91: 7
A92: THAMIRES SANTOS DE ARAUJO | B92: AUTÔNOMOS | FSA | C92: 1 | G92: 1
A93: THAMIRES SANTOS DE ARAUJO | B93: IMOBILIÁRIAS | FSA | D93: 3 | E93: 1 | G93: 4
A94: PAULA CÍCERA PEREIRA DE OLIVEIRA SANTOS - CLT | B94: EQUIPE PRÓPRIA | AGL | E94: 1 | G94: 1
A95: LUIS ALVES DOS SANTOS DA SILVA ROCCHA - CLT | B95: CANAL VIRTUAL | C95: 13 | D95: 4 | G95: 17
A96: LUIS ALVES DOS SANTOS DA SILVA ROCCHA - CLT | B96: CANAL VIRTUAL 1 | D96: 10 | E96: 1 | G96: 11
A97: YVELISE FERREIRA PINHEIRO - CLT | B97: AUTÔNOMOS | AGL | D97: 3 | G97: 3
A98: YVELISE FERREIRA PINHEIRO - CLT | B98: EQUIPE PRÓPRIA | AGL | E98: 1 | G98: 1
A99: ANIBAL HAMU NETO | B99: AUTÔNOMOS | FSA | D99: 1 | E99: 1 | G99: 2
A100: RAQUEL SILVA DE SENNA DIAS DE LAET | B100: BEIRAMAR | DF | E100: 1 | G100: 1
A101: JACQUELINE LINHARES NOVAES | B101: BEIRAMAR | DF | E101: 1 | G101: 1
...

Sheet Planilha2
E1: 46142 | G1: Repasses
C2: Imobiliária | D2: Consultores | E2: Data Início | F2: Qts Meses? | G2: 2024 | H2: 2025 | I2: 2026 | K2: IPC 2024 | L2: IPC 2025 | M2: IPC 2026 | N2: Meta | P2: Situação ? | R2: Gradadivo
A3: 1 | B3: 1 | C3: =VLOOKUP(D3,dinamica!A:B,2,0) -> AUTÔNOMOS | FSA | D3: CLEIDE ALVES DE OLIVEIRA | E3: =VLOOKUP(D3,[1]Colaboradores!$A$2:$D$65,4,0) -> 45769 | F3: =_xlfn.DAYS($E$1,E3)/30 -> 12.433333 | H3: 8 | I3: 8 | K3: =G3/12 -> 0 | L3: =H3/12 -> 0.66666667 | M3: =I3/3 -> 2.6666667 | N3: =VLOOKUP(F3,$U$8:$V$94,2) -> 2 | P3: =IF(M3>=N3,"OK","Analisar") -> OK | U3: 0-3 meses: 2 repasses ou IPC 0,66;
A4: =A3+1 -> 2 | B4: =B3+1 -> 2 | C4: =VLOOKUP(D4,dinamica!A:B,2,0) -> AUTÔNOMOS | FSA | D4: ISABELLA PEREIRA FELICIANO | E4: =VLOOKUP(D4,[1]Colaboradores!$A$2:$D$65,4,0) -> 45156 | F4: =_xlfn.DAYS($E$1,E4)/30 -> 32.866667 | G4: 15 | H4: 34 | I4: 8 | K4: =G4/12 -> 1.25 | L4: =H4/12 -> 2.8333333 | M4: =I4/3 -> 2.6666667 | N4: =VLOOKUP(F4,$U$8:$V$94,2) -> 2 | P4: =IF(M4>=N4,"OK","Analisar") -> OK | U4: 3-6 meses: 4 repasses ou IPC 1,33;
A5: =A4+1 -> 3 | B5: =B4+1 -> 3 | C5: =VLOOKUP(D5,dinamica!A:B,2,0) -> AUTÔNOMOS | FSA | D5: ANNA LUIZA PEREIRA DE SOUSA | E5: =VLOOKUP(D5,[1]Colaboradores!$A$2:$D$65,4,0) -> 45791 | F5: =_xlfn.DAYS($E$1,E5)/30 -> 11.7 | H5: 20 | I5: 7 | K5: =G5/12 -> 0 | L5: =H5/12 -> 1.6666667 | M5: =I5/3 -> 2.3333333 | N5: =VLOOKUP(F5,$U$8:$V$94,2) -> 2 | P5: =IF(M5>=N5,"OK","Analisar") -> OK | R5: Desenvolvimento | U5: 6-9 meses: 5 repasses ou IPC 1,66;
A6: =A5+1 -> 4 | B6: =B5+1 -> 4 | C6: =VLOOKUP(D6,dinamica!A:B,2,0) -> AUTÔNOMOS | FSA | D6: STEFFANY SILVA PINTO | E6: =VLOOKUP(D6,[1]Colaboradores!$A$2:$D$65,4,0) -> 45931 | F6: =_xlfn.DAYS($E$1,E6)/30 -> 7.0333333 | H6: 2 | I6: 4 | K6: =G6/12 -> 0 | L6: =H6/12 -> 0.16666667 | M6: =I6/3 -> 1.3333333 | N6: =VLOOKUP(F6,$U$8:$V$94,2) -> 1.66 | P6: =IF(M6>=N6,"OK","Analisar") -> Analisar | R6: Reposição | U6: Após 9 meses: 6 repasses ou IPC 2;
A7: =A6+1 -> 5 | B7: =B6+1 -> 5 | C7: =VLOOKUP(D7,dinamica!A:B,2,0) -> AUTÔNOMOS | FSA | D7: CAMILA FERNANDES DA SILVA | E7: =VLOOKUP(D7,[1]Colaboradores!$A$2:$D$65,4,0) -> 45261 | F7: =_xlfn.DAYS($E$1,E7)/30 -> 29.366667 | G7: 15 | H7: 19 | I7: 4 | K7: =G7/12 -> 1.25 | L7: =H7/12 -> 1.5833333 | M7: =I7/3 -> 1.3333333 | N7: =VLOOKUP(F7,$U$8:$V$94,2) -> 2 | P7: =IF(M7>=N7,"OK","Analisar") -> Analisar | R7: Críterios Definido
A8: =A7+1 -> 6 | B8: =B7+1 -> 6 | C8: =VLOOKUP(D8,dinamica!A:B,2,0) -> AUTÔNOMOS | FSA | D8: ANIBAL HAMU NETO | E8: =VLOOKUP(D8,[1]Colaboradores!$A$2:$D$65,4,0) -> 45931 | F8: =_xlfn.DAYS($E$1,E8)/30 -> 7.0333333 | H8: 1 | I8: 1 | K8: =G8/12 -> 0 | L8: =H8/12 -> 0.083333333 | M8: =I8/3 -> 0.33333333 | N8: =VLOOKUP(F8,$U$8:$V$94,2) -> 1.66 | P8: =IF(M8>=N8,"OK","Analisar") -> Analisar | U8: 0 | V8: 0.66
A9: =A8+1 -> 7 | B9: =B8+1 -> 7 | C9: =VLOOKUP(D9,dinamica!A:B,2,0) -> AUTÔNOMOS | FSA | D9: EMMANUELY FERNANDA DO NASCIMENTO | E9: =VLOOKUP(D9,[1]Colaboradores!$A$2:$D$65,4,0) -> 45882 | F9: =_xlfn.DAYS($E$1,E9)/30 -> 8.6666667 | H9: 3 | I9: 1 | K9: =G9/12 -> 0 | L9: =H9/12 -> 0.25 | M9: =I9/3 -> 0.33333333 | N9: =VLOOKUP(F9,$U$8:$V$94,2) -> 1.66 | P9: =IF(M9>=N9,"OK","Analisar") -> Analisar | R9: Racional crescimento Gradativo | U9: =1+U8 -> 1 | V9: 0.66
B10: =B9+1 -> 8 | C10: =VLOOKUP(D10,dinamica!A:B,2,0) -> AUTÔNOMOS | FSA | D10: JHENNEFE HORRARA SILVA DE OLIVEIRA | E10: =VLOOKUP(D10,[1]Colaboradores!$A$2:$D$65,4,0) -> 46084 | F10: =_xlfn.DAYS($E$1,E10)/30 -> 1.9333333 | I10: 1 | K10: =G10/12 -> 0 | L10: =H10/12 -> 0 | M10: =I10/3 -> 0.33333333 | N10: =VLOOKUP(F10,$U$8:$V$94,2) -> 0.66 | P10: =IF(M10>=N10,"OK","Analisar") -> Analisar | U10: =1+U9 -> 2 | V10: 0.66
A11: =A9+1 -> 8 | B11: =B10+1 -> 9 | C11: AUTÔNOMOS | FSA | D11: Thâmara Rafaella de Melo Santos | E11: =VLOOKUP(D11,[1]Colaboradores!$A$2:$D$65,4,0) -> 24/03/2026 | F11: =_xlfn.DAYS($E$1,E11)/30 -> 1.2333333 | N11: =VLOOKUP(F11,$U$8:$V$94,2) -> 0.66 | P11: =IF(M11>=N11,"OK","Analisar") -> Analisar | U11: =1+U10 -> 3 | V11: 0.66
A12: =A11+1 -> 9 | B12: 1 | C12: AUTÔNOMOS 2 | FSA | D12: KEULLY DE SOUSA BRAGA | E12: =VLOOKUP(D12,[1]Colaboradores!$A$2:$D$65,4,0) -> 46050 | F12: =_xlfn.DAYS($E$1,E12)/30 -> 3.0666667 | I12: 5 | K12: =G12/12 -> 0 | L12: =H12/12 -> 0 | M12: =I12/3 -> 1.6666667 | N12: =VLOOKUP(F12,$U$8:$V$94,2) -> 0.66 | P12: =IF(M12>=N12,"OK","Analisar") -> OK | R12: Replicar Gerentes | U12: =1+U11 -> 4 | V12: 1.33
A13: =A12+1 -> 10 | B13: =B12+1 -> 2 | C13: =VLOOKUP(D13,dinamica!A:B,2,0) -> AUTÔNOMOS 2 | FSA | D13: GYOVANA FERNANDES ALMEIDA CASTRO | E13: =VLOOKUP(D13,[1]Colaboradores!$A$2:$D$65,4,0) -> 45868 | F13: =_xlfn.DAYS($E$1,E13)/30 -> 9.1333333 | H13: 4 | I13: 5 | K13: =G13/12 -> 0 | L13: =H13/12 -> 0.33333333 | M13: =I13/3 -> 1.6666667 | N13: =VLOOKUP(F13,$U$8:$V$94,2) -> 1.66 | P13: =IF(M13>=N13,"OK","Analisar") -> OK | U13: =1+U12 -> 5 | V13: 1.33
A14: =A13+1 -> 11 | B14: =B13+1 -> 3 | C14: =VLOOKUP(D14,dinamica!A:B,2,0) -> AUTÔNOMOS 2 | FSA | D14: THAIRINE STEFANNI RODRIGUES DA SILVA | E14: =VLOOKUP(D14,[1]Colaboradores!$A$2:$D$65,4,0) -> 45868 | F14: =_xlfn.DAYS($E$1,E14)/30 -> 9.1333333 | H14: 4 | I14: 3 | K14: =G14/12 -> 0 | L14: =H14/12 -> 0.33333333 | M14: =I14/3 -> 1 | N14: =VLOOKUP(F14,$U$8:$V$94,2) -> 1.66 | P14: =IF(M14>=N14,"OK","Analisar") -> Analisar | R14: Rever Remunneração | U14: =1+U13 -> 6 | V14: 1.33
A15: =A14+1 -> 12 | B15: =B14+1 -> 4 | C15: AUTÔNOMOS 2 | FSA | D15: MARCILENE DOS REIS CARVALHO | E15: =VLOOKUP(D15,[1]Colaboradores!$A$2:$D$65,4,0) -> 45531 | F15: =_xlfn.DAYS($E$1,E15)/30 -> 20.366667 | G15: 1 | H15: 9 | I15: 2 | K15: =G15/12 -> 0.083333333 | L15: =H15/12 -> 0.75 | M15: =I15/3 -> 0.66666667 | N15: =VLOOKUP(F15,$U$8:$V$94,2) -> 2 | P15: =IF(M15>=N15,"OK","Analisar") -> Analisar | U15: =1+U14 -> 7 | V15: 1.66
A16: =A15+1 -> 13 | B16: =B15+1 -> 5 | C16: AUTÔNOMOS 2 | FSA | D16: LETÍCIA LORRANNY SANTOS DOURADO | E16: =VLOOKUP(D16,[1]Colaboradores!$A$2:$D$65,4,0) -> 45868 | F16: =_xlfn.DAYS($E$1,E16)/30 -> 9.1333333 | H16: 2 | I16: 2 | K16: =G16/12 -> 0 | L16: =H16/12 -> 0.16666667 | M16: =I16/3 -> 0.66666667 | N16: =VLOOKUP(F16,$U$8:$V$94,2) -> 1.66 | P16: =IF(M16>=N16,"OK","Analisar") -> Analisar | U16: =1+U15 -> 8 | V16: 1.66
A17: =A16+1 -> 14 | B17: =B16+1 -> 6 | C17: AUTÔNOMOS 2 | FSA | D17: Erika Alves Gomes | E17: =VLOOKUP(D17,[1]Colaboradores!$A$2:$D$65,4,0) -> 46099 | F17: =_xlfn.DAYS($E$1,E17)/30 -> 1.4333333 | N17: =VLOOKUP(F17,$U$8:$V$94,2) -> 0.66 | P17: =IF(M17>=N17,"OK","Analisar") -> Analisar | U17: =1+U16 -> 9 | V17: 1.66
A18: =A17+1 -> 15 | B18: =B17+1 -> 7 | C18: AUTÔNOMOS 2 | FSA | D18: Pabline Micheli Oliveira da Silva | E18: =VLOOKUP(D18,[1]Colaboradores!$A$2:$D$65,4,0) -> 46099 | F18: =_xlfn.DAYS($E$1,E18)/30 -> 1.4333333 | N18: =VLOOKUP(F18,$U$8:$V$94,2) -> 0.66 | P18: =IF(M18>=N18,"OK","Analisar") -> Analisar | U18: =1+U17 -> 10 | V18: 2
A19: =A18+1 -> 16 | B19: =B18+1 -> 8 | C19: AUTÔNOMOS 2 | FSA | D19: JOCICLEIDE FERREIRA DA PAIXÃO | E19: =VLOOKUP(D19,[1]Colaboradores!$A$2:$D$65,4,0) -> 46125 | F19: =_xlfn.DAYS($E$1,E19)/30 -> 0.56666667 | N19: =VLOOKUP(F19,$U$8:$V$94,2) -> 0.66 | P19: =IF(M19>=N19,"OK","Analisar") -> Analisar | U19: =1+U18 -> 11 | V19: 2
A20: =A19+1 -> 17 | B20: 1 | C20: EQUIPE PRÓPRIA |FSA | D20: Gabriel do Nascimento Dias | E20: =VLOOKUP(D20,[1]Colaboradores!$A$2:$D$65,4,0) -> 45231 | F20: =_xlfn.DAYS($E$1,E20)/30 -> 30.366667 | G20: 27 | H20: 27 | I20: 7 | K20: =G20/12 -> 2.25 | L20: =H20/12 -> 2.25 | M20: =I20/3 -> 2.3333333 | N20: =VLOOKUP(F20,$U$8:$V$94,2) -> 2 | P20: =IF(M20>=N20,"OK","Analisar") -> OK | U20: =1+U19 -> 12 | V20: 2
A21: =A20+1 -> 18 | B21: =B20+1 -> 2 | C21: EQUIPE PRÓPRIA |FSA | D21: Lucas Paulo Marques Pinto | E21: =VLOOKUP(D21,[1]Colaboradores!$A$2:$D$65,4,0) -> 45880 | F21: =_xlfn.DAYS($E$1,E21)/30 -> 8.7333333 | H21: 6 | I21: 6 | K21: =G21/12 -> 0 | L21: =H21/12 -> 0.5 | M21: =I21/3 -> 2 | N21: =VLOOKUP(F21,$U$8:$V$94,2) -> 1.66 | P21: =IF(M21>=N21,"OK","Analisar") -> OK | U21: =1+U20 -> 13 | V21: 2
A22: =A21+1 -> 19 | B22: =B21+1 -> 3 | C22: EQUIPE PRÓPRIA |FSA | D22: Maria Eugenia Martins alves | E22: =VLOOKUP(D22,[1]Colaboradores!$A$2:$D$65,4,0) -> 45902 | F22: =_xlfn.DAYS($E$1,E22)/30 -> 8 | H22: 8 | I22: 5 | K22: =G22/12 -> 0 | L22: =H22/12 -> 0.66666667 | M22: =I22/3 -> 1.6666667 | N22: =VLOOKUP(F22,$U$8:$V$94,2) -> 1.66 | P22: =IF(M22>=N22,"OK","Analisar") -> OK | U22: =1+U21 -> 14 | V22: 2
A23: =A22+1 -> 20 | B23: =B22+1 -> 4 | C23: EQUIPE PRÓPRIA |FSA | D23: INGRID ALVES DAPARECIDA | E23: =VLOOKUP(D23,[1]Colaboradores!$A$2:$D$65,4,0) -> 45267 | F23: =_xlfn.DAYS($E$1,E23)/30 -> 29.166667 | G23: 21 | H23: 27 | I23: 4 | K23: =G23/12 -> 1.75 | L23: =H23/12 -> 2.25 | M23: =I23/3 -> 1.3333333 | N23: =VLOOKUP(F23,$U$8:$V$94,2) -> 2 | P23: =IF(M23>=N23,"OK","Analisar") -> Analisar | U23: =1+U22 -> 15 | V23: 2
A24: =A23+1 -> 21 | B24: =B23+1 -> 5 | C24: EQUIPE PRÓPRIA |FSA | D24: Nauane Martins Da Silva Oliveira | E24: =VLOOKUP(D24,[1]Colaboradores!$A$2:$D$65,4,0) -> 23/08/2023 | F24: =_xlfn.DAYS($E$1,E24)/30 -> 32.7 | G24: 16 | H24: 26 | I24: 4 | K24: =G24/12 -> 1.3333333 | L24: =H24/12 -> 2.1666667 | M24: =I24/3 -> 1.3333333 | N24: =VLOOKUP(F24,$U$8:$V$94,2) -> 2 | P24: =IF(M24>=N24,"OK","Analisar") -> Analisar | U24: =1+U23 -> 16 | V24: 2
A25: =A24+1 -> 22 | B25: =B24+1 -> 6 | C25: EQUIPE PRÓPRIA |FSA | D25: Ryan Gomes Calazans | E25: =VLOOKUP(D25,[1]Colaboradores!$A$2:$D$65,4,0) -> 45231 | F25: =_xlfn.DAYS($E$1,E25)/30 -> 30.366667 | G25: 23 | H25: 21 | I25: 3 | K25: =G25/12 -> 1.9166667 | L25: =H25/12 -> 1.75 | M25: =I25/3 -> 1 | N25: =VLOOKUP(F25,$U$8:$V$94,2) -> 2 | P25: =IF(M25>=N25,"OK","Analisar") -> Analisar | U25: =1+U24 -> 17 | V25: 2
A26: =A25+1 -> 23 | B26: =B25+1 -> 7 | C26: EQUIPE PRÓPRIA |FSA | D26: MARIA DAIANA DA SILVA BRANDAO | E26: =VLOOKUP(D26,[1]Colaboradores!$A$2:$D$65,4,0) -> 45902 | F26: =_xlfn.DAYS($E$1,E26)/30 -> 8 | H26: 4 | I26: 2 | K26: =G26/12 -> 0 | L26: =H26/12 -> 0.33333333 | M26: =I26/3 -> 0.66666667 | N26: =VLOOKUP(F26,$U$8:$V$94,2) -> 1.66 | P26: =IF(M26>=N26,"OK","Analisar") -> Analisar | U26: =1+U25 -> 18 | V26: 2
A27: =A26+1 -> 24 | B27: =B26+1 -> 8 | C27: EQUIPE PRÓPRIA |FSA | D27: SAMARA FEITOSA VALADARES GENEROSO | E27: =VLOOKUP(D27,[1]Colaboradores!$A$2:$D$65,4,0) -> 21/05/2025 | F27: =_xlfn.DAYS($E$1,E27)/30 -> 11.466667 | H27: 8 | K27: =G27/12 -> 0 | L27: =H27/12 -> 0.66666667 | M27: =I27/3 -> 0 | N27: =VLOOKUP(F27,$U$8:$V$94,2) -> 2 | P27: =IF(M27>=N27,"OK","Analisar") -> Analisar | U27: =1+U26 -> 19 | V27: 2
A28: =A27+1 -> 25 | B28: =B27+1 -> 9 | C28: EQUIPE PRÓPRIA |FSA | D28: Valmir Santana dos Santos | E28: =VLOOKUP(D28,[1]Colaboradores!$A$2:$D$65,4,0) -> 18/03/2026 | F28: =_xlfn.DAYS($E$1,E28)/30 -> 1.4333333 | N28: =VLOOKUP(F28,$U$8:$V$94,2) -> 0.66 | P28: =IF(M28>=N28,"OK","Analisar") -> Analisar | U28: =1+U27 -> 20 | V28: 2
A29: =A28+1 -> 26 | B29: =B28+1 -> 10 | C29: EQUIPE PRÓPRIA |FSA | D29: MURIELLY DE SOUSA SANTOS | E29: =VLOOKUP(D29,[1]Colaboradores!$A$2:$D$65,4,0) -> 18/03/2026 | F29: =_xlfn.DAYS($E$1,E29)/30 -> 1.4333333 | N29: =VLOOKUP(F29,$U$8:$V$94,2) -> 0.66 | P29: =IF(M29>=N29,"OK","Analisar") -> Analisar | U29: =1+U28 -> 21 | V29: 2
A30: =A29+1 -> 27 | B30: =B29+1 -> 11 | C30: EQUIPE PRÓPRIA |FSA | D30: NATÁLIA NOGUEIRA AGUIAR | E30: =VLOOKUP(D30,[1]Colaboradores!$A$2:$D$65,4,0) -> 46118 | F30: =_xlfn.DAYS($E$1,E30)/30 -> 0.8 | N30: =VLOOKUP(F30,$U$8:$V$94,2) -> 0.66 | P30: =IF(M30>=N30,"OK","Analisar") -> Analisar | U30: =1+U29 -> 22 | V30: 2
C31: EQUIPE PRÓPRIA |FSA | D31: LEONARD LUIS MOGENA PEREZ - CLT | E31: =VLOOKUP(D31,[1]Colaboradores!$A$2:$D$65,4,0) -> #N/A | F31: Desligados | H31: 9 | I31: 1 | K31: =G31/12 -> 0 | L31: =H31/12 -> 0.75 | M31: =I31/3 -> 0.33333333 | N31: =VLOOKUP(F31,$U$8:$V$94,2) -> #N/A | P31: Desligado | U31: =1+U30 -> 23 | V31: 2
A32: =A30+1 -> 28 | B32: 1 | C32: CANAL VIRTUAL 1 | D32: MARIA EDUARDA VIEIRA DAMASCENO | E32: =VLOOKUP(D32,[1]Colaboradores!$A$2:$D$65,4,0) -> 45384 | F32: =_xlfn.DAYS($E$1,E32)/30 -> 25.266667 | H32: 15 | I32: 7 | K32: =G32/12 -> 0 | L32: =H32/12 -> 1.25 | M32: =I32/3 -> 2.3333333 | N32: =VLOOKUP(F32,$U$8:$V$94,2) -> 2 | P32: =IF(M32>=N32,"OK","Analisar") -> OK | U32: =1+U31 -> 24 | V32: 2
A33: =A32+1 -> 29 | B33: =B32+1 -> 2 | C33: CANAL VIRTUAL 1 | D33: Daniel Andrade dos Santos | E33: =VLOOKUP(D33,[1]Colaboradores!$A$2:$D$65,4,0) -> 45566 | F33: =_xlfn.DAYS($E$1,E33)/30 -> 19.2 | G33: 2 | H33: 28 | I33: 3 | K33: =G33/12 -> 0.16666667 | L33: =H33/12 -> 2.3333333 | M33: =I33/3 -> 1 | N33: =VLOOKUP(F33,$U$8:$V$94,2) -> 2 | P33: =IF(M33>=N33,"OK","Analisar") -> Analisar | U33: =1+U32 -> 25 | V33: 2
A34: =A33+1 -> 30 | B34: =B33+1 -> 3 | C34: CANAL VIRTUAL 1 | D34: LUCAS DE SOUZA RODRIGUES | E34: =VLOOKUP(D34,[1]Colaboradores!$A$2:$D$65,4,0) -> 46028 | F34: =_xlfn.DAYS($E$1,E34)/30 -> 3.8 | I34: 2 | K34: =G34/12 -> 0 | L34: =H34/12 -> 0 | M34: =I34/3 -> 0.66666667 | N34: =VLOOKUP(F34,$U$8:$V$94,2) -> 0.66 | P34: =IF(M34>=N34,"OK","Analisar") -> OK | U34: =1+U33 -> 26 | V34: 2
A35: =A34+1 -> 31 | B35: =B34+1 -> 4 | C35: CANAL VIRTUAL 1 | D35: CAIO BRENDON LOPES MARTINS | E35: =VLOOKUP(D35,[1]Colaboradores!$A$2:$D$65,4,0) -> 21/07/2025 | F35: =_xlfn.DAYS($E$1,E35)/30 -> 9.4333333 | H35: 2 | I35: 1 | K35: =G35/12 -> 0 | L35: =H35/12 -> 0.16666667 | M35: =I35/3 -> 0.33333333 | N35: =VLOOKUP(F35,$U$8:$V$94,2) -> 1.66 | P35: =IF(M35>=N35,"OK","Analisar") -> Analisar | U35: =1+U34 -> 27 | V35: 2
A36: =A35+1 -> 32 | B36: =B35+1 -> 5 | C36: CANAL VIRTUAL 1 | D36: LUCAS RAMOS DA VICTÓRIA | E36: =VLOOKUP(D36,[1]Colaboradores!$A$2:$D$65,4,0) -> 46118 | F36: =_xlfn.DAYS($E$1,E36)/30 -> 0.8 | N36: =VLOOKUP(F36,$U$8:$V$94,2) -> 0.66 | P36: =IF(M36>=N36,"OK","Analisar") -> Analisar | U36: =1+U35 -> 28 | V36: 2
A37: =A36+1 -> 33 | B37: =B36+1 -> 6 | C37: CANAL VIRTUAL 1 | D37: MARTA ANASTACIO NERES | E37: =VLOOKUP(D37,[1]Colaboradores!$A$2:$D$65,4,0) -> 21/12/2023 | F37: =_xlfn.DAYS($E$1,E37)/30 -> 28.7 | N37: =VLOOKUP(F37,$U$8:$V$94,2) -> 2 | P37: =IF(M37>=N37,"OK","Analisar") -> Analisar | U37: =1+U36 -> 29 | V37: 2
A38: =A37+1 -> 34 | B38: =B37+1 -> 7 | C38: CANAL VIRTUAL 1 | D38: LUIS RAFAEL DO ROSARIO | E38: =VLOOKUP(D38,[1]Colaboradores!$A$2:$D$65,4,0) -> 23/06/2025 | F38: =_xlfn.DAYS($E$1,E38)/30 -> 10.366667 | H38: 3 | K38: =G38/12 -> 0 | L38: =H38/12 -> 0.25 | M38: =I38/3 -> 0 | N38: =VLOOKUP(F38,$U$8:$V$94,2) -> 2 | P38: =IF(M38>=N38,"OK","Analisar") -> Analisar | U38: =1+U37 -> 30 | V38: 2
A39: =A38+1 -> 35 | B39: 1 | C39: =VLOOKUP(D45,dinamica!A:B,2,0) -> CANAL VIRTUAL 2 | D39: LETICIA SANTOS DA SILVA | E39: =VLOOKUP(D39,[1]Colaboradores!$A$2:$D$65,4,0) -> 18/11/2025 | F39: =_xlfn.DAYS($E$1,E39)/30 -> 5.4333333 | I39: 4 | K39: =G39/12 -> 0 | L39: =H39/12 -> 0 | M39: =I39/3 -> 1.3333333 | N39: =VLOOKUP(F39,$U$8:$V$94,2) -> 1.33 | P39: =IF(M39>=N39,"OK","Analisar") -> OK | U39: =1+U38 -> 31 | V39: 2
A40: =A39+1 -> 36 | B40: =B39+1 -> 2 | C40: CANAL VIRTUAL 2 | D40: SANDRA SANTANA DOS SANTOS | E40: =VLOOKUP(D40,[1]Colaboradores!$A$2:$D$65,4,0) -> 45141 | F40: =_xlfn.DAYS($E$1,E40)/30 -> 33.366667 | G40: 1 | H40: 16 | I40: 2 | K40: =G40/12 -> 0.083333333 | L40: =H40/12 -> 1.3333333 | M40: =I40/3 -> 0.66666667 | N40: =VLOOKUP(F40,$U$8:$V$94,2) -> 2 | P40: =IF(M40>=N40,"OK","Analisar") -> Analisar | U40: =1+U39 -> 32 | V40: 2
A41: =A40+1 -> 37 | B41: =B40+1 -> 3 | C41: CANAL VIRTUAL 2 | D41: Lucas Braga de Souza Oliveira | E41: =VLOOKUP(D41,[1]Colaboradores!$A$2:$D$65,4,0) -> 46076 | F41: =_xlfn.DAYS($E$1,E41)/30 -> 2.2 | I41: 1 | K41: =G41/12 -> 0 | L41: =H41/12 -> 0 | M41: =I41/3 -> 0.33333333 | N41: =VLOOKUP(F41,$U$8:$V$94,2) -> 0.66 | P41: =IF(M41>=N41,"OK","Analisar") -> Analisar | U41: =1+U40 -> 33 | V41: 2
A42: =A41+1 -> 38 | B42: =B41+1 -> 4 | C42: CANAL VIRTUAL 2 | D42: ALEXANDRE RABELLO BARBOSA | E42: =VLOOKUP(D42,[1]Colaboradores!$A$2:$D$65,4,0) -> 18/03/2026 | F42: =_xlfn.DAYS($E$1,E42)/30 -> 1.4333333 | N42: =VLOOKUP(F42,$U$8:$V$94,2) -> 0.66 | P42: =IF(M42>=N42,"OK","Analisar") -> Analisar | U42: =1+U41 -> 34 | V42: 2
A43: =A42+1 -> 39 | B43: =B42+1 -> 5 | C43: CANAL VIRTUAL 2 | D43: BRENDA MONICA DOS SANTOS | E43: =VLOOKUP(D43,[1]Colaboradores!$A$2:$D$65,4,0) -> 46043 | F43: =_xlfn.DAYS($E$1,E43)/30 -> 3.3 | N43: =VLOOKUP(F43,$U$8:$V$94,2) -> 0.66 | P43: =IF(M43>=N43,"OK","Analisar") -> Analisar | U43: =1+U42 -> 35 | V43: 2
A44: =A43+1 -> 40 | B44: =B43+1 -> 6 | C44: CANAL VIRTUAL 2 | D44: LUANA SANTANA DOS SANTOS | E44: =VLOOKUP(D44,[1]Colaboradores!$A$2:$D$65,4,0) -> 45294 | F44: =_xlfn.DAYS($E$1,E44)/30 -> 28.266667 | N44: =VLOOKUP(F44,$U$8:$V$94,2) -> 2 | P44: =IF(M44>=N44,"OK","Analisar") -> Analisar | U44: =1+U43 -> 36 | V44: 2
C45: CANAL VIRTUAL 2 | D45: LUCIANO PONTES SILVA JUNIOR - CLT | E45: =VLOOKUP(D45,[1]Colaboradores!$A$2:$D$65,4,0) -> #N/A | F45: Desligados | H45: 1 | I45: 6 | K45: =G45/12 -> 0 | L45: =H45/12 -> 0.083333333 | M45: =I45/3 -> 2 | N45: =VLOOKUP(F45,$U$8:$V$94,2) -> #N/A | P45: Desligado | U45: =1+U44 -> 37 | V45: 2
A46: =A44+1 -> 41 | B46: 1 | C46: EQUIPE PRÓPRIA | AGL | D46: MAYSA GABRIELA GONCALVES OLIVEIRA | E46: =VLOOKUP(D46,[1]Colaboradores!$A$2:$D$65,4,0) -> 44904 | F46: =_xlfn.DAYS($E$1,E46)/30 -> 41.266667 | G46: 13 | H46: 9 | I46: 4 | K46: =G46/12 -> 1.0833333 | L46: =H46/12 -> 0.75 | M46: =I46/3 -> 1.3333333 | N46: =VLOOKUP(F46,$U$8:$V$94,2) -> 2 | P46: =IF(M46>=N46,"OK","Analisar") -> Analisar | U46: =1+U45 -> 38 | V46: 2
A47: =A46+1 -> 42 | B47: =B46+1 -> 2 | C47: EQUIPE PRÓPRIA | AGL | D47: MILENE DE ALMEIDA LIMA | E47: =VLOOKUP(D47,[1]Colaboradores!$A$2:$D$65,4,0) -> 21/07/2025 | F47: =_xlfn.DAYS($E$1,E47)/30 -> 9.4333333 | H47: 3 | I47: 4 | K47: =G47/12 -> 0 | L47: =H47/12 -> 0.25 | M47: =I47/3 -> 1.3333333 | N47: =VLOOKUP(F47,$U$8:$V$94,2) -> 1.66 | P47: =IF(M47>=N47,"OK","Analisar") -> Analisar | U47: =1+U46 -> 39 | V47: 2
A48: =A47+1 -> 43 | B48: =B47+1 -> 3 | C48: EQUIPE PRÓPRIA | AGL | D48: JONATAN CASTRO DA SILVA | E48: =VLOOKUP(D48,[1]Colaboradores!$A$2:$D$65,4,0) -> 45298 | F48: =_xlfn.DAYS($E$1,E48)/30 -> 28.133333 | G48: 8 | H48: 16 | I48: 3 | K48: =G48/12 -> 0.66666667 | L48: =H48/12 -> 1.3333333 | M48: =I48/3 -> 1 | N48: =VLOOKUP(F48,$U$8:$V$94,2) -> 2 | P48: =IF(M48>=N48,"OK","Analisar") -> Analisar | U48: =1+U47 -> 40 | V48: 2
A49: =A48+1 -> 44 | B49: =B48+1 -> 4 | C49: EQUIPE PRÓPRIA | AGL | D49: ARIANI MORAIS DE SOUSA PEREIRA | E49: =VLOOKUP(D49,[1]Colaboradores!$A$2:$D$65,4,0) -> 21/07/2025 | F49: =_xlfn.DAYS($E$1,E49)/30 -> 9.4333333 | H49: 10 | I49: 3 | K49: =G49/12 -> 0 | L49: =H49/12 -> 0.83333333 | M49: =I49/3 -> 1 | N49: =VLOOKUP(F49,$U$8:$V$94,2) -> 1.66 | P49: =IF(M49>=N49,"OK","Analisar") -> Analisar | U49: =1+U48 -> 41 | V49: 2
A50: =A49+1 -> 45 | B50: =B49+1 -> 5 | C50: EQUIPE PRÓPRIA | AGL | D50: YVELISE FERREIRA PINHEIRO | E50: =VLOOKUP(D50,[1]Colaboradores!$A$2:$D$65,4,0) -> 46056 | F50: =_xlfn.DAYS($E$1,E50)/30 -> 2.8666667 | H50: 3 | I50: 1 | K50: =G50/12 -> 0 | L50: =H50/12 -> 0.25 | M50: =I50/3 -> 0.33333333 | N50: =VLOOKUP(F50,$U$8:$V$94,2) -> 0.66 | P50: =IF(M50>=N50,"OK","Analisar") -> Analisar | U50: =1+U49 -> 42 | V50: 2
A51: =A50+1 -> 46 | B51: =B50+1 -> 6 | C51: EQUIPE PRÓPRIA | AGL | D51: REBECA DO ESPIRITO SANTO SOUZA CARVALHO | E51: =VLOOKUP(D51,[1]Colaboradores!$A$2:$D$65,4,0) -> 46056 | F51: =_xlfn.DAYS($E$1,E51)/30 -> 2.8666667 | H51: 7 | K51: =G51/12 -> 0 | L51: =H51/12 -> 0.58333333 | M51: =I51/3 -> 0 | N51: =VLOOKUP(F51,$U$8:$V$94,2) -> 0.66 | P51: =IF(M51>=N51,"OK","Analisar") -> Analisar | U51: =1+U50 -> 43 | V51: 2
A52: =A51+1 -> 47 | B52: =B51+1 -> 7 | C52: EQUIPE PRÓPRIA | AGL | D52: NATASHA LUCILIA BARBOSA | E52: =VLOOKUP(D52,[1]Colaboradores!$A$2:$D$65,4,0) -> 45994 | F52: =_xlfn.DAYS($E$1,E52)/30 -> 4.9333333 | N52: =VLOOKUP(F52,$U$8:$V$94,2) -> 1.33 | P52: =IF(M52>=N52,"OK","Analisar") -> Analisar | U52: =1+U51 -> 44 | V52: 2
B53: 1 | C53: EQUIPE PRÓPRIA 2 | AGL | D53: FABIANE BEZERRA MOREIRA DOS SANTOS | E53: =VLOOKUP(D53,[1]Colaboradores!$A$2:$D$65,4,0) -> 45937 | F53: =_xlfn.DAYS($E$1,E53)/30 -> 6.8333333 | H53: 1 | I53: 5 | K53: =G53/12 -> 0 | L53: =H53/12 -> 0.083333333 | M53: =I53/3 -> 1.6666667 | N53: =VLOOKUP(F53,$U$8:$V$94,2) -> 1.33 | P53: =IF(M53>=N53,"OK","Analisar") -> OK | U53: =1+U52 -> 45 | V53: 2
A54: =+A52+1 -> 48 | B54: =B53+1 -> 2 | C54: EQUIPE PRÓPRIA 2 | AGL | D54: JOAO VITOR BRITO DE ANDRADE | E54: =VLOOKUP(D54,[1]Colaboradores!$A$2:$D$65,4,0) -> 45937 | F54: =_xlfn.DAYS($E$1,E54)/30 -> 6.8333333 | H54: 2 | I54: 4 | K54: =G54/12 -> 0 | L54: =H54/12 -> 0.16666667 | M54: =I54/3 -> 1.3333333 | N54: =VLOOKUP(F54,$U$8:$V$94,2) -> 1.33 | P54: =IF(M54>=N54,"OK","Analisar") -> OK | U54: =1+U53 -> 46 | V54: 2
A55: =A54+1 -> 49 | B55: =B54+1 -> 3 | C55: EQUIPE PRÓPRIA 2 | AGL | D55: WANDERSON ROMERO COELHO DA SILVA | E55: =VLOOKUP(D55,[1]Colaboradores!$A$2:$D$65,4,0) -> 46056 | F55: =_xlfn.DAYS($E$1,E55)/30 -> 2.8666667 | H55: 8 | I55: 4 | K55: =G55/12 -> 0 | L55: =H55/12 -> 0.66666667 | M55: =I55/3 -> 1.3333333 | N55: =VLOOKUP(F55,$U$8:$V$94,2) -> 0.66 | P55: =IF(M55>=N55,"OK","Analisar") -> OK | U55: =1+U54 -> 47 | V55: 2
A56: =A55+1 -> 50 | B56: =B55+1 -> 4 | C56: EQUIPE PRÓPRIA 2 | AGL | D56: JULIANA MARIA DE SOUZA | E56: =VLOOKUP(D56,[1]Colaboradores!$A$2:$D$65,4,0) -> 45965 | F56: =_xlfn.DAYS($E$1,E56)/30 -> 5.9 | I56: 4 | K56: =G56/12 -> 0 | L56: =H56/12 -> 0 | M56: =I56/3 -> 1.3333333 | N56: =VLOOKUP(F56,$U$8:$V$94,2) -> 1.33 | P56: =IF(M56>=N56,"OK","Analisar") -> OK | U56: =1+U55 -> 48 | V56: 2
A57: =A56+1 -> 51 | B57: =B56+1 -> 5 | C57: EQUIPE PRÓPRIA 2 | AGL | D57: REBECA CRISTHINA PIRES DIAS | E57: =VLOOKUP(D57,[1]Colaboradores!$A$2:$D$65,4,0) -> 45965 | F57: =_xlfn.DAYS($E$1,E57)/30 -> 5.9 | I57: 2 | K57: =G57/12 -> 0 | L57: =H57/12 -> 0 | M57: =I57/3 -> 0.66666667 | N57: =VLOOKUP(F57,$U$8:$V$94,2) -> 1.33 | P57: =IF(M57>=N57,"OK","Analisar") -> Analisar | U57: =1+U56 -> 49 | V57: 2
A58: =A57+1 -> 52 | B58: =B57+1 -> 6 | C58: EQUIPE PRÓPRIA 2 | AGL | D58: LUIS ALVES DOS SANTOS DA SILVA ROCHA | E58: =VLOOKUP(D58,[1]Colaboradores!$A$2:$D$65,4,0) -> 23/08/2023 | F58: =_xlfn.DAYS($E$1,E58)/30 -> 32.7 | G58: 13 | H58: 14 | I58: 1 | K58: =G58/12 -> 1.0833333 | L58: =H58/12 -> 1.1666667 | M58: =I58/3 -> 0.33333333 | N58: =VLOOKUP(F58,$U$8:$V$94,2) -> 2 | P58: =IF(M58>=N58,"OK","Analisar") -> Analisar | U58: =1+U57 -> 50 | V58: 2
A59: =A58+1 -> 53 | B59: =B58+1 -> 7 | C59: EQUIPE PRÓPRIA 2 | AGL | D59: ANA LUIZA ENTREPORTES DA COSTA | E59: =VLOOKUP(D59,[1]Colaboradores!$A$2:$D$65,4,0) -> 46099 | F59: =_xlfn.DAYS($E$1,E59)/30 -> 1.4333333 | N59: =VLOOKUP(F59,$U$8:$V$94,2) -> 0.66 | P59: =IF(M59>=N59,"OK","Analisar") -> Analisar | U59: =1+U58 -> 51 | V59: 2
C60: =VLOOKUP(D60,dinamica!A:B,2,0) -> EQUIPE PRÓPRIA 2 | AGL | D60: NATASHA LUCÍLIA BARBOSA - CLT | E60: =VLOOKUP(D60,[1]Colaboradores!$A$2:$D$65,4,0) -> #N/A | F60: Desligados | H60: 1 | I60: 4 | K60: =G60/12 -> 0 | L60: =H60/12 -> 0.083333333 | M60: =I60/3 -> 1.3333333 | P60: =IF(H60>0,IF(I60>5,"OK","Analisar")) -> Analisar | U60: =1+U59 -> 52 | V60: 2
U61: =1+U60 -> 53 | V61: 2
U62: =1+U61 -> 54 | V62: 2
U63: =1+U62 -> 55 | V63: 2
U64: =1+U63 -> 56 | V64: 2
U65: =1+U64 -> 57 | V65: 2
U66: =1+U65 -> 58 | V66: 2
U67: =1+U66 -> 59 | V67: 2
U68: =1+U67 -> 60 | V68: 2
U69: =1+U68 -> 61 | V69: 2
U70: =1+U69 -> 62 | V70: 2
U71: =1+U70 -> 63 | V71: 2
U72: =1+U71 -> 64 | V72: 2
... U94: =1+U93 -> 86 | V94: 2

Sheet 20260409120513_69d7c029a4692
A1: Número | B1: Situação do Repasse | C1: Reserva | D1: Empreendimento | E1: Etapa | F1: Bloco | G1: Unidade | H1: Região | I1: Cliente | J1: Documento do Cliente | K1: Imobiliária | L1: Corretor | M1: Parcela | N1: Contrato Quitado | O1: Contrato Liquidado | P1: Registro Pago | Q1: ITBI Pago | R1: Laudêmio Pago | S1: Recebendo financiamento | T1: Valor previsto | U1: Parcela de conclusão | V1: Saldo devedor | W1: Valor da dívida | X1: Valor do subsídio | Y1: Valor do FGTS | Z1: Valor financiado | AA1: Medição Obra | AB1: % de medição de obra | AC1: Próxima ação | AD1: Nº do contrato | AE1: Contrato | AF1: Nº de matrícula | AG1: Data do registro | AH1: Valor do registro | AI1: Data de Assinatura | AJ1: Data | AK1: Data de contabilização de contrato | AL1: Data do contrato liberado | AM1: Data de unidade liberada | AN1: Data de laudo liberado | AO1: Data de recurso liberado | AP1: Correspondente | AQ1: Usuário correspondente | AR1: Banco | AS1: Agência | AT1: Data de alteração do status | AU1: Data da última alteração | AV1: Situação da Reserva | AW1: Data de Venda | AX1: Código Interno da Reserva | AY1: Valor Contrato | AZ1: Tipo de Venda | BA1: Sigla do Empreendimento | BB1: Contrato Interno | BC1: Nome - Documento do Associado | BD1: Cidade | BE1: Estado | BF1: Telefone | BG1: Endereço | BH1: Cep | BI1: Bairro | BJ1: Email | BK1: Celular | BL1: Renda | BM1: Vencimento da Aprovação | BN1: Grupo de Situações | BO1: Última Mensagem | BP1: Data Última Mensagem | BQ1: Código Interno Unidade | BR1: Código Interno Cliente | BS1: Profissão do Cliente | BT1: Data da Solicitação Da Confissão de Dívida | BU1: Valor do Produto Caixa | BV1: Data de pagamento do produto CAIXA | BW1: Aprovado pela Secretaria de Vendas | BX1: Data Vencimento | Produto Caixa | BY1: N° da Ficha AGEHAB | BZ1: Data da Aprovação da SV | CA1: Data do recebimento do contrato CEF (FISICO ASSINADO) | CB1: Protocolo - ONR | CC1: Data de cadastro da ficha AGEHAB | CD1: Unidade no CV x Unidade contrato CEF conferem? | CE1: AP - PRODUTO | CF1: Data do Envio da Confissão de Divida | CG1: Data da Inconformidade CEHOP | CH1: Tipo de Exceção | CI1: Data do Reenvio CEHOP | CJ1: Data Pagamento do ITBI | CK1: Confissão de Divida Com Exceção | CL1: Data da Assinatura da Confissão de Divida | CM1: Data de Protocolo no Cartório | CN1: Data do Envio da Ficha | CO1: Data Solicitação do Contrato AGEHAB | CP1: Data de Solicitação do ITBI-Prefeitura | CQ1: Excedente de cobrança | CR1: Data Da Aprovação da Ficha AGEHAB | CS1: Data da Validação do Espelho | CT1: Data de validade da avaliação SICAQ | CU1: Data Solicitação Pagamento ITBI-Financeiro | CV1: Data do Recebimento do Contrato AGEHAB | CW1: Data do Espelho Anexado | CX1: Data de Pagamento do Registro | CY1: Aprovado Espelho pela SV | CZ1: Data da Exigência | DA1: FGTS Futuro | DB1: Data de Envio Comitê CEF | DC1: Data do Cumprimento da Exigência | DD1: Data do Kit Registro OK | DE1: Data da Emissão da Minuta CAIXA | DF1: Data de Envio da Solicitação de Garantia | DG1: Protocolo - ITBI | DH1: Obs Garantia | DI1: Data da conformidade da Garantia | DJ1: Data Envio CEHOP | DK1: Data de Envio Contrato AGEHAB e 7LM ao Repasse | DL1: Data da Assinatura Contrato AGEHAB | DM1: Data do Recebimento Contrato AGEHAB e 7LM do Repasse | DN1: Data do Envio do Contrato a AGEHAB | DO1: Data Conformida de CEHOP | DP1: Contrato Validado Pela AGEHAB | DQ1: Data de solicitação de credito ONR | DR1: Fichas com Pendência | DS1: Situação Prenotação | DT1: Título Prenotação | DU1: Título Taxa de Registro | DV1: Situação Taxa Registro | DW1: Data agendamento CEF | DX1: Score Fiador | DY1: AP - ITBI | DZ1: ONR | EA1: Obs Cartório | EB1: Obs Prefeitura | EC1: Origem Clube | ED1: Titulo | EE1: Valor ITBI | EF1: Obs. Sinal | EG1: Situação Sinal | EH1: Obs. AGEHAB | EI1: Obs. Caixa | EJ1: Obs. Fiador | EK1: Probabilidade de assinatura
A2: 3181 | B2: PROCESSO FINALIZADO | C2: 3703 | D2: FSA009 - VILA DOS IPÊS | E2: Única | F2: BLOCO E | G2: 3 | H2: FORMOSA | I2: PEDRO HENRIQUE MARTINS CINTRA | J2: "04813989101" | K2: AUTÔNOMOS | FSA | L2: AMANDA SOUZA PEREIRA | M2: Não | N2: Não | O2: Não | P2: Não | Q2: Não | R2: Não | S2: Não | T2: 152100.93 | U2: 600 | V2: 0 | W2: 116205.93 | X2: 35895 | Y2: 0 | Z2: 152100.93 | AA2: 0 | AB2: 0 | AD2: 8787718825423 | AE2: Contrato Adimplente | AF2: 740228 | AG2: 45365 | AH2: 2705.72 | AI2: 45309 | AJ2: 2004 | AK2: 45294 | AP2: Endy Carvalho Consultoria imobiliária | AT2: 45484 | AU2: 45484 | AV2: VENDA FINALIZADA | AW2: 45279 | AX2: 19519 | AY2: 217100.93 | BA2: FSA09 | BB2: 19519 | BD2: Formosa | BE2: Goiás | BF2: 5562999626525 | BG2: Via 13, QD CH, 240, L. 0, BLOCO G | BH2: 73802419 | BI2: Setor Sul | BJ2: pedrocintra.agro@gmail.com | BL2: 2000 | BM2: 45452 | BQ2: 3095 | BR2: 5375 | BS2: Autônomo(a) | BT2: 45279 | BW2: sim | BY2: MP134432 | BZ2: 45279 | CA2: 45309 | CC2: 45299 | CD2: Sim | CF2: 45279 | CL2: 45295 | CM2: 45324 | CN2: 45299 | CO2: 45323 | CP2: 45315 | CR2: 45301 | CS2: 45295 | CT2: 45452 | CV2: 45338 | CW2: 45295 | CY2: Sim | DB2: 45307 | DD2: 45316 | DE2: 45308 | DF2: 45365 | DI2: 45387 | DJ2: 45293 | DK2: 45338 | DL2: 45344 | DM2: 45357 | DN2: 45383 | DO2: 45295 | DP2: OK
A3: 3182 | B3: PROCESSO FINALIZADO | C3: 3719 | D3: FSA009 - VILA DOS IPÊS | E3: Única | F3: BLOCO Q | G3: 203 | H3: FORMOSA | I3: VANESSA PEREIRA MATEUS | J3: "04311812175" | K3: AUTÔNOMOS | FSA | L3: ALANA RABELO DA COSTA | M3: Não | N3: Não | O3: Não | P3: Não | Q3: Não | R3: Não | S3: Não | T3: 138176.1 | U3: 705 | V3: 0 | W3: 133779.1 | X3: 4397 | Y3: 0 | Z3: 138176.1 | AA3: 0 | AB3: 0 | AD3: 8787718868467 | AE3: Contrato Adimplente | AF3: 74228 | AG3: 45419 | AH3: 2794.99 | AI3: 45324 | AJ3: 2004 | AK3: 45294 | AP3: Endy Carvalho Consultoria imobiliária | AT3: 45484 | AU3: 45484 | AV3: VENDA FINALIZADA | AW3: 45288 | AX3: 19520 | AY3: 195000.4 | BA3: FSA09 | BB3: 19520 | BD3: Formosa | BE3: Goiás | BF3: 556181488530 | BG3: RUA 17, Q 117, L 9 | BH3: 73813240 | BI3: Formosinha | BJ3: vanessapmateus@gmail.com | BL3: 2600 | BM3: 45459 | BQ3: 3291 | BR3: 5376 | BS3: Administrador | BT3: 45289 | BW3: sim | BY3: MP134429 | BZ3: 45289 | CA3: 45324 | CC3: 45295 | CD3: Sim | CF3: 45289 | CG3: 45299 | CI3: 45299 | CL3: 45295 | CM3: 45379 | CN3: 45295 | CO3: 45337 | CR3: 45299 | CS3: 45321 | CT3: 45459 | CU3: 45364 | CV3: 45338 | CW3: 45321 | CY3: Sim | DB3: 45323 | DD3: 45327 | DE3: 45324 | DF3: 45420 | DI3: 45421 | DJ3: 45295 | DK3: 45338 | DL3: 45365 | DM3: 45371 | DN3: 45383 | DO3: 45321 | DP3: OK | EE3: 1972.69
A4: 3183 | B4: PROCESSO FINALIZADO | C4: 3673 | D4: FSA009 - VILA DOS IPÊS | E4: Única | F4: BLOCO D | G4: 301 | H4: FORMOSA | I4: MARCO ANTONIO ALVES DE SOUSA | J4: "08188049123" | K4: AUTÔNOMOS | FSA | L4: VITÓRIA IMÓVEIS IMOB | M4: Não | N4: Não | O4: Não | P4: Não | Q4: Não | R4: Não | S4: Não | T4: 158378.66 | U4: 594 | V4: 0 | W4: 123432.66 | X4: 35470 | Y4: 0 | Z4: 158902.66 | AA4: 0 | AB4: 0 | AD4: 8787718828767 | AE4: Contrato Adimplente | AF4: 74022 | AG4: 45359 | AH4: 2705.72 | AI4: 45314 | AJ4: 2004 | AK4: 45295 | AP4: Endy Carvalho Consultoria imobiliária | AT4: 45484 | AU4: 45484 | AV4: VENDA FINALIZADA | AW4: 45266 | AX4: 19555 | AY4: 205000.02 | BA4: FSA09 | BB4: 19555 | BD4: Formosa | BE4: Goiás | BF4: 556198789745 | BG4: RUA 13 QUADRA 10 LOTE 8 | BH4: 73808305 | BI4: Parque Vila Verde | BJ4: Alvesmarco6161@gmail.com | BL4: 1980 | BM4: 45439 | BQ4: 3085 | BR4: 5377 | BS4: Auxiliar de Serviços Gerais | BT4: 45289 | BW4: sim | BY4: MP134440 | BZ4: 45289 | CA4: 45320 | CC4: 45302 | CD4: Sim | CF4: 45289 | CL4: 45296 | CM4: 45338 | CN4: 45302 | CO4: 45323 | CP4: 45322 | CR4: 45303 | CS4: 45287 | CT4: 45439 | CV4: 45338 | CW4: 45287 | CY4: Sim | DB4: 45307 | DD4: 45327 | DE4: 45309 | DF4: 45360 | DI4: 45363 | DJ4: 45282 | DK4: 45338 | DL4: 45350 | DM4: 45357 | DN4: 45383 | DO4: 45286 | DP4: OK
A5: 3184 | B5: PROCESSO FINALIZADO | C5: 3717 | D5: FSA009 - VILA DOS IPÊS | E5: Única | F5: BLOCO J | G5: 302 | H5: FORMOSA | I5: CRISTIANA DAS DORES BEZERRA | J5: "01989023100" | K5: EQUIPE PRÓPRIA |FSA | L5: TAKADA IMOB | M5: Não | N5: Não | O5: Não | P5: Não | Q5: Não | R5: Não | S5: Não | T5: 149640.3 | U5: 647.7 | V5: 0 | W5: 121181.98 | X5: 28884 | Y5: 0 | Z5: 150065.98 | AA5: 0 | AB5: 0 | AD5: 8787718907039 | AE5: Contrato Adimplente | AF5: 74119 | AG5: 45348 | AH5: 2794.99 | AI5: 45307 | AJ5: 2004 | AK5: 45295 | AP5: Endy Carvalho Consultoria imobiliária | AT5: 45484 | AU5: 45484 | AV5: VENDA FINALIZADA | AW5: 45288 | AX5: 19558 | AY5: 205000.1 | BA5: FSA09 | BB5: 19558 | BD5: Cabeceiras | BE5: Goiás | BF5: 5561999165094 | BG5: Rua Benedito Ribeiro, Q. 10, L. 13A | BH5: 73870000 | BI5: Setor Mariano Machado | BJ5: cristianadores12@gmail.com | BL5: 2158.99 | BM5: 45100 | BQ5: 3174 | BR5: 5380 | BS5: Auxiliar | BT5: 45288 | BW5: sim | BY5: MP13443 | BZ5: 45288 | CA5: 45309 | CC5: 45295 | CD5: Sim | CF5: 45288 | CL5: 45296 | CM5: 45324 | CN5: 45295 | CO5: 45323 | CP5: 45315 | CR5: 45296 | CS5: 45302 | CT5: 45466 | CV5: 45338 | CW5: 45302 | CY5: Sim | DB5: 45303 | DD5: 45306 | DE5: 45306 | DF5: 45349 | DI5: 45350 | DJ5: 45299 | DK5: 45338 | DL5: 45356 | DM5: 45357 | DN5: 45383 | DO5: 45302 | DP5: OK
A6: 3185 | B6: PROCESSO FINALIZADO | C6: 3707 | D6: FSA009 - VILA DOS IPÊS | E6: Única | F6: BLOCO I | G6: 301 | H6: FORMOSA | I6: KAYLANE KAREN FERREIRA DE OLIVEIRA | J6: "09372448133" | K6: AUTÔNOMOS | FSA | L6: MATEUS VITOR DIAS - DESLIGADO | M6: Não | N6: Não | O6: Não | P6: Não | Q6: Não | R6: Não | S6: Não | T6: 151587.93 | U6: 0 | V6: 0 | W6: 116972.93 | X6: 35128 | Y6: 0 | Z6: 152100.93 | AA6: 0 | AB6: 0 | AD6: 8787718868114 | AE6: Contrato Adimplente | AF6: 74102 | AG6: 45348 | AH6: 1794.89 | AI6: 45314 | AJ6: 2004 | AK6: 45295 | AP6: Endy Carvalho Consultoria imobiliária | AT6: 45484 | AU6: 45484 | AV6: VENDA FINALIZADA | AW6: 45280 | AX6: 19557 | AY6: 207000.73 | BA6: FSA09 | BB6: 19557 | BD6: Formosa | BE6: Goiás | BF6: 5561999930487 | BG6: Rua 15, Q. 41, | BH6: 73805216 | BI6: Jardim Oliveira | BJ6: kayllane.karen12@gmail.com | BL6: 2000 | BM6: 45457 | BQ6: 3165 | BR6: 5379 | BS6: Vendedor(a) | BT6: 45288 | BW6: sim | BY6: MP134441 | BZ6: 45288 | CA6: 45320 | CC6: 45302 | CD6: Sim | CF6: 45288 | CL6: 45296 | CM6: 45338 | CN6: 45302 | CO6: 45323 | CP6: 45322 | CR6: 45303 | CS6: 45296 | CT6: 45457 | CV6: 45338 | CW6: 45295 | CY6: Sim | DB6: 45307 | DD6: 45317 | DE6: 45314 | DF6: 45349 | DI6: 45350 | DJ6: 45290 | DK6: 45338 | DL6: 45350 | DM6: 45357 | DN6: 45383 | DO6: 45293 | DP6: OK
A7: 3186 | B7: PROCESSO FINALIZADO | C7: 3724 | D7: FSA007 - VILA DAS HORTÊNSIAS | E7: Etapa | F7: BLOCO B | G7: 3 | H7: FORMOSA | I7: MATHEUS BATISTA BALDOINO | J7: "05194042116" | K7: EQUIPE PRÓPRIA |FSA | L7: FERNANDO FONSECA DE DEUS GALVÃO - CLT- DESLIGADO | M7: Não | N7: Não | O7: Não | P7: Não | Q7: Não | R7: Não | S7: Não | T7: 151620.01 | U7: 600 | V7: 0 | W7: 115858.9 | X7: 35895 | Y7: 0 | Z7: 151753.9 | AA7: 0 | AB7: 0 | AD7: 8787718899834 | AE7: Contrato Adimplente | AF7: 72657 | AG7: 45457 | AH7: 5515.43 | AI7: 45343 | AJ7: 2004 | AK7: 45295 | AP7: Endy Carvalho Consultoria imobiliária | AT7: 46098 | AU7: 46098 | AV7: VENDA FINALIZADA | AW7: 45289 | AX7: 19560 | AY7: 220000 | BA7: FSA07 | BB7: 19560 | BD7: Formosa | BE7: Goiás | BF7: 5561996990087 | BG7: Rua CRUNDWALD COSTA, Q 40 | BH7: 73807840 | BI7: Jardim Califórnia | BJ7: matheusbfsa@hotmail.com | BL7: 2000 | BM7: 45467 | BO7: Bruno Macário (Gestor): Cliente precisou ser reavaliado, pois a agência não aceitou o faturamento da Empresa dele. Com isso, o cliente está aguardando conformidade no momento. Vou retornar a fase anterior. | BP7: 31/01/2024 às 12h32 | BQ7: 854 | BR7: 5382 | BS7: Auxiliar | BT7: 45290 | BW7: sim | BY7: MP139498 | BZ7: 45290 | CA7: 45341 | CC7: 45295 | CD7: Sim | CF7: 45290 | CG7: 45323 | CI7: 45324 | CL7: 45296 | CM7: 45358 | CN7: 45295 | CO7: 45352 | CR7: 45296 | CS7: 45330 | CT7: 45467 | CV7: 45364 | CW7: 45330 | CY7: Sim | DD7: 45300 | DF7: 45457 | DI7: 45460 | DJ7: 45295 | DK7: 45364 | DL7: 45463 | DM7: 45502 | DN7: 46057 | DP7: 46057
A8: 3187 | B8: PROCESSO FINALIZADO | C8: 3714 | D8: AGL028 - VILA DO CERRADO | E8: ETAPA 01 | F8: BLOCO A | G8: 304 | H8: ÁGUAS LINDAS | I8: GIZELLA FERREIRA DOS SANTOS MOREIRA | J8: "73032913187" | K8: EQUIPE PRÓPRIA | AGL | L8: MAYSA GABRIELA GONÇALVES OLIVEIRA - CLT | M8: Não | N8: Não | O8: Não | P8: Sim | Q8: Sim | R8: Não | S8: Não | T8: 159215.6 | U8: 544.5 | V8: 0 | W8: 111109.23 | X8: 47654 | Y8: 0.01 | Z8: 158763.24 | AA8: 0 | AB8: 0 | AE8: Contrato Adimplente | AF8: 96022 | AG8: 45316 | AH8: 2740.25 | AI8: 45303 | AJ8: 2004 | AK8: 45295 | AP8: Endy Carvalho Consultoria imobiliária | AT8: 45653 | AU8: 45744 | AV8: VENDA FINALIZADA | AW8: 45287 | AX8: 19559 | AY8: 203222.55 | BA8: AGL28 | BB8: 19559 | BD8: Águas Lindas de Goiás | BE8: Goiás | BF8: 5561998773302 | BG8: Q C-08 L 04 | BH8: 72910000 | BI8: MANSOES VILLAGE | BJ8: GIZELINHAMARIA.MOREIRA@GMAIL.COM | BL8: 1815 | BM8: 45460 | BQ8: 2712 | BR8: 5381 | BS8: Servente | BT8: 45287 | BU8: 500 | BV8: 45310 | BX8: 45315 | BY8: MP129681 | BZ8: 45287 | CA8: 45306 | CC8: 45296 | CD8: Sim | CF8: 45287 | CG8: 45295 | CI8: 45295 | CJ8: 45307 | CL8: 45296 | CM8: 45308 | CN8: 45296 | CO8: 45323 | CP8: 45306 | CR8: 45299 | CS8: 45296 | CU8: 45307 | CV8: 45329 | CW8: 45296 | CY8: Sim | DD8: 45289 | DF8: 45317 | DI8: 45322 | DJ8: 45320 | DK8: 45329 | DL8: 45339 | DM8: 45345 | DN8: 45624 | DO8: 45296 | DP8: 45624 | EE8: 4029.63
A9: 3188 | B9: PROCESSO FINALIZADO | C9: 3698 | D9: AGL028 - VILA DO CERRADO | E9: ETAPA 01 | F9: BLOCO U | G9: 304 | H9: ÁGUAS LINDAS | I9: IGOR OLIVEIRA MAIA | J9: "06154176120" | K9: EQUIPE PRÓPRIA | AGL | L9: MAYSA GABRIELA GONÇALVES OLIVEIRA - CLT | M9: Não | N9: Não | O9: Não | P9: Sim | Q9: Sim | R9: Não | S9: Não | T9: 155762.32 | U9: 593.87 | V9: 79827.04 | W9: 115493.34 | X9: 39840 | Y9: 0 | Z9: 155333.34 | AA9: 0 | AB9: 0 | AD9: 8787718888166 | AE9: Contrato Adimplente | AF9: 96342 | AG9: 45316 | AH9: 2740.25 | AI9: 45302 | AJ9: 2004 | AK9: 45295 | AP9: Endy Carvalho Consultoria imobiliária | AT9: 45653 | AU9: 45744 | AV9: VENDA FINALIZADA | AW9: 45276 | AX9: 19556 | AY9: 197333.34 | BA9: AGL28 | BB9: 19556 | BD9: Águas Lindas de Goiás | BE9: Goiás | BF9: 5561994159998 | BG9: CHAC 24 QUADRA Q | BH9: 72910000 | BI9: SETOR COIMBRA CHACARA | BJ9: Igorr11@live.com | BL9: 1979.6 | BM9: 45432 | BQ9: 3053 | BR9: 5378 | BS9: Atendente | BT9: 45276 | BU9: 501.6 | BV9: 45303 | BX9: 45307 | BY9: MP129682 | BZ9: 45276 | CA9: 45303 | CC9: 45296 | CD9: Sim | CF9: 45276 | CG9: 45295 | CJ9: 45307 | CL9: 45296 | CM9: 45308 | CN9: 45296 | CO9: 45323 | CP9: 45306 | CR9: 45299 | CS9: 45296 | CU9: 45307 | CV9: 45329 | CW9: 45295 | CY9: Sim | DD9: 45293 | DF9: 45317 | DI9: 45322 | DJ9: 45294 | DK9: 45329 | DL9: 45334 | DM9: 45345 | DN9: 45624 | DO9: 45295 | DP9: 45624 | EE9: 3981.32
A10: 3189 | B10: PROCESSO FINALIZADO | C10: 3711 | D10: AGL028 - VILA DO CERRADO | E10: ETAPA 01 | F10: BLOCO C | G10: 204 | H10: ÁGUAS LINDAS | I10: SARA DE JESUS GONCALVES | J10: "06955895125" | K10: EQUIPE PRÓPRIA | AGL | L10: JOSUÉ GOMES DE SOUZA | M10: Não | N10: Não | O10: Não | P10: Sim | Q10: Sim | R10: Não | S10: Não | T10: 135725.53 | U10: 610.57 | V10: 0 | W10: 115800 | X10: 19790 | Y10: 3248 | Z10: 138838 | AA10: 0 | AB10: 0 | AD10: 8787718856361 | AE10: Contrato Adimplente | AF10: 96050 | AG10: 45362 | AH10: 2740.25 | AI10: 45343 | AJ10: 2004 | AK10: 45299 | AP10: Endy Carvalho Consultoria imobiliária | AT10: 45653 | AU10: 45744 | AV10: VENDA FINALIZADA | AW10: 45280 | AX10: 19639 | AY10: 190000.33 | BA10: AGL28 | BB10: 19639 | BD10: Águas Lindas de Goiás | BE10: Goiás | BF10: 5561999798938 | BG10: RUA 11 -A Q 79 BLOCO 16 LT 10 CONJUNTO A | BH10: 72910000 | BI10: SETOR 12 | BJ10: sj24136@gmail.com | BL10: 2481.3 | BO10: Gledson Carlos da Silva leandro (Gestor): Aguardando finalização do distrato de contrato de FI anteriormente assinado. | BP10: 17/01/2024 às 11h37 | BQ10: 2733 | BR10: 1228 | BS10: Auxiliar | BT10: 45280 | BU10: 500 | BV10: 45344 | BX10: 45350 | BY10: MP129683 | BZ10: 45280 | CA10: 45349 | CC10: 45299 | CD10: Sim | CF10: 45280 | CG10: 45338 | CI10: 45338 | CJ10: 45356 | CL10: 45299 | CM10: 45357 | CN10: 45299 | CO10: 45352 | CP10: 45349 | CR10: 45299 | CS10: 45341 | CU10: 45349 | CV10: 45363 | CW10: 45341 | CX10: 45359 | CY10: Sim | DD10: 45297 | DF10: 45363 | DI10: 45364 | DJ10: 45316 | DK10: 45364 | DL10: 45379 | DM10: 45386 | DN10: 45624 | DO10: 45341 | DP10: 45624 | EE10: 3981.32
A11: 3190 | B11: PROCESSO FINALIZADO | C11: 3723 | D11: FSA009 - VILA DOS IPÊS | E11: Única | F11: BLOCO A | G11: 202 | H11: FORMOSA | I11: JOÃO PAULO PIERDONA | J11: "06384149117" | K11: AUTÔNOMOS | FSA | L11: BRUNO SOARES BEZERRA - PARCEIRO | M11: Não | N11: Não | O11: Não | P11: Não | Q11: Não | R11: Não | S11: Não | T11: 164200 | U11: 1016.14 | V11: 0 | W11: 161635 | X11: 2565 | Y11: 0 | Z11: 164200 | AA11: 0 | AB11: 0 | AD11: 8787718908159 | AE11: Contrato Adimplente | AF11: 73971 | AG11: 45344 | AH11: 3171.57 | AI11: 45310 | AJ11: 2004 | AK11: 45299 | AP11: Endy Carvalho Consultoria imobiliária | AT11: 45484 | AU11: 45484 | AV11: VENDA FINALIZADA | AW11: 45289 | AX11: 19646 | AY11: 213119.02 | BA11: FSA09 | BB11: 19646 | BD11: Formosa | BE11: Goiás | BF11: 5561999678206 | BG11: Rua Visconde de Porto Seguro | BH11: 73801010 | BI11: Centro | BJ11: joaopaulopierdona@hotmail.com | BL11: 3432 | BM11: 45454 | BQ11: 3034 | BR11: 364 | BS11: Motorista | BT11: 45289 | BW11: sim | BY11: MP134431 | BZ11: 45289 | CA11: 45313 | CC11: 45299 | CD11: Sim | CF11: 45289 | CL11: 45300 | CM11: 45329 | CN11: 45299 | CO11: 45323 | CP11: 45315 | CR11: 45299 | CS11: 45307 | CT11: 45453 | CV11: 45338 | CW11: 45307 | CY11: Sim | DB11: 45307 | DD11: 45321 | DE11: 45309 | DF11: 45348 | DI11: 45350 | DJ11: 45303 | DK11: 45338 | DL11: 45366 | DM11: 45379 | DN11: 45383 | DO11: 45306 | DP11: OK
A12: 3191 | B12: PROCESSO FINALIZADO | C12: 3726 | D12: AGL028 - VILA DO CERRADO | E12: ETAPA 02 | F12: BLOCO T | G12: 203 | H12: ÁGUAS LINDAS | I12: THEOALBERTO JEFERSON VILA NOVA LIMBERG | J12: "02310779121" | K12: CANAL VIRTUAL | L12: JÉSSICA NOGUEIRA DE SOUSA - CLT | M12: Não | N12: Não | O12: Não | P12: Sim | Q12: Sim | R12: Não | S12: Não | T12: 132578.74 | U12: 536.07 | V12: 0 | W12: 100417.74 | X12: 30883 | Y12: 0 | Z12: 131300.74 | AA12: 0 | AB12: 0 | AD12: 8787718918421 | AE12: Contrato Adimplente | AG12: 45330 | AH12: 2740.25 | AI12: 45317 | AJ12: 2004 | AK12: 45299 | AP12: Endy Carvalho Consultoria imobiliária | AT12: 45741 | AU12: 45741 | AV12: VENDA FINALIZADA | AW12: 45290 | AX12: 19640 | AY12: 185000.86 | BA12: AGL28 | BB12: 19640 | BD12: Ceilândia | BE12: Distrito Federal | BF12: 5561993093348 | BG12: QNP 28 CJ Z | BH12: 72235824 | BI12: CEILANDIA SUL | BJ12: th.limberg22@gmail.com | BL12: 2144.29 | BQ12: 3031 | BR12: 5383 | BS12: Operador de Loja | BT12: 45310 | BU12: 500 | BV12: 45320 | BW12: sim | BX12: 45324 | BY12: MP129807 | BZ12: 45310 | CA12: 45320 | CC12: 45299 | CD12: Sim | CF12: 45310 | CG12: 45393 | CJ12: 45322 | CL12: 45313 | CM12: 45324 | CN12: 45299 | CO12: 45323 | CP12: 45320 | CR12: 45302 | CS12: 45303 | CU12: 45320 | CV12: 45329 | CW12: 45303 | CY12: Sim | DD12: 45297 | DF12: 45331 | DI12: 45338 | DJ12: 45299 | DK12: 45329 | DL12: 45332 | DM12: 45345 | DN12: 45548 | DO12: 45302 | DP12: 45548 | EE12: 3981.32
A13: 3192 | B13: PROCESSO FINALIZADO | C13: 3728 | D13: FSA009 - VILA DOS IPÊS | E13: Única | F13: BLOCO K | G13: 302 | H13: FORMOSA | I13: ALINE DE JESUS | J13: "05550067196" | K13: EQUIPE PRÓPRIA |FSA | L13: GABRIEL DO NASCIMENTO DIAS - CLT | M13: Não | N13: Não | O13: Não | P13: Não | Q13: Não | R13: Não | S13: Não | T13: 158808.28 | U13: 600 | V13: 0 | W13: 124715.28 | X13: 34606 | Y13: 0 | Z13: 159321.28 | AA13: 0 | AB13: 0 | AD13: 8787718917484 | AE13: Contrato Adimplente | AF13: 74135 | AG13: 45348 | AH13: 2794.99 | AI13: 45313 | AJ13: 2004 | AK13: 45299 | AP13: Endy Carvalho Consultoria imobiliária | AT13: 45484 | AU13: 45484 | AV13: VENDA FINALIZADA | AW13: 45300 | AX13: 19647 | AY13: 212608.44 | BA13: FSA09 | BB13: 19647 | BD13: Formosa | BE13: Goiás | BF13: 5561999121003 | BG13: Rua 29, Q. 03, | BH13: 73802025 | BI13: Setor Bosque | BJ13: lnk_00@hotmail.com | BL13: 2000 | BM13: 45471 | BQ13: 3198 | BR13: 5386 | BS13: Auxiliar | BT13: 45293 | BW13: sim | BY13: MP134433 | BZ13: 45293 | CA13: 45313 | CC13: 45299 | CD13: Sim | CF13: 45293 | CL13: 45300 | CM13: 45329 | CN13: 45299 | CO13: 45323 | CR13: 45301 | CS13: 45302 | CT13: 45468 | CV13: 45338 | CW13: 45302 | CY13: Sim | DB13: 45307 | DD13: 45329 | DE13: 45309 | DF13: 45349 | DI13: 45350 | DJ13: 45299 | DK13: 45338 | DL13: 45349 | DM13: 45357 | DN13: 45383 | DO13: 45302 | DP13: OK
A14: 3193 | B14: PROCESSO FINALIZADO | C14: 3729 | D14: FSA009 - VILA DOS IPÊS | E14: Única | F14: BLOCO G | G14: 204 | H14: FORMOSA | I14: CAIO VITOR SILVERIO SANTANA | J14: "05141790150" | K14: AUTÔNOMOS | FSA | L14: ANA CAROLINA FERREIRA DE ANDRADE - CARLOS ANDRADE IMOBILIÁRIA | M14: Não | N14: Não | O14: Não | P14: Não | Q14: Não | R14: Não | S14: Não | T14: 151313.36 | U14: 1051.03 | V14: 0 | W14: 149503.36 | X14: 1811 | Y14: 0 | Z14: 151314.36 | AA14: 0 | AB14: 0 | AD14: 8787718918146 | AE14: Contrato Adimplente | AF14: 74069 | AG14: 45362 | AH14: 3207 | AI14: 45308 | AJ14: 2004 | AK14: 45299 | AP14: Endy Carvalho Consultoria imobiliária | AT14: 45484 | AU14: 45484 | AV14: VENDA FINALIZADA | AW14: 45300 | AX14: 19648 | AY14: 205113.64 | BA14: FSA09 | BB14: 19648 | BD14: Formosa | BE14: Goiás | BF14: 5561996341087 | BG14: Rua 7, Q.44, L. 2A | BH14: 73813420 | BI14: Formosinha | BJ14: caio.silver.98@gmail.com | BL14: 4204.17 | BM14: 45476 | BQ14: 3125 | BR14: 5387 | BS14: Auxiliar | BT14: 45295 | BW14: sim | BY14: MP134435 | BZ14: 45295 | CA14: 45309 | CC14: 45299 | CD14: Sim | CF14: 45295 | CJ14: 45323 | CL14: 45300 | CM14: 45324 | CN14: 45299 | CO14: 45323 | CP14: 45315 | CR14: 45301 | CS14: 45303 | CT14: 45474 | CV14: 45338 | CW14: 45303 | CY14: Sim | DB14: 45303 | DD14: 45308 | DE14: 45306 | DF14: 45361 | DI14: 45363 | DJ14: 45299 | DK14: 45338 | DL14: 45348 | DM14: 45357 | DN14: 45383 | DO14: 45302 | DP14: OK
A15: 3194 | B15: PROCESSO FINALIZADO | C15: 3730 | D15: FSA009 - VILA DOS IPÊS | E15: Única | F15: BLOCO H | G15: 101 | H15: FORMOSA | I15: KARISME RODRIGUES DE SOUSA | J15: "05443756109" | K15: AUTÔNOMOS | FSA | L15: JANDER JACKSON VENANCIO DE SOUZA- DESLIGADO | M15: Não | N15: Não | O15: Não | P15: Não | Q15: Não | R15: Não | S15: Não | T15: 156350.43 | U15: 710.16 | V15: 0 | W15: 134782.43 | X15: 21890 | Y15: 0 | Z15: 156672.43 | AA15: 0 | AB15: 0 | AD15: 8787718918723 | AE15: Contrato Adimplente | AF15: 74078 | AG15: 45345 | AH15: 2794.99 | AI15: 45310 | AJ15: 2004 | AK15: 45299 | AP15: Endy Carvalho Consultoria imobiliária | AT15: 45484 | AU15: 45484 | AV15: VENDA FINALIZADA | AW15: 45300 | AX15: 19649 | AY15: 215001.07 | BA15: FSA09 | BB15: 19649 | BD15: Formosa | BE15: Goiás | BF15: 5561996319166 | BG15: Avenida Circular, Q. 47 | BH15: 73805207 | BI15: Jardim Oliveira | BJ15: karinemacedo71@gmail.com | BL15: 2367.21 | BM15: 45473 | BQ15: 3144 | BR15: 5388 | BS15: Auxiliar | BT15: 45309 | BW15: sim | BY15: MP134434 | BZ15: 45309 | CA15: 45313 | CC15: 45299 | CD15: Sim | CF15: 45309 | CL15: 45309 | CM15: 45324 | CN15: 45299 | CO15: 45323 | CP15: 45315 | CR15: 45301 | CS15: 45303 | CT15: 45473 | CV15: 45338 | CW15: 45303 | CY15: Sim | DB15: 45309 | DD15: 45310 | DE15: 45309 | DF15: 45348 | DI15: 45350 | DJ15: 45299 | DK15: 45338 | DL15: 45344 | DM15: 45357 | DN15: 45383 | DO15: 45302 | DP15: OK
A16: 3195 | B16: PROCESSO FINALIZADO | C16: 3732 | D16: AGL028 - VILA DO CERRADO | E16: ETAPA 01 | F16: BLOCO D | G16: 104 | H16: ÁGUAS LINDAS | I16: MARIELLY CRISTINA MACHADO DO NASCIMENTO | J16: "61985243377" | K16: EQUIPE PRÓPRIA | AGL | L16: WELLINGTON ARAUJO - CLT | M16: Não | N16: Não | O16: Não | P16: Sim | Q16: Sim | R16: Não | S16: Não | T16: 155767.38 | U16: 594 | V16: 0 | W16: 115946.38 | X16: 39821 | Y16: 0 | Z16: 155767.38 | AA16: 0 | AB16: 0 | AD16: 8787718918065 | AE16: Contrato Adimplente | AF16: 96062 | AG16: 45316 | AH16: 2740.25 | AI16: 45308 | AJ16: 2004 | AK16: 45299 | AP16: Endy Carvalho Consultoria imobiliária | AT16: 45653 | AU16: 45744 | AV16: VENDA FINALIZADA | AW16: 45300 | AX16: 19650 | AY16: 205767.38 | BA16: AGL28 | BB16: 19650 | BD16: Águas Lindas de Goiás | BE16: Goiás | BF16: 5534984428805 | BG16: Q 45 L 05 CONJUNTO A | BH16: 72910000 | BI16: SETOR 8 | BJ16: mariellycristina627@gmail.com | BL16: 1980 | BM16: 45475 | BQ16: 2756 | BR16: 5389 | BS16: Auxiliar de Serviços Gerais | BT16: 45295 | BU16: 500 | BV16: 45310 | BX16: 45315 | BY16: MP129684 | BZ16: 45295 | CA16: 45309 | CC16: 45299 | CD16: Sim | CF16: 45295 | CJ16: 45310 | CL16: 45300 | CM16: 45313 | CN16: 45299 | CO16: 45323 | CP16: 45309 | CR16: 45300 | CS16: 45303 | CU16: 45309 | CV16: 45329 | CW16: 45303 | CY16: Sim | DB16: 45303 | DD16: 45299 | DF16: 45317 | DI16: 45322 | DJ16: 45299 | DK16: 45329 | DL16: 45458 | DM16: 45629 | DN16: 45624 | DO16: 45302 | DP16: 45624 | EE16: 3981.32
A17: 3196 | B17: PROCESSO FINALIZADO | C17: 3722 | D17: AGL028 - VILA DO CERRADO | E17: ETAPA 01 | F17: BLOCO W | G17: 3 | H17: ÁGUAS LINDAS | I17: RENE TORRE DOS SANTOS | J17: "10235632406" | K17: EQUIPE PRÓPRIA | AGL | L17: JOSUÉ GOMES DE SOUZA | M17: Não | N17: Não | O17: Não | P17: Sim | Q17: Sim | R17: Não | S17: Não | T17: 163541.32 | U17: 579 | V17: 0 | W17: 120260.32 | X17: 43281 | Y17: 0 | Z17: 163541.32 | AA17: 0 | AB17: 0 | AD17: 8787718932513 | AE17: Contrato Adimplente | AG17: 45329 | AH17: 2740.25 | AI17: 45314 | AJ17: 2004 | AK17: 45299 | AP17: Endy Carvalho Consultoria imobiliária | AT17: 45653 | AU17: 45744 | AV17: VENDA FINALIZADA | AW17: 45288 | AX17: 19645 | AY17: 210541.32 | BA17: AGL28 | BB17: 19645 | BD17: Águas Lindas de Goiás | BE17: Goiás | BF17: 5561987308967 | BG17: Quadra 38 02/03 | BH17: 72915099 | BI17: Jardim Brasília | BJ17: renetorre20@hotmail.com | BK17: 558187308967 | BL17: 1930 | BM17: 45467 | BQ17: 3074 | BR17: 5385 | BS17: Tecnico em tecnologia da informação | BT17: 45288 | BU17: 500 | BV17: 45316 | BX17: 45322 | BY17: MP129686 | BZ17: 45288 | CA17: 45320 | CC17: 45300 | CD17: Sim | CF17: 45288 | CG17: 45306 | CJ17: 45322 | CL17: 45300 | CM17: 45324 | CN17: 45300 | CO17: 45323 | CP17: 45320 | CR17: 45300 | CS17: 45313 | CU17: 45320 | CV17: 45329 | CW17: 45313 | CY17: Sim | DD17: 45297 | DF17: 45330 | DI17: 45331 | DJ17: 45303 | DK17: 45330 | DL17: 45336 | DM17: 45345 | DN17: 45624 | DO17: 45313 | DP17: 45624 | EE17: 4165.32
A18: 3197 | B18: PROCESSO FINALIZADO | C18: 3672 | D18: AGL028 - VILA DO CERRADO | E18: ETAPA 01 | F18: BLOCO D | G18: 3 | H18: ÁGUAS LINDAS | I18: ALINE LEIA DA SILVA PENHA | J18: "05079223103" | K18: CANAL VIRTUAL | L18: CRISTIANO SANTOS PEREIRA - CLT | M18: Não | N18: Não | O18: Não | P18: Sim | Q18: Sim | R18: Não | S18: Não | T18: 155918.28 | U18: 558.82 | V18: 0 | W18: 108751.28 | X18: 47104 | Y18: 0 | Z18: 155855.28 | AA18: 0 | AB18: 0 | AD18: 8787718802830 | AE18: Contrato Adimplente | AF18: 96057 | AG18: 45370 | AH18: 2721.61 | AI18: 45337 | AJ18: 2004 | AK18: 45299 | AP18: Endy Carvalho Consultoria imobiliária | AT18: 45652 | AU18: 45744 | AV18: VENDA FINALIZADA | AW18: 45266 | AX18: 19644 | AY18: 205000.2 | BA18: AGL28 | BB18: 19644 | BD18: Águas Lindas de Goiás | BE18: Goiás | BF18: 5561998735384 | BG18: RUA 6 QUADRA 12 | BH18: 72910000 | BI18: JARDIM DA BARRAGEM III | BJ18: aline84nx@gmail.com | BL18: 1862.78 | BM18: 45444 | BO18: Gledson Carlos da Silva leandro (Gestor): Aguardando nada consta de imovel registrado. CEF consta cliente como vendedora de imovel. | BP18: 17/01/2024 às 11h36 | BQ18: 2751 | BR18: 5384 | BS18: Tecnico em Enfermagem | BT18: 45296 | BU18: 500 | BV18: 45342 | BX18: 45344 | BY18: MP129685 | BZ18: 45296 | CA18: 45342 | CC18: 45300 | CD18: Sim | CF18: 45296 | CG18: 45330 | CI18: 45328 | CJ18: 45344 | CL18: 45300 | CM18: 45345 | CN18: 45300 | CO18: 45352 | CP18: 45342 | CQ18: 2721.61 | CR18: 45300 | CS18: 45330 | CU18: 45342 | CV18: 45363 | CW18: 45330 | CX18: 45369 | CY18: Sim | DD18: 45275 | DF18: 45371 | DI18: 45372 | DJ18: 45303 | DK18: 45364 | DL18: 45370 | DM18: 45386 | DN18: 45624 | DO18: 45330 | DP18: 45624 | EE18: 4165.32
A19: 3198 | B19: DISTRATO | C19: 3715 | D19: AGL028 - VILA DO CERRADO | E19: ETAPA 01 | F19: BLOCO G | G19: 104 | H19: ÁGUAS LINDAS | I19: FRANCISCO LISBOA OLINVINDA | J19: "13651653889" | K19: EQUIPE PRÓPRIA | AGL | L19: WELLINGTON ARAUJO - CLT | M19: Não | N19: Não | O19: Não | P19: Não | Q19: Não | R19: Não | S19: Não | T19: 126860.63 | U19: 594 | V19: 0 | W19: 85371 | X19: 41299 | Y19: 0 | Z19: 126670 | AA19: 0 | AB19: 0 | AE19: Contrato Adimplente | AH19: 0 | AK19: 45300 | AP19: Endy Carvalho Consultoria imobiliária | AT19: 45322 | AU19: 45322 | AV19: DISTRATO | AW19: 45287 | AX19: 19661 | AY19: 188897.2 | BA19: AGL28 | BB19: 19661 | BC19: PAULA FERNANDA DE CARVALHO LISBOA - 06009099641 | BD19: Águas Lindas de Goiás | BE19: Goiás | BF19: 5561982891785 | BG19: GLEBA A L 21A | BH19: 72910000 | BI19: LAGO DO DESCOBERTO | BJ19: FRANCISCOLISBOA749@GMAIL.COM | BL19: 1980 | BM19: 45451 | BO19: Gledson Carlos da Silva leandro (Gestor): Cliente sinalizou desistência em razão de não ter fiador. | BP19: 17/01/2024 às 11h36 | BQ19: 2807 | BR19: 5390 | BS19: Psicólogo | BY19: MP129687 | CC19: 45300 | CN19: 45300 | CR19: 45307 | CS19: 45308 | CW19: 45307 | CY19: Sim | DD19: 45288 | DJ19: 45301 | DO19: 45306
A20: 3199 | B20: DISTRATO | C20: 3708 | D20: FSA009 - VILA DOS IPÊS | E20: Única | F20: BLOCO B | G20: 201 | H20: FORMOSA | I20: ANA VITÓRIA FIGUEIREDO FERREIRA | J20: "70842803165" | K20: EQUIPE PRÓPRIA |FSA | L20: NAUANE MARTINS DA SILVA OLIVEIRA - CLT | M20: Não | N20: Não | O20: Não | P20: Não | Q20: Não | R20: Não | S20: Não | T20: 146395.51 | U20: 472.42 | V20: 63604.49 | W20: 91395.51 | X20: 55000 | Y20: 0 | Z20: 146395.51 | AA20: 0 | AB20: 0 | AE20: Contrato Adimplente | AH20: 0 | AK20: 45300 | AP20: Endy Carvalho Consultoria imobiliária | AT20: 45349 | AU20: 45349 | AV20: DISTRATO | AW20: 45280 | AX20: 19729 | AY20: 205000.31 | BA20: FSA09 | BB20: 19729 | BD20: Formosa | BE20: Goiás | BF20: 5561998733299 | BG20: RUA TOPAZIO Q 01 | BH20: 73807805 | BI20: JARDIM CALIFÓRNIA | BJ20: anavitoriaferrefig@gmail.com | BL20: 2600 | BM20: 45460 | BQ20: 3044 | BR20: 5392 | BS20: Caixa | BY20: MP134439 | CC20: 45301 | CG20: 45308 | CN20: 45301 | CR20: 45302 | CT20: 45460 | DD20: 45306 | DJ20: 45302
A21: 3200 | B21: DISTRATO | C21: 3720 | D21: FSA007 - VILA DAS HORTÊNSIAS | E21: Etapa | F21: BLOCO K | G21: 4 | H21: FORMOSA | I21: HILLARY CAMPELO DE JESUS | J21: "06998358105" | K21: AUTÔNOMOS | FSA | L21: JE EMPREENDIMENTOS IMOBILIÁRIOS | M21: Não | N21: Não | O21: Não | P21: Não | Q21: Não | R21: Não | S21: Não | T21: 157375.84 | U21: 625.28 | V21: 0 | W21: 126015.84 | X21: 31360 | Y21: 0 | Z21: 157375.84 | AA21: 0 | AB21: 0 | AE21: Contrato Adimplente | AH21: 0 | AK21: 45300 | AP21: Endy Carvalho Consultoria imobiliária | AT21: 45369 | AU21: 45369 | AV21: DISTRATO | AW21: 45288 | AX21: 19730 | AY21: 215000.09 | BA21: FSA07 | BB21: 19730 | BD21: Formosa | BE21: Goiás | BF21: 5562998612879 | BG21: RUA 12, Q. 11 | BH21: 73808310 | BI21: PARQUE VILA VERDE | BJ21: hillarycampello@gmail.com | BL21: 2084.28 | BM21: 45431 | BQ21: 1005 | BR21: 5393 | BS21: Atendente | BY21: MP139499 | CC21: 45301 | CG21: 45307 | CN21: 45301 | CR21: 45301 | CT21: 45431 | DJ21: 45301
A22: 3201 | B22: PROCESSO FINALIZADO | C22: 3733 | D22: FSA009 - VILA DOS IPÊS | E22: Única | F22: BLOCO O | G22: 203 | H22: FORMOSA | I22: DANILO ALVES PAPA | J22: "01832826120" | K22: AUTÔNOMOS | FSA | L22: CAMILA FERNANDES DA SILVA | M22: Não | N22: Não | O22: Não | P22: Não | Q22: Não | R22: Não | S22: Não | T22: 151467.16 | U22: 480 | V22: 0 | W22: 97797.16 | X22: 53702 | Y22: 0 | Z22: 151499.16 | AA22: 0 | AB22: 0 | AD22: 8787718953740 | AE22: Contrato Adimplente | AF22: 74196 | AG22: 45516 | AH22: 0 | AI22: 45349 | AJ22: 2004 | AK22: 45300 | AP22: Endy Carvalho Consultoria imobiliária | AT22: 45484 | AU22: 45555 | AV22: VENDA FINALIZADA | AW22: 45302 | AX22: 19732 | AY22: 206000.76 | BA22: FSA09 | BB22: 19732 | BD22: Formosa | BE22: Goiás | BF22: 5561996765545 | BG22: Rua São Pedro | BH22: 73807160 | BI22: Setor Nordeste | BJ22: danilo.a.papa@outlook.com | BL22: 1600 | BM22: 45473 | BQ22: 3259 | BR22: 5395 | BS22: Assistente | BT22: 45296 | BW22: sim | BY22: MP134438 | BZ22: 44931 | CA22: 45345 | CC22: 45301 | CD22: Sim | CF22: 45296 | CG22: 45323 | CI22: 45324 | CL22: 45302 | CM22: 45391 | CN22: 45301 | CO22: 45352 | CR22: 45302 | CS22: 45327 | CT22: 45302 | CV22: 45364 | CW22: 45325 | CY22: Sim | DD22: 45355 | DF22: 45553 | DI22: 45554 | DJ22: 45302 | DK22: 45364 | DL22: 45365 | DM22: 45371 | DN22: 45383 | DO22: 45324 | DP22: OK
A23: 3202 | B23: PROCESSO FINALIZADO | C23: 3736 | D23: FSA009 - VILA DOS IPÊS | E23: Única | F23: BLOCO K | G23: 103 | H23: FORMOSA | I23: THAYNÁ DA SILVA LIMA | J23: "08427039182" | K23: EQUIPE PRÓPRIA |FSA | L23: GABRIEL DO NASCIMENTO DIAS - CLT | M23: Não | N23: Não | O23: Não | P23: Não | Q23: Não | R23: Não | S23: Não | T23: 151421.64 | U23: 649.09 | V23: 0 | W23: 122332.64 | X23: 28661 | Y23: 0 | Z23: 150993.64 | AA23: 0 | AB23: 0 | AD23: 8787718944643 | AE23: Contrato Adimplente | AG23: 45386 | AH23: 3559.94 | AI23: 45362 | AJ23: 2004 | AK23: 45300 | AP23: Endy Carvalho Consultoria imobiliária | AT23: 45743 | AU23: 45743 | AV23: VENDA FINALIZADA | AW23: 45302 | AX23: 19733 | AY23: 205221.64 | BA23: FSA09 | BB23: 19733 | BD23: Formosa | BE23: Goiás | BF23: 5561999801092 | BG23: RUA 23 | BH23: 73813350 | BI23: FORMOSINHA | BJ23: Limathaynadasilva2@gmail.com | BL23: 2153.66 | BM23: 45475 | BQ23: 3191 | BR23: 5396 | BS23: Atendente | BT23: 45299 | BW23: sim | BY23: MP134436 | BZ23: 45299 | CA23: 45357 | CC23: 45301 | CD23: Sim | CF23: 45299 | CG23: 45308 | CI23: 45351 | CL23: 45302 | CM23: 45373 | CN23: 45301 | CO23: 45366 | CP23: 45365 | CR23: 45301 | CS23: 45352 | CT23: 45475 | CV23: 45366 | CW23: 45352 | CY23: Sim | DB23: 45352 | DD23: 45303 | DE23: 45357 | DF23: 45386 | DI23: 45387 | DJ23: 45301 | DK23: 45387 | DL23: 45462 | DM23: 45504 | DN23: 45728 | DO23: 45352 | DP23: 45728
A24: 3203 | B24: DISTRATO | C24: 3725 | D24: FSA009 - VILA DOS IPÊS | E24: Única | F24: BLOCO B | G24: 203 | H24: FORMOSA | I24: EDUARDA GAIA LIMA DOS SANTOS | J24: "09884070199" | K24: AUTÔNOMOS | FSA | L24: MILENA BOTELHO DE PAIVA DIAS | M24: Não | N24: Não | O24: Não | P24: Não | Q24: Não | R24: Não | S24: Não | T24: 146950.69 | U24: 475.2 | V24: 0 | W24: 91950.69 | X24: 55000 | Y24: 0 | Z24: 146950.69 | AA24: 0 | AB24: 0 | AE24: Contrato Adimplente | AH24: 0 | AK24: 45301 | AP24: Endy Carvalho Consultoria imobiliária | AT24: 45349 | AU24: 45349 | AV24: DISTRATO | AW24: 45289 | AX24: 19731 | AY24: 200750.69 | BA24: FSA09 | BB24: 19731 | BD24: Formosa | BE24: Goiás | BF24: 5561996383737 | BG24: Rua 24 Q 140 L 09 | BH24: 73813360 | BI24: Formosinha | BJ24: dudahgaia0@gmail.com | BL24: 2350 | BM24: 45461 | BQ24: 3054 | BR24: 5394 | BS24: Atendente | BY24: MP134437 | CC24: 45301 | CF24: 45290 | CG24: 45309 | CL24: 45302 | CN24: 45301 | CR24: 45301 | CT24: 45461 | DJ24: 45303
A25: 3204 | B25: PROCESSO FINALIZADO | C25: 3735 | D25: FSA007 - VILA DAS HORTÊNSIAS | E25: Etapa | F25: BLOCO L | G25: 4 | H25: FORMOSA | I25: GEOVANE DA ROCHA NASCIMENTO | J25: "05108008155" | K25: CANAL VIRTUAL | L25: JÉSSICA NOGUEIRA DE SOUSA - CLT | M25: Não | N25: Não | O25: Não | P25: Não | Q25: Não | R25: Não | S25: Não | T25: 168000 | U25: 750 | V25: 0 | W25: 150447 | X25: 42000 | Y25: 0 | Z25: 192447 | AA25: 0 | AB25: 0 | AD25: 8787718954851 | AE25: Contrato Adimplente | AF25: 72818 | AG25: 45355 | AH25: 3171.57 | AI25: 45316 | AJ25: 2004 | AK25: 45302 | AP25: Endy Carvalho Consultoria imobiliária | AT25: 45749 | AU25: 45888 | AV25: VENDA FINALIZADA | AW25: 45303 | AX25: 19807 | AY25: 218000 | BA25: FSA07 | BB25: 19807 | BD25: Formosa | BE25: Goiás | BF25: 5561999346007 | BG25: AV. FERROVIARIA E Q M | BH25: 73807330 | BI25: SETOR NORDESTE | BJ25: geovanedarochanascimento@gmail.com | BL25: 2800 | BM25: 45477 | BQ25: 837 | BR25: 5397 | BS25: Motorista | BT25: 45299 | BW25: sim | BY25: MP139500 | BZ25: 45299 | CA25: 45320 | CC25: 45302 | CD25: Sim | CF25: 45299 | CJ25: 45334 | CL25: 45303 | CM25: 45345 | CN25: 45302 | CO25: 45323 | CP25: 45322 | CR25: 45308 | CS25: 45309 | CT25: 45477 | CU25: 45327 | CV25: 45338 | CW25: 45308 | CY25: Sim | DB25: 45309 | DD25: 45344 | DE25: 23/01/1024 | DF25: 45355 | DI25: 45356 | DJ25: 45302 | DK25: 45338 | DL25: 45341 | DM25: 45357 | DN25: 45435 | DO25: 45308 | DP25: 45435 | EE25: 2013.84
A26: 3205 | B26: PROCESSO FINALIZADO | C26: 3738 | D26: FSA009 - VILA DOS IPÊS | E26: Única | F26: BLOCO I | G26: 203 | H26: FORMOSA | I26: BIANCA ALVES DOS SANTOS | J26: "04231492107" | K26: EQUIPE PRÓPRIA |FSA | L26: KÁLITA CRISTINE MARTINS FRADE - CLT | M26: Não | N26: Não | O26: Não | P26: Não | Q26: Não | R26: Não | S26: Não | T26: 151967.22 | U26: 660 | V26: 0 | W26: 125034.22 | X26: 26934 | Y26: 0 | Z26: 151968.22 | AA26: 0 | AB26: 0 | AD26: 8787718955173 | AE26: Contrato Adimplente | AF26: 74100 | AG26: 45355 | AH26: 2849.02 | AI26: 45338 | AJ26: 2004 | AK26: 45303 | AP26: Endy Carvalho Consultoria imobiliária | AT26: 45503 | AU26: 45503 | AV26: VENDA FINALIZADA | AW26: 45307 | AX26: 19929 | AY26: 205767.22 | BA26: FSA09 | BB26: 19929 | BD26: Formosa | BE26: Goiás | BF26: 5561996646328 | BG26: RUA 07 QUADRA 18 | BH26: 73805280 | BI26: JARDIM OLIVEIRA | BJ26: biancaalves2001fsa@gmail.com | BL26: 2200 | BM26: 45479 | BQ26: 3166 | BR26: 5398 | BS26: Professor | BT26: 45300 | BW26: sim | BY26: MP134442 | BZ26: 45300 | CA26: 45330 | CC26: 45303 | CD26: Sim | CF26: 45300 | CG26: 45308 | CI26: 45317 | CL26: 45307 | CM26: 45336 | CN26: 45306 | CO26: 45337 | CP26: 45341 | CR26: 45306 | CS26: 45323 | CT26: 45479 | CV26: 45338 | CW26: 45323 | CY26: Sim | DD26: 45336 | DF26: 45355 | DI26: 45357 | DJ26: 45302 | DK26: 45338 | DL26: 45341 | DM26: 45358 | DN26: 45383 | DO26: 45323 | DP26: OK
A27: 3206 | B27: PROCESSO FINALIZADO | C27: 3739 | D27: FSA009 - VILA DOS IPÊS | E27: Única | F27: BLOCO G | G27: 201 | H27: FORMOSA | I27: LORRANE STEFANY DE ARAUJO | J27: "05791544162" | K27: EQUIPE PRÓPRIA |FSA | L27: KÁLITA CRISTINE MARTINS FRADE - CLT | M27: Não | N27: Não | O27: Não | P27: Não | Q27: Não | R27: Não | S27: Não | T27: 161523.69 | U27: 775.27 | V27: 0 | W27: 157026.69 | X27: 48475.31 | Y27: 0 | Z27: 205502 | AA27: 0 | AB27: 0 | AD27: 8787718954967 | AE27: Contrato Adimplente | AF27: 74066 | AG27: 45356 | AH27: 3171.52 | AI27: 45315 | AJ27: 2004 | AK27: 45306 | AP27: Endy Carvalho Consultoria imobiliária | AT27: 45484 | AU27: 45484 | AV27: VENDA FINALIZADA | AW27: 45307 | AX27: 19930 | AY27: 215323.69 | BA27: FSA09 | BB27: 19930 | BD27: Formosa | BE27: Goiás | BF27: 5561998236829 | BG27: AVENIDA FORMOSA QUADRA 46 | BH27: 73813250 | BI27: FORMOSINHA | BJ27: lorranearauj488@gmail.com | BL27: 2584.25 | BM27: 45382 | BQ27: 3124 | BR27: 5399 | BS27: Assistente | BT27: 45302 | BW27: sim | BY27: MP134444 | BZ27: 45302 | CA27: 45320 | CC27: 45307 | CD27: Sim | CF27: 45302 | CL27: 45307 | CM27: 45345 | CN27: 45307 | CO27: 45323 | CP27: 45336 | CR27: 45308 | CS27: 45309 | CT27: 45382 | CV27: 45338 | CW27: 45308 | CY27: Sim | DB27: 45309 | DD27: 45337 | DE27: 45314 | DF27: 45356 | DI27: 45357 | DJ27: 45302 | DK27: 45338 | DL27: 45379 | DM27: 45358 | DN27: 45383 | DO27: 45308 | DP27: OK
A28: 3207 | B28: PROCESSO FINALIZADO | C28: 3740 | D28: FSA009 - VILA DOS IPÊS | E28: Única | F28: BLOCO F | G28: 4 | H28: FORMOSA | I28: ALINE MARIANO DE OLIVEIRA | J28: "03569343146" | K28: AUTÔNOMOS | FSA | L28: ALANA RABELO DA COSTA | M28: Não | N28: Não | O28: Não | P28: Não | Q28: Não | R28: Não | S28: Não | T28: 154934.99 | U28: 693.48 | V28: 0 | W28: 131540.99 | X28: 23921 | Y28: 0 | Z28: 155461.99 | AA28: 0 | AB28: 0 | AD28: 8787718962730 | AE28: Contrato Adimplente | AG28: 45350 | AH28: 3559.97 | AI28: 45329 | AJ28: 2004 | AK28: 45306 | AP28: Endy Carvalho Consultoria imobiliária | AT28: 45503 | AU28: 45503 | AV28: VENDA FINALIZADA | AW28: 45307 | AX28: 19931 | AY28: 225000.6 | BA28: FSA09 | BB28: 19931 | BC28: JANETE MARIANO PASSOS - 77731077187 | BD28: Formosa | BE28: Goiás | BF28: 556199068260 | BG28: Rua 8, Q 38 | BH28: 73807315 | BI28: Setor Nordeste | BJ28: alinemariano01@hotmail.com | BL28: 2311.61 | BM28: 45477 | BQ28: 3116 | BR28: 5400 | BS28: Vendedor(a) | BT28: 45307 | BW28: sim | BY28: MP134443 | BZ28: 45308 | CA28: 45327 | CC28: 45307 | CD28: Sim | CF28: 45308 | CG28: 45313 | CI28: 45314 | CL28: 45310 | CM28: 45327 | CN28: 45307 | CO28: 45337 | CP28: 45341 | CR28: 45307 | CS28: 45321 | CT28: 45477 | CV28: 45338 | CW28: 45317 | CY28: Sim | DB28: 45323 | DD28: 45327 | DE28: 45324 | DF28: 45350 | DI28: 45352 | DJ28: 45303 | DK28: 45338 | DL28: 45350 | DM28: 45371 | DN28: 45383 | DO28: 45317 | DP28: OK
A29: 3208 | B29: PROCESSO FINALIZADO | C29: 3757 | D29: AGL028 - VILA DO CERRADO | E29: ETAPA 01 | F29: BLOCO B | G29: 2 | H29: ÁGUAS LINDAS | I29: WILLIAM SANTOS SILVA | J29: "06332147105" | K29: EQUIPE PRÓPRIA | AGL | L29: DOUGLAS DIVINO PEREIRA DA SILVA - CLT | M29: Não | N29: Não | O29: Não | P29: Sim | Q29: Sim | R29: Não | S29: Não | T29: 163032.44 | U29: 545.86 | V29: 0 | W29: 113535.15 | X29: 49161 | Y29: 0 | Z29: 162696.15 | AA29: 0 | AB29: 0 | AD29: 8787718976383 | AE29: Contrato Adimplente | AG29: 45329 | AH29: 2740.25 | AI29: 45315 | AJ29: 2004 | AK29: 45306 | AP29: Endy Carvalho Consultoria imobiliária | AT29: 45653 | AU29: 45744 | AV29: VENDA FINALIZADA | AW29: 45307 | AX29: 19932 | AY29: 218000.23 | BA29: AGL28 | BB29: 19932 | BD29: Águas Lindas de Goiás | BE29: Goiás | BF29: 5561984663735 | BG29: Q 57 | BH29: 72910000 | BI29: JARDIM SANTA LUCIA | BJ29: awilliamsantos@gmail.com | BL29: 1819.53 | BM29: 45482 | BQ29: 2717 | BR29: 5401 | BS29: Vendedor(a) | BT29: 45314 | BU29: 449 | BV29: 45316 | BX29: 45322 | BY29: MP129688 | BZ29: 45314 | CA29: 45320 | CC29: 45307 | CD29: Sim | CF29: 45314 | CG29: 45310 | CJ29: 45322 | CL29: 45314 | CM29: 45324 | CN29: 45307 | CO29: 45323 | CP29: 45320 | CR29: 45307 | CS29: 45314 | CU29: 45320 | CV29: 45329 | CW29: 45314 | CY29: Sim | DD29: 45306 | DF29: 45330 | DI29: 45331 | DJ29: 45306 | DK29: 45330 | DL29: 45519 | DM29: 45345 | DN29: 45624 | DO29: 45310 | DP29: 45624 | EE29: 4165.32
A30: 3209 | B30: PROCESSO FINALIZADO | C30: 3745 | D30: FSA009 - VILA DOS IPÊS | E30: Única | F30: BLOCO B | G30: 4 | H30: FORMOSA | I30: ANA LAURA DE ASSIS FERREIRA | J30: "05573490109" | K30: AUTÔNOMOS | FSA | L30: ANA CAROLINA FERREIRA DE ANDRADE - CARLOS ANDRADE IMOBILIÁRIA | M30: Não | N30: Não | O30: Não | P30: Não | Q30: Não | R30: Não | S30: Não | T30: 162189.79 | U30: 862.69 | V30: 0 | W30: 159457.79 | X30: 2732 | Y30: 0 | Z30: 162189.79 | AA30: 0 | AB30: 0 | AD30: 8787718940079 | AE30: Contrato Adimplente | AF30: 73981 | AG30: 45355 | AH30: 3225.6 | AI30: 45337 | AJ30: 2004 | AK30: 45307 | AP30: Endy Carvalho Consultoria imobiliária | AT30: 45503 | AU30: 45503 | AV30: VENDA FINALIZADA | AW30: 45308 | AX30: 19998 | AY30: 225000.16 | BA30: FSA09 | BB30: 19998 | BC30: EDNA TELMA DE ASSIS FERREIRA - 88604497153 | BD30: Formosa | BE30: Goiás | BF30: 5561996843351 | BG30: Rua Virgílio Alves Ferreira, Q 4, | BH30: 73805345 | BI30: Setor Pampulha | BJ30: analaurawgf@gmail.com | BL30: 2875.65 | BM30: 45475 | BQ30: 3052 | BR30: 5403 | BS30: Auxiliar | BT30: 45321 | BW30: sim | BY30: MP134445 | BZ30: 45322 | CA30: 45331 | CC30: 45307 | CD30: Sim | CF30: 45322 | CL30: 45327 | CM30: 45331 | CN30: 45307 | CO30: 45337 | CP30: 45341 | CR30: 45308 | CS30: 45310 | CV30: 45338 | CW30: 45309 | CY30: Sim | DB30: 45329 | DD30: 45331 | DE30: 45330 | DF30: 45355 | DI30: 45359 | DJ30: 45306 | DK30: 45338 | DL30: 45365 | DM30: 45371 | DN30: 45383 | DO30: 45309 | DP30: OK
A31: 3210 | B31: PROCESSO FINALIZADO | C31: 3744 | D31: AGL028 - VILA DO CERRADO | E31: ETAPA 02 | F31: BLOCO I | G31: 304 | H31: ÁGUAS LINDAS | I31: THAINARA FERNANDES DOS SANTOS | J31: "02347367129" | K31: EQUIPE PRÓPRIA | AGL | L31: MAYSA GABRIELA GONÇALVES OLIVEIRA - CLT | M31: Não | N31: Não | O31: Não | P31: Sim | Q31: Sim | R31: Não | S31: Não | T31: 155601.28 | U31: 589.8 | V31: 0 | W31: 115104.28 | X31: 40497 | Y31: 0 | Z31: 155601.28 | AA31: 0 | AB31: 0 | AD31: 8787718975832 | AE31: Contrato Adimplente | AG31: 45329 | AH31: 2740.25 | AI31: 45315 | AJ31: 2004 | AK31: 45307 | AP31: Endy Carvalho Consultoria imobiliária | AT31: 45741 | AU31: 45741 | AV31: VENDA FINALIZADA | AW31: 45308 | AX31: 19997 | AY31: 200000 | BA31: AGL28 | BB31: 19997 | BD31: Águas Lindas de Goiás | BE31: Goiás | BF31: 5561991207614 | BG31: RUA 8 Q 63 L 26 | BH31: 72910000 | BI31: PEROLA II | BJ31: THAINARAFERNANDES68@GMAIL.COM | BL31: 1966 | BM31: 45481 | BQ31: 2849 | BR31: 5402 | BS31: Recepcionista | BT31: 45302 | BU31: 500 | BV31: 45316 | BX31: 45322 | BY31: MP129808 | BZ31: 45302 | CA31: 45320 | CC31: 45306 | CD31: Sim | CF31: 45302 | CG31: 45307 | CI31: 45309 | CJ31: 45322 | CL31: 45308 | CM31: 45324 | CN31: 45308 | CO31: 45323 | CP31: 45320 | CR31: 45310 | CS31: 45310 | CU31: 45320 | CV31: 45329 | CW31: 45310 | CY31: Sim | DD31: 45306 | DF31: 45330 | DI31: 45336 | DJ31: 45306 | DK31: 45329 | DL31: 45331 | DM31: 45345 | DN31: 45548 | DO31: 45310 | DP31: 45548 | EE31: 3981.32
A32: 3211 | B32: PROCESSO FINALIZADO | C32: 3737 | D32: FSA009 - VILA DOS IPÊS | E32: Única | F32: BLOCO G | G32: 102 | H32: FORMOSA | I32: SALUSTIANO ALVES PEREIRA NETO | J32: "02252591170" | K32: AUTÔNOMOS | FSA | L32: MATEUS VITOR DIAS - DESLIGADO | M32: Não | N32: Não | O32: Não | P32: Não | Q32: Não | R32: Não | S32: Não | T32: 152966 | U32: 498 | V32: 0 | W32: 102560 | X32: 51132 | Y32: 0 | Z32: 153692 | AA32: 0 | AB32: 0 | AD32: 8787718954231 | AE32: Contrato Adimplente | AF32: 74063 | AG32: 45350 | AH32: 3559.94 | AI32: 45331 | AJ32: 2004 | AK32: 45308 | AP32: Endy Carvalho Consultoria imobiliária | AT32: 45503 | AU32: 45503 | AV32: VENDA FINALIZADA | AW32: 45309 | AX32: 20042 | AY32: 215000.6 | BA32: FSA09 | BB32: 20042 | BC32: MARIA ZIZELDA GONÇALVES RODRIGUES - 84431776168 | BD32: Formosa | BE32: Goiás | BF32: 5562996749952 | BG32: Avenida João Ísper Gebrim | BH32: 73813210 | BI32: Formosinha | BJ32: saude88198@gmail.com | BL32: 1660 | BM32: 45460 | BQ32: 3129 | BR32: 5404 | BS32: Motorista | BT32: 45321 | BW32: sim | BY32: MP134446 | BZ32: 45321 | CA32: 45329 | CC32: 45308 | CD32: Sim | CF32: 45321 | CL32: 45327 | CM32: 45329 | CN32: 45308 | CO32: 45337 | CP32: 45341 | CR32: 45309 | CS32: 45309 | CT32: 45460 | CV32: 45338 | CW32: 45308 | CY32: Sim | DB32: 45324 | DD32: 45329 | DE32: 45328 | DF32: 45350 | DI32: 45352 | DJ32: 45302 | DK32: 45338 | DL32: 45365 | DM32: 45371 | DN32: 45383 | DO32: 45308 | DP32: OK
A33: 3212 | B33: PROCESSO FINALIZADO | C33: 3746 | D33: FSA009 - VILA DOS IPÊS | E33: Única | F33: BLOCO Q | G33: 3 | H33: FORMOSA | I33: SABRINA SILVA GOMES DA MOTA | J33: "71382547170" | K33: AUTÔNOMOS | FSA | L33: ANA CAROLINA FERREIRA DE ANDRADE - CARLOS ANDRADE IMOBILIÁRIA | M33: Não | N33: Não | O33: Não | P33: Não | Q33: Não | R33: Não | S33: Não | T33: 147817.32 | U33: 510.14 | V33: 0 | W33: 98956.32 | X33: 50603 | Y33: 0 | Z33: 149559.32 | AA33: 0 | AB33: 0 | AD33: 8787718968860 | AE33: Contrato Adimplente | AG33: 45358 | AH33: 3559.95 | AI33: 45343 | AJ33: 2004 | AK33: 45308 | AP33: Endy Carvalho Consultoria imobiliária | AT33: 45503 | AU33: 45503 | AV33: VENDA FINALIZADA | AW33: 45309 | AX33: 20043 | AY33: 225000 | BA33: FSA09 | BB33: 20043 | BC33: GABRIELA SILVA GOMES DA MOTA - 71382552173 | BD33: Formosa | BE33: Goiás | BF33: 5561999215463 | BG33: Rua 7, Q 130 | BH33: 73813420 | BI33: Formosinha | BJ33: sabrinagomesmota18@gmail.com | BL33: 1700.47 | BM33: 45475 | BQ33: 3283 | BR33: 5405 | BS33: Recepcionista | BT33: 45315 | BW33: sim | BY33: MP134447 | BZ33: 45315 | CA33: 45337 | CC33: 45308 | CD33: Sim | CF33: 45315 | CL33: 45317 | CM33: 45343 | CN33: 45309 | CO33: 45352 | CR33: 45313 | CS33: 45324 | CT33: 45475 | CV33: 45364 | CW33: 45321 | CY33: Sim | DB33: 45331 | DD33: 45343 | DE33: 45337 | DF33: 45358 | DI33: 45359 | DJ33: 45310 | DK33: 45364 | DL33: 45366 | DM33: 45371 | DN33: 45383 | DO33: 45315 | DP33: OK
A34: 3213 | B34: PROCESSO FINALIZADO | C34: 3747 | D34: FSA009 - VILA DOS IPÊS | E34: Única | F34: BLOCO A | G34: 204 | H34: FORMOSA | I34: GISLANE OLIVEIRA MOTA | J34: "06543134151" | K34: EQUIPE PRÓPRIA |FSA | L34: NAUANE MARTINS DA SILVA OLIVEIRA - CLT | M34: Não | N34: Não | O34: Não | P34: Não | Q34: Não | R34: Não | S34: Não | T34: 151967.22 | U34: 660 | V34: 0 | W34: 125034.22 | X34: 26934 | Y34: 0 | Z34: 151968.22 | AA34: 0 | AB34: 0 | AD34: 8787719016820 | AE34: Contrato Adimplente | AF34: 73973 | AG34: 45355 | AH34: 2794.99 | AI34: 45322 | AJ34: 2004 | AK34: 45309 | AP34: Endy Carvalho Consultoria imobiliária | AT34: 45484 | AU34: 45484 | AV34: VENDA FINALIZADA | AW34: 45310 | AX34: 20185 | AY34: 205767.22 | BA34: FSA09 | BB34: 20185 | BD34: Formosa | BE34: Goiás | BF34: 5561998166002 | BG34: AVENIDA CIRCULAR Q 16 L 8 | BH34: 73805207 | BI34: JARDIM OLIVEIRA | BJ34: gislanegatinhaa@gmail.com | BL34: 2200 | BM34: 45482 | BO34: Debora Mesquita Aguiar Mendes (Gestor): teste de disparo | BP34: 19/01/2024 às 14h10 | BQ34: 3036 | BR34: 5406 | BS34: Esteticista | BT34: 45303 | BW34: sim | BY34: MP134448 | BZ34: 45303 | CA34: 45323 | CC34: 45309 | CD34: Sim | CF34: 45303 | CL34: 45310 | CM34: 45345 | CN34: 45309 | CO34: 45337 | CP34: 45336 | CR34: 45313 | CS34: 45315 | CT34: 45482 | CV34: 45338 | CW34: 45315 | CY34: Sim | DB34: 45320 | DD34: 45322 | DE34: 45321 | DF34: 45355 | DI34: 45357 | DJ34: 45310 | DK34: 45338 | DL34: 45365 | DM34: 45371 | DN34: 45383 | DO34: 45315 | DP34: OK
A35: 3214 | B35: PROCESSO FINALIZADO | C35: 3749 | D35: FSA009 - VILA DOS IPÊS | E35: Única | F35: BLOCO E | G35: 1 | H35: FORMOSA | I35: GEOVANE LOPES DA CUNHA | J35: "06907233185" | K35: AUTÔNOMOS | FSA | L35: MATEUS VITOR DIAS - DESLIGADO | M35: Não | N35: Não | O35: Não | P35: Não | Q35: Não | R35: Não | S35: Não | T35: 164200 | U35: 952.3 | V35: 0 | W35: 162778 | X35: 1422 | Y35: 0 | Z35: 164200 | AA35: 0 | AB35: 0 | AD35: 8787719018815 | AE35: Contrato Adimplente | AF35: 74026 | AG35: 45510 | AH35: 0 | AI35: 45323 | AJ35: 2004 | AK35: 45310 | AP35: Endy Carvalho Consultoria imobiliária | AT35: 45484 | AU35: 45520 | AV35: VENDA FINALIZADA | AW35: 45313 | AX35: 20239 | AY35: 218000 | BA35: FSA09 | BB35: 20239 | BD35: Formosa | BE35: Goiás | BF35: 556196386784 | BG35: Rua 11, Q. 33, | BH35: 73808315 | BI35: PARQUE VILA VERDE | BJ35: geovanelopesdacunha7@gmail.com | BL35: 3174.36 | BM35: 45483 | BQ35: 3098 | BR35: 5407 | BS35: Auxiliar | BT35: 45309 | BW35: sim | BY35: MP134449 | BZ35: 45309 | CA35: 45324 | CC35: 45310 | CD35: Sim | CF35: 45309 | CL35: 45313 | CM35: 45384 | CN35: 45313 | CO35: 45337 | CR35: 45313 | CS35: 45317 | CT35: 45483 | CV35: 45338 | CW35: 45316 | CY35: Sim | DB35: 45320 | DD35: 45510 | DE35: 45321 | DF35: 45512 | DI35: 45519 | DJ35: 45310 | DK35: 45338 | DL35: 45341 | DM35: 45357 | DN35: 45383 | DO35: 45315 | DP35: OK
A36: 3215 | B36: PROCESSO FINALIZADO | C36: 3772 | D36: FSA009 - VILA DOS IPÊS | E36: Única | F36: BLOCO Q | G36: 1 | H36: FORMOSA | I36: GUSTAVO BENICIO DOS SANTOS | J36: "03903037125" | K36: EQUIPE PRÓPRIA |FSA | L36: TAKADA IMOB | M36: Não | N36: Não | O36: Não | P36: Não | Q36: Não | R36: Não | S36: Não | T36: 164200 | U36: 902.06 | V36: 0 | W36: 158762 | X36: 5438 | Y36: 0 | Z36: 164200 | AA36: 0 | AB36: 0 | AD36: 8787719030289 | AE36: Contrato Adimplente | AF36: 74218 | AG36: 45386 | AH36: 3920.95 | AI36: 45358 | AJ36: 2004 | AK36: 45314 | AP36: Endy Carvalho Consultoria imobiliária | AT36: 45743 | AU36: 45743 | AV36: VENDA FINALIZADA | AW36: 45316 | AX36: 20366 | AY36: 230000 | BA36: FSA09 | BB36: 20366 | BC36: LUANA CRISTINA ALVES - 02890896110 | BD36: Formosa | BE36: Goiás | BF36: 5561996279986 | BG36: RUA H Q 94 L 25A | BH36: 73808068 | BI36: PARQUE DA COLINA | BJ36: gusttavo2.0gbs@gmail.com | BL36: 3113.77 | BM36: 45488 | BQ36: 3281 | BR36: 5411 | BS36: Auxiliar | BT36: 45330 | BW36: sim | BY36: MP134453 | BZ36: 45330 | CA36: 45356 | CC36: 45315 | CD36: Sim | CF36: 45330 | CL36: 45336 | CM36: 45373 | CN36: 45315 | CO36: 45366 | CP36: 45365 | CR36: 45316 | CS36: 45342 | CT36: 45488 | CV36: 45387 | CW36: 45342 | CY36: Sim | DB36: 45342 | DD36: 45316 | DE36: 45355 | DF36: 45386 | DI36: 45387 | DJ36: 45313 | DK36: 45387 | DL36: 45463 | DM36: 45504 | DN36: 45728 | DO36: 45342 | DP36: 45728
A37: 3216 | B37: PROCESSO FINALIZADO | C37: 3760 | D37: FSA009 - VILA DOS IPÊS | E37: Única | F37: BLOCO L | G37: 304 | H37: FORMOSA | I37: MATHEU GOMES DE AMORIM | J37: "07435470120" | K37: AUTÔNOMOS | FSA | L37: JANDER JACKSON VENANCIO DE SOUZA- DESLIGADO | M37: Não | N37: Não | O37: Não | P37: Não | Q37: Não | R37: Não | S37: Não | T37: 149433.92 | U37: 540 | V37: 0 | W37: 105639.92 | X37: 43796 | Y37: 0 | Z37: 149435.92 | AA37: 0 | AB37: 0 | AD37: 8787718978491 | AE37: Contrato Adimplente | AF37: 74153 | AG37: 45358 | AH37: 3559.94 | AI37: 45345 | AJ37: 2004 | AK37: 45314 | AP37: Endy Carvalho Consultoria imobiliária | AT37: 45503 | AU37: 45503 | AV37: VENDA FINALIZADA | AW37: 45316 | AX37: 20363 | AY37: 205000 | BA37: FSA09 | BB37: 20363 | BD37: Formosa | BE37: Goiás | BF37: 5561996176990 | BG37: Rua 10-A, Q.31 | BH37: 73805235 | BI37: Jardim Oliveira | BJ37: matheug056@gmail.com | BL37: 1800 | BM37: 45483 | BQ37: 3203 | BR37: 5409 | BS37: Auxiliar | BT37: 45309 | BW37: sim | BY37: MP134452 | BZ37: 45309 | CA37: 45342 | CC37: 45315 | CD37: Sim | CF37: 45309 | CG37: 45329 | CI37: 45330 | CL37: 45314 | CM37: 45345 | CN37: 45315 | CO37: 45352 | CR37: 45316 | CS37: 45337 | CT37: 45483 | CV37: 45364 | CW37: 45337 | CY37: Sim | DD37: 45345 | DF37: 45358 | DI37: 45359 | DJ37: 45315 | DK37: 45364 | DL37: 45372 | DM37: 45379 | DN37: 45383 | DO37: 45337 | DP37: OK
A38: 3217 | B38: PROCESSO FINALIZADO | C38: 3771 | D38: FSA009 - VILA DOS IPÊS | E38: Única | F38: BLOCO N | G38: 3 | H38: FORMOSA | I38: LEILANE LOPES FERREIRA | J38: "05210592162" | K38: EQUIPE PRÓPRIA |FSA | L38: TAKADA IMOB | M38: Não | N38: Não | O38: Não | P38: Não | Q38: Não | R38: Não | S38: Não | T38: 159623.6 | U38: 600 | V38: 0 | W38: 125530.6 | X38: 34775 | Y38: 0 | Z38: 160305.6 | AA38: 0 | AB38: 0 | AD38: 8787719030645 | AE38: Contrato Adimplente | AF38: 74172 | AG38: 45448 | AH38: 5466.82 | AI38: 45330 | AJ38: 2004 | AK38: 45315 | AP38: Endy Carvalho Consultoria imobiliária | AT38: 45484 | AU38: 45484 | AV38: VENDA FINALIZADA | AW38: 45316 | AX38: 20364 | AY38: 215000.2 | BA38: FSA09 | BB38: 20364 | BD38: Formosa | BE38: Goiás | BF38: 5561999365358 | BG38: AVENIDA CALIFORNIA Q 37 | BH38: 73807600 | BI38: JARDIM CALIFÓRNIA | BJ38: leilopes2008@hotmail.com | BL38: 2000 | BM38: 45488 | BQ38: 3235 | BR38: 5410 | BS38: Auxiliar | BT38: 45309 | BW38: sim | BY38: MP134451 | BZ38: 45309 | CA38: 45328 | CC38: 45315 | CD38: Sim | CF38: 45309 | CG38: 45317 | CI38: 45318 | CL38: 45316 | CM38: 45366 | CN38: 45315 | CO38: 45337 | CR38: 45316 | CS38: 45321 | CT38: 45488 | CU38: 45364 | CV38: 45338 | CW38: 45321 | CY38: Sim | DD38: 45316 | DI38: 45453 | DJ38: 45313 | DK38: 45338 | DL38: 45350 | DM38: 45357 | DN38: 45383 | DO38: 45321 | DP38: OK | EE38: 2347.62
A39: 3218 | B39: PROCESSO FINALIZADO | C39: 3731 | D39: FSA009 - VILA DOS IPÊS | E39: Única | F39: BLOCO F | G39: 1 | H39: FORMOSA | I39: RONALDO ADRIANO DE SOUSA FILHO | J39: "70878880135" | K39: EQUIPE PRÓPRIA |FSA | L39: FERNANDO FONSECA DE DEUS GALVÃO - CLT- DESLIGADO | M39: Não | N39: Não | O39: Não | P39: Não | Q39: Não | R39: Não | S39: Não | T39: 164200 | U39: 1131.49 | V39: 0 | W39: 163639 | X39: 561 | Y39: 0 | Z39: 164200 | AA39: 0 | AB39: 0 | AD39: 8787719019960 | AE39: Contrato Adimplente | AF39: 74042 | AG39: 45383 | AH39: 3936.55 | AI39: 45351 | AJ39: 2004 | AK39: 45315 | AP39: Endy Carvalho Consultoria imobiliária | AT39: 45503 | AU39: 45503 | AV39: VENDA FINALIZADA | AW39: 45316 | AX39: 20362 | AY39: 218000 | BA39: FSA09 | BB39: 20362 | BF39: 5561994223415 | BG39: Av Aeroporto, Q. D, L. 03-F | BH39: 73800000 | BI39: SETOR IRIS VILLAGE CHACARAS DO ABREU | BJ39: ronaldo.adrianof@gmail.com | BL39: 4171.48 | BM39: 45474 | BQ39: 3114 | BR39: 5408 | BS39: Auxiliar | BT39: 45295 | BW39: sim | BY39: MP134450 | BZ39: 45295 | CA39: 45349 | CC39: 45315 | CD39: Sim | CF39: 45295 | CJ39: 45358 | CL39: 45316 | CM39: 45351 | CN39: 45315 | CO39: 45352 | CP39: 45356 | CR39: 45316 | CS39: 45315 | CT39: 45474 | CU39: 45364 | CV39: 45364 | CW39: 45315 | CY39: Sim | DD39: 45351 | DF39: 45384 | DI39: 45385 | DJ39: 45310 | DK39: 45364 | DL39: 45366 | DM39: 45371 | DN39: 45383 | DO39: 45315 | DP39: OK | EE39: 1768.46
A40: 3219 | B40: PROCESSO FINALIZADO | C40: 3777 | D40: FSA009 - VILA DOS IPÊS | E40: Única | F40: BLOCO K | G40: 2 | H40: FORMOSA | I40: SIMEIA MAKELLE PEREIRA DE ALVIM | J40: "03796691102" | K40: EQUIPE PRÓPRIA |FSA | L40: TAKADA IMOB | M40: Não | N40: Não | O40: Não | P40: Não | Q40: Não | R40: Não | S40: Não | T40: 152325.98 | U40: 600 | V40: 0 | W40: 117710.98 | X40: 35635 | Y40: 0 | Z40: 153345.98 | AA40: 0 | AB40: 0 | AD40: 8787719054137 | AE40: Contrato Adimplente | AF40: 74123 | AG40: 45369 | AH40: 2849.02 | AI40: 45351 | AJ40: 2004 | AK40: 45316 | AP40: Endy Carvalho Consultoria imobiliária | AT40: 45503 | AU40: 45503 | AV40: VENDA FINALIZADA | AW40: 45317 | AX40: 20412 | AY40: 215000 | BA40: FSA09 | BB40: 20412 | BC40: REGIS WILLIAN NOGUEIRA - 03167662166 | BD40: Formosa | BE40: Goiás | BF40: 5561996823402 | BG40: RUA F | BH40: 73808155 | BI40: PARQUE DA COLINA II | BJ40: simeiamakelle20@gmail.com | BL40: 2000 | BM40: 45490 | BQ40: 3186 | BR40: 5415 | BS40: Auxiliar | BT40: 45330 | BW40: sim | BY40: MP134457 | BZ40: 45330 | CA40: 45345 | CC40: 45317 | CD40: Sim | CF40: 45330 | CL40: 45336 | CM40: 45351 | CN40: 45317 | CO40: 45352 | CP40: 45356 | CR40: 45320 | CS40: 45342 | CT40: 45490 | CU40: 45364 | CV40: 45364 | CW40: 45342 | CY40: Sim | DD40: 45351 | DF40: 45369 | DI40: 45370 | DJ40: 45315 | DK40: 45364 | DL40: 45365 | DM40: 45371 | DN40: 45383 | DO40: 45342 | DP40: OK | EE40: 2466.47
A41: 3220 | B41: PROCESSO FINALIZADO | C41: 3697 | D41: FSA009 - VILA DOS IPÊS | E41: Única | F41: BLOCO G | G41: 203 | H41: FORMOSA | I41: EMELY CAMPOS ENGLER | J41: "70856212148" | K41: AUTÔNOMOS | FSA | L41: AMANDA SOUZA PEREIRA | M41: Não | N41: Não | O41: Não | P41: Não | Q41: Não | R41: Não | S41: Não | T41: 149200 | U41: 569.42 | V41: 0 | W41: 110069 | X41: 39131 | Y41: 0 | Z41: 149200 | AA41: 0 | AB41: 0 | AD41: 8787718824214 | AE41: Contrato Adimplente | AF41: 74068 | AG41: 45355 | AH41: 2794.99 | AI41: 45321 | AJ41: 2004 | AK41: 45316 | AP41: Endy Carvalho Consultoria imobiliária | AT41: 45484 | AU41: 45484 | AV41: VENDA FINALIZADA | AW41: 45317 | AX41: 20409 | AY41: 203000 | BA41: FSA09 | BB41: 20409 | BD41: Formosa | BE41: Goiás | BF41: 5561999708382 | BG41: Rua 21, Q.82, L.15 | BH41: 73813320 | BI41: Formosinha | BJ41: emelyengler@hotmail.com | BL41: 1898.06 | BM41: 45452 | BQ41: 3134 | BR41: 5412 | BS41: Auxiliar | BT41: 45315 | BW41: sim | BY41: MP134454 | BZ41: 45315 | CA41: 45323 | CC41: 45317 | CD41: Sim | CF41: 45315 | CL41: 45317 | CM41: 45345 | CN41: 45317 | CO41: 45337 | CR41: 45317 | CS41: 45287 | CT41: 45452 | CV41: 45338 | CW41: 45286 | CY41: Sim | DB41: 45321 | DD41: 45321 | DE41: 45321 | DF41: 45355 | DI41: 45357 | DJ41: 45281 | DK41: 45338 | DL41: 45364 | DM41: 45371 | DN41: 45383 | DO41: 45286 | DP41: OK
A42: 3221 | B42: PROCESSO FINALIZADO | C42: 3766 | D42: FSA009 - VILA DOS IPÊS | E42: Única | F42: BLOCO I | G42: 302 | H42: FORMOSA | I42: CARLEANO RODRIGUES CUSTÓDIO | J42: "02265778133" | K42: EQUIPE PRÓPRIA |FSA | L42: TAKADA IMOB | M42: Não | N42: Não | O42: Não | P42: Não | Q42: Não | R42: Não | S42: Não | T42: 161238.18 | U42: 717 | V42: 0 | W42: 141079.18 | X42: 20476 | Y42: 0 | Z42: 161555.18 | AA42: 0 | AB42: 0 | AD42: 8787719053661 | AE42: Contrato Adimplente | AG42: 45359 | AH42: 3210.01 | AI42: 45342 | AJ42: 2004 | AK42: 45316 | AP42: Endy Carvalho Consultoria imobiliária | AQ42: Michelle Deisy Pereira da Silva | AT42: 45503 | AU42: 45503 | AV42: VENDA FINALIZADA | AW42: 45317 | AX42: 20411 | AY42: 215038.18 | BA42: FSA09 | BB42: 20411 | BD42: Cabeceiras | BE42: Goiás | BF42: 5561996125410 | BG42: RUA JOSE PEREIRA DE SOUZA Q 10 | BH42: 73870000 | BI42: SETOR ENIS MACHADO | BJ42: rodriguescustodiocarleano@gmail.com | BL42: 2390 | BM42: 45486 | BQ42: 3158 | BR42: 5414 | BS42: Assistente | BT42: 45306 | BW42: sim | BY42: MP134456 | BZ42: 45306 | CA42: 45328 | CC42: 45317 | CD42: Sim | CF42: 45306 | CL42: 45317 | CM42: 45329 | CN42: 45317 | CO42: 45337 | CR42: 45320 | CS42: 45321 | CT42: 45486 | CV42: 45338 | CW42: 45321 | CY42: Sim | DB42: 45324 | DD42: 45329 | DE42: 45327 | DF42: 45484 | DI42: 45488 | DJ42: 45315 | DK42: 45338 | DL42: 45342 | DM42: 45357 | DN42: 45383 | DO42: 45321 | DP42: OK
A43: 3222 | B43: DISTRATO | C43: 3755 | D43: FSA009 - VILA DOS IPÊS | E43: Única | F43: BLOCO H | G43: 204 | H43: FORMOSA | I43: PABLINE LOPES DOS REIS | J43: "71302625160" | K43: EQUIPE PRÓPRIA |FSA | L43: INGRID ALVES D'APARECIDA - CLT | M43: Não | N43: Não | O43: Não | P43: Não | Q43: Não | R43: Não | S43: Não | T43: 155412.45 | U43: 690 | V43: 0 | W43: 131625.45 | X43: 23787 | Y43: 0 | Z43: 155412.45 | AA43: 0 | AB43: 0 | AE43: Contrato Adimplente | AH43: 0 | AK43: 45316 | AP43: Endy Carvalho Consultoria imobiliária | AT43: 45342 | AU43: 45342 | AV43: DISTRATO | AW43: 45317 | AX43: 20410 | AY43: 209212.45 | BA43: FSA09 | BB43: 20410 | BD43: Formosa | BE43: Goiás | BF43: 5561996455079 | BG43: RUA MARRECO, Q 12, L 15 | BH43: 73813788 | BI43: PARQUE LAGO | BJ43: lopesreis1312@gmail.com | BL43: 2300 | BQ43: 3141 | BR43: 5413 | BS43: Auxiliar | BY43: MP134455 | CC43: 45317 | CF43: 45304 | CL43: 45317 | CN43: 45317 | CR43: 45317 | CS43: 45315 | CT43: 45483 | CW43: 45315 | CY43: Sim | DD43: 45317 | DJ43: 45309 | DO43: 45315
A44: 3223 | B44: PROCESSO FINALIZADO | C44: 3783 | D44: FSA003 - AURIUM HOME | E44: ETAPA 01 | F44: BLOCO RESIDENCIAL | G44: APT 401 | H44: FORMOSA | I44: JULIANA NAVES DE DEUS | J44: "71108270115" | K44: NOVKA| DF | L44: LUCIANO DE OLIVEIRA NASCIMENTO | M44: Sim | N44: Não | O44: Não | P44: Não | Q44: Não | R44: Não | S44: Sim | T44: 480000 | U44: 0 | V44: 480000 | W44: 480000 | X44: 0 | Y44: 0 | Z44: 480000 | AA44: 0 | AB44: 0 | AE44: Contrato Adimplente | AF44: 10861 | AG44: 45663 | AH44: 5655.4 | AI44: 45597 | AJ44: 2004 | AK44: 45317 | AP44: Porto seguro empreendimento lotérico Ltda | AT44: 45677 | AU44: 45677 | AV44: VENDA FINALIZADA | AW44: 45317 | AX44: 20414 | AY44: 532000 | BA44: FSA 03 | BB44: 20414 | BD44: Formosa | BE44: Goiás | BF44: 5561996838873 | BG44: Rua Modesto de Melo | BH44: 73801530 | BI44: Centro | BJ44: junaves2006@gmail.com | BL44: 20964.41 | BO44: Eduardo Martins (Gestor): Processo de registro concluído com sucesso. Garantia já conforme na Caixa Econômica. | BP44: 20/01/2025 às 16h36 | BQ44: 1957 | BR44: 5416 | BS44: Administrador | CS44: 45589 | CW44: 45588 | CY44: Sim | DD44: 45670 | DE44: 45597 | DF44: 45663 | DI44: 45664 | EG44: Pago
A45: 3224 | B45: PROCESSO FINALIZADO | C45: 3776 | D45: AGL028 - VILA DO CERRADO | E45: ETAPA 02 | F45: BLOCO I | G45: 2 | H45: ÁGUAS LINDAS | I45: NATHANAELE GRAZIELE FERREIRA DE MELO | J45: "06260412100" | K45: EQUIPE PRÓPRIA | AGL | L45: MICHELE RODRIGUES DA SILVA | M45: Não | N45: Não | O45: Não | P45: Sim | Q45: Não | R45: Não | S45: Não | T45: 153918.6 | U45: 506.73 | V45: 0 | W45: 98603.41 | X45: 55000 | Y45: 0 | Z45: 153603.41 | AA45: 0 | AB45: 0 | AD45: 8787719038557 | AE45: Contrato Adimplente | AF45: 96136 | AG45: 45341 | AH45: 2740.25 | AI45: 45323 | AJ45: 2004 | AK45: 45317 | AP45: Endy Carvalho Consultoria imobiliária | AT45: 45741 | AU45: 45741 | AV45: VENDA FINALIZADA | AW45: 45320 | AX45: 20470 | AY45: 204999.89 | BA45: AGL28 | BB45: 20470 | BD45: Brasília | BE45: Distrito Federal | BF45: 5561992801015 | BG45: SHSN RN HORIZ R 21 | BH45: 72290666 | BI45: Ceilândia II | BJ45: Nathanaele123ke@gmail.com | BL45: 1689.16 | BM45: 45489 | BQ45: 2835 | BR45: 5418 | BS45: Auxiliar de Serviços Gerais | BT45: 45317 | BU45: 500 | BV45: 45327 | BX45: 45330 | BY45: MP129809 | BZ45: 45317 | CA45: 45328 | CC45: 45317 | CD45: Sim | CF45: 45317 | CG45: 45317 | CL45: 45320 | CM45: 45331 | CN45: 45317 | CO45: 45414 | CP45: 45328 | CR45: 45320 | CS45: 45320 | CU45: 45328 | CV45: 45342 | CW45: 45320 | CX45: 45337 | CY45: Sim | DD45: 45315 | DF45: 45342 | DI45: 45343 | DJ45: 45315 | DK45: 45477 | DL45: 45527 | DM45: 45631 | DN45: 45693 | DO45: 45317 | DP45: 45693 | EE45: 4165.32
A46: 3225 | B46: PROCESSO FINALIZADO | C46: 3701 | D46: FSA009 - VILA DOS IPÊS | E46: Única | F46: BLOCO H | G46: 304 | H46: FORMOSA | I46: LETICIA GABRIELE RODRIGUES GONÇALVES | J46: "09953840105" | K46: AUTÔNOMOS | FSA | L46: LAYNNE KAMYLLA OLIVEIRA BORGES FONSECA | M46: Não | N46: Não | O46: Não | P46: Não | Q46: Não | R46: Não | S46: Não | T46: 147617.87 | U46: 501.61 | V46: 0 | W46: 97245.94 | X46: 50373 | Y46: 0 | Z46: 147618.94 | AA46: 0 | AB46: 0 | AD46: 8787718831202 | AE46: Contrato Adimplente | AF46: 74089 | AG46: 45397 | AH46: 3544.37 | AI46: 45357 | AJ46: 2004 | AK46: 45317 | AP46: Endy Carvalho Consultoria imobiliária | AT46: 45743 | AU46: 45743 | AV46: VENDA FINALIZADA | AW46: 45322 | AX46: 20701 | AY46: 201417.87 | BA46: FSA09 | BB46: 20701 | BD46: Formosa | BE46: Goiás | BF46: 5561999125292 | BG46: Rua 8, Q. K, L. 15 | BH46: 73808755 | BI46: Setor Bela Vista | BJ46: klebia12e@gmail.com | BL46: 1672.05 | BM46: 45455 | BQ46: 3139 | BR46: 5429 | BS46: Assistente | BT46: 45316 | BW46: sim | BY46: MP134458 | BZ46: 45316 | CA46: 45355 | CC46: 45320 | CD46: Sim | CF46: 45316 | CL46: 45327 | CM46: 45357 | CN46: 45320 | CO46: 45366 | CP46: 45363 | CR46: 45320 | CS46: 45287 | CT46: 45455 | CW46: 45286 | DB46: 45287 | DD46: 45357 | DE46: 45355 | DF46: 45397 | DI46: 45399 | DJ46: 45282 | DK46: 45387 | DL46: 45497 | DM46: 45504 | DN46: 45728 | DO46: 45286 | DP46: 45728
A47: 3226 | B47: PROCESSO FINALIZADO | C47: 3741 | D47: FSA009 - VILA DOS IPÊS | E47: Única | F47: BLOCO N | G47: 1 | H47: FORMOSA | I47: ANDREW GOTTFRIED LAVALL | J47: "06162216144" | K47: EQUIPE PRÓPRIA |FSA | L47: NAUANE MARTINS DA SILVA OLIVEIRA - CLT | M47: Não | N47: Não | O47: Não | P47: Não | Q47: Não | R47: Não | S47: Não | T47: 164200 | U47: 1131.49 | V47: 0 | W47: 162329 | X47: 1871 | Y47: 0 | Z47: 164200 | AA47: 0 | AB47: 0 | AD47: 8787719122167 | AE47: Contrato Adimplente | AF47: 74170 | AG47: 45358 | AH47: 3936.53 | AI47: 45345 | AJ47: 2004 | AK47: 45317 | AP47: Endy Carvalho Consultoria imobiliária | AT47: 45484 | AU47: 45484 | AV47: VENDA FINALIZADA | AW47: 45320 | AX47: 20469 | AY47: 218000 | BA47: FSA09 | BB47: 20469 | BD47: Formosa | BE47: Goiás | BF47: 5561998300318 | BG47: RUA SEM NOME, LOTE 1471 | BH47: 73750000 | BI47: LOTEAMENTO SANTA MARIA | BJ47: andrewgottfried23@gmail.com | BL47: 3960.32 | BM47: 45474 | BQ47: 3233 | BR47: 5417 | BS47: Operador de Loja | BT47: 45301 | BW47: sim | BY47: MP134459 | BZ47: 45301 | CA47: 45341 | CC47: 45320 | CD47: Sim | CF47: 45301 | CL47: 45320 | CM47: 45345 | CN47: 45320 | CO47: 45352 | CR47: 45320 | CS47: 45330 | CT47: 45474 | CV47: 45364 | CW47: 45330 | CY47: Sim | DD47: 45342 | DF47: 45358 | DI47: 45359 | DJ47: 45324 | DK47: 45364 | DL47: 45366 | DM47: 45371 | DN47: 45383 | DO47: 45329 | DP47: OK
A48: 3227 | B48: PROCESSO FINALIZADO | C48: 3778 | D48: FSA009 - VILA DOS IPÊS | E48: Única | F48: BLOCO D | G48: 203 | H48: FORMOSA | I48: ADAILSON SOUZA DA SILVA | J48: "08220559535" | K48: EQUIPE PRÓPRIA |FSA | L48: TAKADA IMOB | M48: Não | N48: Não | O48: Não | P48: Não | Q48: Não | R48: Não | S48: Não | T48: 151480.25 | U48: 588.59 | V48: 0 | W48: 114687.25 | X48: 36260 | Y48: 0 | Z48: 150947.25 | AA48: 0 | AB48: 0 | AD48: 8787719073026 | AE48: Contrato Adimplente | AF48: 74020 | AG48: 45372 | AH48: 2884.43 | AI48: 45357 | AJ48: 2004 | AK48: 45320 | AP48: Endy Carvalho Consultoria imobiliária | AT48: 45743 | AU48: 45743 | AV48: VENDA FINALIZADA | AW48: 45321 | AX48: 20514 | AY48: 205280.25 | BA48: FSA09 | BB48: 20514 | BD48: Formosa | BE48: Goiás | BF48: 5561996607100 | BG48: RUA 09 Q 55 L 06 CASA 01 | BH48: 73808330 | BI48: PARQUE VILA VERDE | BJ48: adailsonsouza2030@gmail.com | BL48: 1962 | BM48: 45459 | BQ48: 3083 | BR48: 5420 | BS48: Auxiliar de Serviços Gerais | BT48: 45311 | BW48: sim | BY48: MP134461 | BZ48: 45311 | CA48: 45355 | CC48: 45320 | CD48: Sim | CF48: 45311 | CL48: 45321 | CM48: 45357 | CN48: 45320 | CO48: 45366 | CP48: 45363 | CR48: 45321 | CS48: 45323 | CT48: 45279 | CV48: 45387 | CW48: 45323 | CY48: Sim | DB48: 45323 | DD48: 45321 | DE48: 45355 | DF48: 45377 | DI48: 45421 | DJ48: 45317 | DK48: 45387 | DL48: 45469 | DM48: 45504 | DN48: 45728 | DO48: 45323 | DP48: 45728
A49: 3228 | B49: PROCESSO FINALIZADO | C49: 3773 | D49: FSA009 - VILA DOS IPÊS | E49: Única | F49: BLOCO I | G49: 2 | H49: FORMOSA | I49: TATIANE RAMOS DE AQUINO | J49: "02786440157" | K49: AUTÔNOMOS | FSA | L49: VITÓRIA IMÓVEIS IMOB | M49: Não | N49: Não | O49: Não | P49: Não | Q49: Não | R49: Não | S49: Não | T49: 158927.24 | U49: 600 | V49: 0 | W49: 124834.24 | X49: 35113 | Y49: 0 | Z49: 159947.24 | AA49: 0 | AB49: 0 | AD49: 8787719074200 | AE49: Contrato Adimplente | AF49: 74091 | AG49: 45386 | AH49: 3559.97 | AI49: 45351 | AJ49: 2004 | AK49: 45320 | AP49: Endy Carvalho Consultoria imobiliária | AT49: 45503 | AU49: 45503 | AV49: VENDA FINALIZADA | AW49: 45321 | AX49: 20513 | AY49: 215000.04 | BA49: FSA09 | BB49: 20513 | BD49: Formosa | BE49: Goiás | BF49: 5561996296114 | BG49: Rua 1 Q A L 30 | BH49: 73808715 | BI49: Setor Bela Vista ll | BJ49: tatianeramosdeaquino@gmail.com | BL49: 2000 | BM49: 45487 | BQ49: 3163 | BR49: 5419 | BS49: Auxiliar | BT49: 45316 | BW49: sim | BY49: MP134460 | BZ49: 45316 | CA49: 45345 | CC49: 45320 | CD49: Sim | CF49: 45316 | CL49: 45321 | CM49: 45351 | CN49: 45320 | CO49: 45352 | CP49: 45356 | CR49: 45321 | CS49: 45323 | CT49: 45487 | CU49: 45364 | CV49: 45364 | CW49: 45323 | CY49: Sim | DD49: 45351 | DF49: 45386 | DI49: 45387 | DJ49: 45317 | DK49: 45364 | DL49: 45365 | DM49: 45371 | DN49: 45383 | DO49: 45323 | DP49: OK | EE49: 2358.21
A50: 3229 | B50: PROCESSO FINALIZADO | C50: 3763 | D50: FSA009 - VILA DOS IPÊS | E50: Única | F50: BLOCO O | G50: 2 | H50: FORMOSA | I50: MICHAEL PEREIRA DOS SANTOS | J50: "06871962131" | K50: EQUIPE PRÓPRIA |FSA | L50: GABRIEL DO NASCIMENTO DIAS - CLT | M50: Não | N50: Não | O50: Não | P50: Não | Q50: Não | R50: Não | S50: Não | T50: 159221.81 | U50: 957.3 | V50: 0 | W50: 154695.81 | X50: 4526 | Y50: 0 | Z50: 159221.81 | AA50: 0 | AB50: 0 | AD50: 8787718978491 | AE50: Contrato Adimplente | AF50: 74187 | AG50: 45357 | AH50: 3936.52 | AI50: 45343 | AJ50: 2004 | AK50: 45320 | AP50: Endy Carvalho Consultoria imobiliária | AT50: 45503 | AU50: 45503 | AV50: VENDA FINALIZADA | AW50: 45321 | AX50: 20512 | AY50: 215000 | BA50: FSA09 | BB50: 20512 | BD50: Formosa | BE50: Goiás | BF50: 5561998498969 | BG50: RUA 13, Q 33, L 15 | BH50: 73800000 | BI50: JARDIM OLIVEIRA | BJ50: MichaelPereira1243@gmail.com | BL50: 3191.1 | BM50: 45483 | BQ50: 3250 | BR50: 254 | BS50: Eletricista | BT50: 45307 | BW50: sim | BY50: MP134462 | BZ50: 45307 | CA50: 45341 | CC50: 45321 | CD50: Sim | CF50: 45307 | CL50: 45321 | CM50: 45343 | CN50: 45321 | CO50: 45352 | CR50: 45322 | CS50: 45330 | CT50: 45483 | CV50: 45364 | CW50: 45330 | CY50: Sim | DD50: 45321 | DF50: 45357 | DI50: 45358 | DJ50: 45320 | DK50: 45364 | DL50: 45366 | DM50: 45371 | DN50: 45383 | DO50: 45330 | DP50: OK
A51: 3230 | B51: PROCESSO FINALIZADO | C51: 3770 | D51: FSA009 - VILA DOS IPÊS | E51: Única | F51: BLOCO F | G51: 303 | H51: FORMOSA | I51: CARLA ALVIS DE ALMEIDA | J51: "06418296125" | K51: EQUIPE PRÓPRIA |FSA | L51: TAKADA IMOB | M51: Não | N51: Não | O51: Não | P51: Não | Q51: Não | R51: Não | S51: Não | T51: 151587.93 | U51: 600 | V51: 0 | W51: 116972.93 | X51: 34617 | Y51: 0 | Z51: 151589.93 | AA51: 0 | AB51: 0 | AD51: 8787719060234 | AE51: Contrato Adimplente | AF51: 74056 | AG51: 45366 | AH51: 2849.02 | AI51: 45348 | AJ51: 2004 | AK51: 45321 | AP51: Endy Carvalho Consultoria imobiliária | AT51: 45503 | AU51: 45503 | AV51: VENDA FINALIZADA | AW51: 45322 | AX51: 20580 | AY51: 205387.93 | BA51: FSA09 | BB51: 20580 | BD51: Formosa | BE51: Goiás | BF51: 5561996518653 | BG51: RUA 15 Q E | BH51: 73807265 | BI51: SETOR NORDESTE | BJ51: carlaalvis776@gmail.com | BL51: 2000 | BM51: 45486 | BQ51: 3120 | BR51: 5422 | BS51: Cuidador de Idosos | BT51: 45309 | BW51: sim | BY51: MP134464 | BZ51: 45309 | CA51: 45344 | CC51: 45321 | CD51: Sim | CF51: 45309 | CL51: 45322 | CM51: 45348 | CN51: 45321 | CO51: 45352 | CR51: 45322 | CS51: 45341 | CT51: 45486 | CV51: 45364 | CW51: 45337 | CY51: Sim | DD51: 45321 | DF51: 45366 | DI51: 45369 | DJ51: 45316 | DK51: 45364 | DL51: 45366 | DM51: 45371 | DN51: 45383 | DO51: 45331 | DP51: OK
A52: 3231 | B52: PROCESSO FINALIZADO | C52: 3750 | D52: FSA009 - VILA DOS IPÊS | E52: Única | F52: BLOCO J | G52: 301 | H52: FORMOSA | I52: REGIO AUGUSTO RISSATI GERMANA | J52: "35806597822" | K52: EQUIPE PRÓPRIA |FSA | L52: GABRIEL DO NASCIMENTO DIAS - CLT | M52: Não | N52: Não | O52: Não | P52: Não | Q52: Não | R52: Não | S52: Não | T52: 158488.71 | U52: 599.99 | V52: 58611.19 | W52: 123882.71 | X52: 34606 | Y52: 0 | Z52: 158488.71 | AA52: 0 | AB52: 0 | AD52: 8787719049435 | AE52: Contrato Adimplente | AF52: 74118 | AG52: 45359 | AH52: 3544.37 | AI52: 45348 | AJ52: 2004 | AK52: 45321 | AP52: Endy Carvalho Consultoria imobiliária | AT52: 45503 | AU52: 45503 | AV52: VENDA FINALIZADA | AW52: 45322 | AX52: 20579 | AY52: 215000.71 | BA52: FSA09 | BB52: 20579 | BD52: Formosa | BE52: Goiás | BF52: 5561996369353 | BG52: RUA 1, Q 12 | BH52: 73813601 | BI52: São Benedito | BJ52: regioalgustorissatigermana@gmail.com | BL52: 2000 | BM52: 45483 | BQ52: 3181 | BR52: 5421 | BS52: Mecânico | BT52: 45303 | BW52: sim | BY52: MP134463 | BZ52: 45303 | CA52: 45344 | CC52: 45321 | CD52: Sim | CF52: 45303 | CL52: 45322 | CM52: 45348 | CN52: 45321 | CO52: 45352 | CR52: 45322 | CS52: 45341 | CT52: 45483 | CV52: 45364 | CW52: 45337 | CY52: Sim | DD52: 45321 | DF52: 45360 | DI52: 45362 | DJ52: 45321 | DK52: 45364 | DL52: 45366 | DM52: 45371 | DN52: 45383 | DO52: 45331 | DP52: OK
A53: 3232 | B53: PROCESSO FINALIZADO | C53: 3794 | D53: FSA009 - VILA DOS IPÊS | E53: Única | F53: BLOCO G | G53: 302 | H53: FORMOSA | I53: VITOR CARIOLANO DA SILVA | J53: "08206286110" | K53: AUTÔNOMOS | FSA | L53: ALANA RABELO DA COSTA | M53: Não | N53: Não | O53: Não | P53: Não | Q53: Não | R53: Não | S53: Não | T53: 150339.35 | U53: 547.45 | V53: 89900.65 | W53: 107138.83 | X53: 43198 | Y53: 0 | Z53: 150336.83 | AA53: 0 | AB53: 0 | AD53: 8787719123384 | AE53: Contrato Adimplente | AF53: 74071 | AG53: 45359 | AH53: 3559.94 | AI53: 45348 | AJ53: 2004 | AK53: 45322 | AP53: Endy Carvalho Consultoria imobiliária | AT53: 45503 | AU53: 45503 | AV53: VENDA FINALIZADA | AW53: 45316 | AX53: 20606 | AY53: 215000.08 | BA53: FSA09 | BB53: 20606 | BC53: ROSANGELA DA SILVA OLIVEIRA COSTA - 02010175123 | BD53: Formosa | BE53: Goiás | BF53: 5561996731796 | BG53: Rua 22 Q 37 | BH53: 73808425 | BI53: Parque Vila Verde | BJ53: vcariolano@gmail.com | BL53: 1824.86 | BM53: 45495 | BQ53: 3126 | BR53: 5425 | BS53: Assistente | BT53: 45331 | BW53: sim | BY53: MP134465 | BZ53: 45331 | CA53: 45344 | CC53: 45322 | CD53: Sim | CF53: 45331 | CL53: 45336 | CM53: 45348 | CN53: 45322 | CO53: 45352 | CR53: 45323 | CS53: 45330 | CT53: 45495 | CV53: 45364 | CW53: 45330 | CY53: Sim | DD53: 45344 | DF53: 45360 | DI53: 45362 | DJ53: 45324 | DK53: 45364 | DL53: 45370 | DM53: 45379 | DN53: 45383 | DO53: 45329 | DP53: OK
A54: 3233 | B54: PROCESSO FINALIZADO | C54: 3767 | D54: FSA009 - VILA DOS IPÊS | E54: Única | F54: BLOCO K | G54: 203 | H54: FORMOSA | I54: ALAN DA SILVA GUEDES | J54: "11808385640" | K54: EQUIPE PRÓPRIA |FSA | L54: GABRIEL DO NASCIMENTO DIAS - CLT | M54: Não | N54: Não | O54: Não | P54: Não | Q54: Não | R54: Não | S54: Não | T54: 149128.42 | U54: 705 | V54: 0 | W54: 134471.42 | X54: 14657 | Y54: 0 | Z54: 149128.42 | AA54: 0 | AB54: 0 | AD54: 8787719122680 | AE54: Contrato Adimplente | AF54: 74132 | AG54: 45366 | AH54: 2849.02 | AI54: 45348 | AJ54: 2004 | AK54: 45322 | AP54: Endy Carvalho Consultoria imobiliária | AT54: 45503 | AU54: 45503 | AV54: VENDA FINALIZADA | AW54: 45307 | AX54: 20605 | AY54: 205000 | BA54: FSA09 | BB54: 20605 | BD54: Formosa | BE54: Goiás | BF54: 5538997366952 | BG54: Avenida Perimetral, Q 90-E | BH54: 73808365 | BI54: Parque Vila Verde | BJ54: alanguedes.top@gmail.com | BL54: 2600 | BM54: 45489 | BQ54: 3195 | BR54: 5424 | BS54: Autônomo(a) | BT54: 45308 | BW54: sim | BY54: MP134467 | BZ54: 45308 | CA54: 45344 | CC54: 45323 | CD54: Sim | CF54: 45308 | CL54: 45323 | CM54: 45348 | CN54: 45323 | CO54: 45352 | CR54: 45327 | CS54: 45330 | CT54: 45487 | CV54: 45364 | CW54: 45330 | CY54: Sim | DD54: 45331 | DF54: 45366 | DI54: 45369 | DJ54: 45324 | DK54: 45364 | DL54: 45366 | DM54: 45371 | DN54: 45383 | DO54: 45329 | DP54: OK
A55: 3234 | B55: PROCESSO FINALIZADO | C55: 3762 | D55: FSA009 - VILA DOS IPÊS | E55: Única | F55: BLOCO Q | G55: 2 | H55: FORMOSA | I55: MARCIEL CARDOSO DOS SANTOS | J55: "89194349134" | K55: EQUIPE PRÓPRIA |FSA | L55: TAKADA IMOB | M55: Não | N55: Não | O55: Não | P55: Não | Q55: Não | R55: Não | S55: Não | T55: 158638.61 | U55: 712.49 | V55: 51361.39 | W55: 138017.61 | X55: 21265 | Y55: 0 | Z55: 159282.61 | AA55: 0 | AB55: 0 | AD55: 8787718975476 | AE55: Contrato Adimplente | AF55: 74219 | AG55: 45349 | AH55: 3559.94 | AI55: 45338 | AJ55: 2004 | AK55: 45322 | AP55: Endy Carvalho Consultoria imobiliária | AT55: 45503 | AU55: 45503 | AV55: VENDA FINALIZADA | AW55: 45306 | AX55: 20604 | AY55: 215000.14 | BA55: FSA09 | BB55: 20604 | BD55: Cabeceiras | BE55: Goiás | BF55: 5561998828332 | BG55: AV. BRASILIA Q 17 L 02 | BH55: 73870000 | BI55: SETOR MARIANO MACHADO | BJ55: Cielcs@hotmail.com | BL55: 2375 | BM55: 45483 | BQ55: 3282 | BR55: 5423 | BS55: Auxiliar | BT55: 45321 | BW55: sim | BZ55: 45321 | CA55: 45329 | CC55: 45323 | CD55: Sim | CF55: 45321 | CL55: 45323 | CM55: 45329 | CN55: 45323 | CO55: 45337 | CP55: 45341 | CR55: 45323 | CS55: 45323 | CT55: 45483 | CV55: 45338 | CW55: 45323 | CY55: Sim | DB55: 45324 | DD55: 45329 | DE55: 45328 | DF55: 45349 | DI55: 45350 | DJ55: 45321 | DK55: 45338 | DL55: 45371 | DM55: 45379 | DN55: 45383 | DO55: 45323 | DP55: OK
A56: 3235 | B56: PROCESSO FINALIZADO | C56: 3743 | D56: FSA009 - VILA DOS IPÊS | E56: Única | F56: BLOCO O | G56: 202 | H56: FORMOSA | I56: JOÃO PEDRO TEIXEIRA DE SOUSA | J56: "06728859136" | K56: EQUIPE PRÓPRIA |FSA | L56: TAKADA IMOB | M56: Não | N56: Não | O56: Não | P56: Não | Q56: Não | R56: Não | S56: Não | T56: 159321.28 | U56: 600 | V56: 0 | W56: 124715.28 | X56: 34606 | Y56: 0 | Z56: 159321.28 | AA56: 0 | AB56: 0 | AD56: 8787719088104 | AE56: Contrato Adimplente | AF56: 74195 | AG56: 45365 | AH56: 2849.02 | AI56: 45344 | AJ56: 2004 | AK56: 45323 | AP56: Endy Carvalho Consultoria imobiliária | AT56: 45503 | AU56: 45503 | AV56: VENDA FINALIZADA | AW56: 45302 | AX56: 20651 | AY56: 215000.23 | BA56: FSA09 | BB56: 20651 | BD56: Formosa | BE56: Goiás | BF56: 5561991433193 | BG56: RUA VERA CRUZ | BH56: 73805325 | BI56: SETOR PAMPULHA | BJ56: joaopedroteixeiradesousa@gmail.com | BL56: 2200 | BM56: 45480 | BQ56: 3258 | BR56: 5427 | BS56: Analista | BT56: 45322 | BW56: sim | BY56: MP134469 | BZ56: 45322 | CA56: 45342 | CC56: 45324 | CD56: Sim | CF56: 45322 | CL56: 45324 | CM56: 45344 | CN56: 45324 | CO56: 45352 | CR56: 45327 | CS56: 45323 | CT56: 45480 | CV56: 45364 | CW56: 45323 | CY56: Sim | DD56: 45324 | DF56: 45366 | DI56: 45369 | DJ56: 45319 | DK56: 45364 | DL56: 45365 | DM56: 45371 | DN56: 45383 | DO56: 45323 | DP56: OK
A57: 3236 | B57: DISTRATO | C57: 3802 | D57: DF001 - HAUS | E57: ETAPA 01 | F57: TORRE | G57: 503 | H57: BRASÍLIA | I57: ANNA MOREL FARIA GARCIA | J57: "05984426188" | K57: PSI NEGOCIOS IMOBILIARIOS LTDA | L57: PSI NEGOCIOS IMOBILIARIOS LTDA | M57: Não | N57: Não | O57: Não | P57: Não | Q57: Não | R57: Não | S57: Não | T57: 968959 | U57: 0 | V57: 0 | W57: 968959 | X57: 0 | Y57: 0 | Z57: 968959 | AA57: 0 | AB57: 0 | AE57: Contrato Adimplente | AH57: 0 | AK57: 45323 | AP57: GRUPO IMERGE | AQ57: Eduardo - Crédito Novka | AT57: 45756 | AU57: 45756 | AV57: DISTRATO | AW57: 45317 | AX57: 20620 | AY57: 968959 | BA57: DF 001 | BB57: 20620 | BD57: Brasília | BE57: Distrito Federal | BF57: 5561992906038 | BG57: CCSW 2 Lote 4 | BH57: 70680270 | BI57: Setor Sudoeste | BJ57: annamorel51@gmail.com | BL57: 16949 | BO57: Eduardo Martins (Gestor): Cliente me enviou uma mensagem informando que vai decidir pelo distrato mesmo. Segue mensagem enviada pela cliente. "Realmente, optamos pelo destrato. O valor da parcela ficará muito além do que imaginamos, foi nos passado que poderia ser até 9mil, inicialmente falaram até 6 mil, então ficou bem puxado e mesmo alugando, não compensa". | BP57: 13/03/2025 às 14h55 | BQ57: 2966 | BR57: 5426 | BS57: Empresario
A58: 3237 | B58: PROCESSO FINALIZADO | C58: 3785 | D58: FSA009 - VILA DOS IPÊS | E58: Única | F58: BLOCO G | G58: 2 | H58: FORMOSA | I58: THALITA RAMBO RIBEIRO | J58: "07933447198" | K58: EQUIPE PRÓPRIA |FSA | L58: INGRID ALVES D'APARECIDA - CLT | M58: Não | N58: Não | O58: Não | P58: Não | Q58: Não | R58: Não | S58: Não | T58: 163604.21 | U58: 689.99 | V58: 0 | W58: 140218.21 | X58: 23740 | Y58: 0 | Z58: 163958.21 | AA58: 0 | AB58: 0 | AD58: 8787719095704 | AE58: Contrato Adimplente | AG58: 45357 | AH58: 3559.94 | AI58: 45342 | AJ58: 2004 | AK58: 45323 | AP58: Endy Carvalho Consultoria imobiliária | AT58: 45503 | AU58: 45503 | AV58: VENDA FINALIZADA | AW58: 45313 | AX58: 20652 | AY58: 217404.21 | BA58: FSA09 | BB58: 20652 | BD58: Formosa | BE58: Goiás | BF58: 5561999990795 | BG58: TRAV 19 | BH58: 73000000 | BI58: SETOR SUL | BJ58: thalitarambo59@gmail.com | BL58: 2300 | BM58: 45493 | BQ58: 3131 | BR58: 5428 | BS58: Recepcionista | BT58: 45313 | BW58: sim | BY58: MP134468 | BZ58: 45313 | CA58: 45337 | CC58: 45324 | CD58: Sim | CF58: 45313 | CG58: 45323 | CI58: 45324 | CJ58: 45339 | CL58: 45324 | CM58: 45342 | CN58: 45324 | CO58: 45352 | CR58: 45327 | CS58: 45325 | CT58: 45493 | CV58: 45364 | CW58: 45325 | DB58: 45331 | DD58: 45329 | DE58: 45337 | DF58: 45357 | DI58: 45387 | DJ58: 45322 | DK58: 45364 | DL58: 45366 | DM58: 45371 | DN58: 45383 | DO58: 45325 | DP58: OK
A59: 3238 | B59: PROCESSO FINALIZADO | C59: 3748 | D59: FSA009 - VILA DOS IPÊS | E59: Única | F59: BLOCO N | G59: 302 | H59: FORMOSA | I59: CARLA MARTINS NOGUEIRA | J59: "05624236131" | K59: AUTÔNOMOS | FSA | L59: ROMÁRIO AUGUSTO NEGÓCIOS IMOBILIÁRIOS LTDA. | M59: Não | N59: Não | O59: Não | P59: Não | Q59: Não | R59: Não | S59: Não | T59: 164200 | U59: 1073.2 | V59: 0 | W59: 163648 | X59: 552 | Y59: 0 | Z59: 164200 | AA59: 0 | AB59: 0 | AD59: 8787719108130 | AE59: Contrato Adimplente | AF59: 74183 | AG59: 45357 | AH59: 3936.52 | AI59: 45343 | AJ59: 2004 | AK59: 45324 | AP59: Endy Carvalho Consultoria imobiliária | AT59: 45503 | AU59: 45503 | AV59: VENDA FINALIZADA | AW59: 45327 | AX59: 20702 | AY59: 218000 | BA59: FSA09 | BB59: 20702 | BD59: Formosa | BE59: Goiás | BF59: 5561983282286 | BG59: Rua 4 L.200 | BH59: 73813615 | BI59: São Benedito | BJ59: carlanogueiramart@gmail.com | BL59: 4111.55 | BM59: 45481 | BQ59: 3246 | BR59: 5430 | BS59: Tecnico em Enfermagem | BT59: 45322 | BW59: sim | BY59: MP134470 | BZ59: 45322 | CA59: 45341 | CC59: 45327 | CD59: Sim | CF59: 45322 | CL59: 45327 | CM59: 45343 | CN59: 45327 | CO59: 45352 | CR59: 45328 | CS59: 45327 | CV59: 45364 | CW59: 45327 | CY59: Sim | DD59: 45327 | DF59: 45357 | DI59: 45359 | DJ59: 45323 | DK59: 45364 | DL59: 45366 | DM59: 45371 | DN59: 45383 | DO59: 45327 | DP59: OK
A60: 3239 | B60: PROCESSO FINALIZADO | C60: 3801 | D60: AGL029 - VILA FLAMBOYANT | E60: Etapa Unica | F60: BLOCO G | G60: 101 | H60: ÁGUAS LINDAS | I60: LEILISON ALEFF DE FREITAS SOUSA | J60: "11135057613" | K60: EQUIPE PRÓPRIA | AGL | L60: JOSUÉ GOMES DE SOUZA | M60: Não | N60: Não | O60: Não | P60: Sim | Q60: Sim | R60: Não | S60: Não | T60: 127910.02 | U60: 718.92 | V60: 0 | W60: 117848.85 | X60: 9857 | Y60: 0 | Z60: 127705.85 | AA60: 0 | AB60: 0 | AD60: 8787719102689 | AE60: Contrato Adimplente | AF60: 105320 | AG60: 45373 | AH60: 2740.25 | AI60: 45351 | AJ60: 2004 | AK60: 45327 | AP60: Endy Carvalho Consultoria imobiliária | AT60: 45736 | AU60: 45736 | AV60: VENDA FINALIZADA | AW60: 45317 | AX60: 20890 | AY60: 190000.42 | BA60: AGL29 | BB60: 20890 | BD60: Águas Lindas de Goiás | BE60: Goiás | BF60: 5561993626382 | BG60: RUA SEM NOME QUADRA 09 LOTE | BH60: 72910001 | BI60: CONDOMINIO BELA VISTA | BJ60: l.aleff@hotmail.com | BL60: 2875.69 | BO60: Denise Batista da Silva Nunes (Gestor): 1. Apresentar procuração referente a alienante, incorporadora e entidade organizadora e fiadora. Obs.: a procuração citada não corresponde. Deverá também fazer ressalva no contrato quanto aos dados. 2. Apresentar procuração referente a construtora e fiadora. Obs.: a procuração citada não corresponde. Deverá também fazer ressalva no contrato quanto aos dados. | BP60: 20/03/2024 às 15h59 | BQ60: 3409 | BR60: 5431 | BS60: Operador de Loja | BT60: 45350 | BU60: 500 | BV60: 45365 | BW60: sim | BX60: 45369 | BY60: MP140254 | BZ60: 45350 | CA60: 45355 | CC60: 45327 | CD60: Sim | CF60: 45350 | CJ60: 45359 | CL60: 45350 | CM60: 45364 | CN60: 45327 | CO60: 45414 | CP60: 45355 | CR60: 45328 | CS60: 45327 | CU60: 45357 | CV60: 45450 | CW60: 45327 | CX60: 45397 | CY60: Sim | CZ60: 45371 | DC60: 45372 | DD60: 45324 | DF60: 45376 | DI60: 45378 | DJ60: 45323 | DK60: 45450 | DL60: 45606 | DM60: 45629 | DN60: 45712 | DO60: 45327 | DP60: 45712 | EE60: 3805.32
A61: 3240 | B61: PROCESSO FINALIZADO | C61: 3824 | D61: FSA009 - VILA DOS IPÊS | E61: Única | F61: BLOCO N | G61: 202 | H61: FORMOSA | I61: MARYANA NAYELLE DIAS DE OLIVEIRA | J61: "06878128102" | K61: AUTÔNOMOS | FSA | L61: KAROLYNA APARECIDA ALVES DE ARAUJO | M61: Não | N61: Não | O61: Não | P61: Não | Q61: Não | R61: Não | S61: Não | T61: 138250.06 | U61: 570 | V61: 0 | W61: 115222.06 | X61: 23028 | Y61: 0 | Z61: 138250.06 | AA61: 0 | AB61: 0 | AD61: 8787719160832 | AE61: Contrato Adimplente | AG61: 45600 | AH61: 5515.43 | AI61: 45362 | AJ61: 2004 | AK61: 45328 | AP61: Endy Carvalho Consultoria imobiliária | AT61: 45743 | AU61: 45743 | AV61: VENDA FINALIZADA | AW61: 45328 | AX61: 20781 | AY61: 215000 | BA61: FSA09 | BB61: 20781 | BC61: VANIA APARECIDA CAETANO DA SILVA - 37419650225 | BD61: Formosa | BE61: Goiás | BF61: 5562982392986 | BG61: Rua 15 Q 137 L 6 | BH61: 73813220 | BI61: Formosinha | BJ61: maryanadiasoliveira2@outlook.com.br | BL61: 2300 | BM61: 45500 | BQ61: 3242 | BR61: 5432 | BS61: Autônomo(a) | BT61: 45344 | BW61: sim | BY61: MP134471 | BZ61: 45344 | CC61: 45328 | CD61: Sim | CF61: 45344 | CL61: 45350 | CM61: 45379 | CN61: 45328 | CO61: 45366 | CR61: 45329 | CS61: 45345 | CT61: 45500 | CV61: 45366 | CW61: 45344 | CY61: Sim | DB61: 45345 | DC61: 45580 | DD61: 45359 | DE61: 45358 | DF61: 45601 | DI61: 45602 | DJ61: 45329 | DK61: 45387 | DL61: 45461 | DM61: 45504 | DN61: 45728 | DO61: 45344 | DP61: 45728
A62: 3241 | B62: PROCESSO FINALIZADO | C62: 3812 | D62: AGL028 - VILA DO CERRADO | E62: ETAPA 01 | F62: BLOCO V | G62: 3 | H62: ÁGUAS LINDAS | I62: YAGO MATHEUS DE SOUZA MESQUITA | J62: "05572906190" | K62: EQUIPE PRÓPRIA | AGL | L62: TIAGO WILIS - CLT | M62: Não | N62: Não | O62: Não | P62: Sim | Q62: Sim | R62: Não | S62: Não | T62: 162675.48 | U62: 626.07 | V62: 0 | W62: 126568.22 | X62: 35739 | Y62: 0 | Z62: 162307.22 | AA62: 0 | AB62: 0 | AD62: 8787719111718 | AE62: Contrato Adimplente | AF62: 96345 | AG62: 45352 | AH62: 2740.25 | AI62: 45331 | AJ62: 2004 | AK62: 45328 | AP62: Endy Carvalho Consultoria imobiliária | AT62: 45744 | AU62: 45744 | AV62: VENDA FINALIZADA | AW62: 45321 | AX62: 20782 | AY62: 212000.27 | BA62: AGL28 | BB62: 20782 | BD62: Cidade Ocidental | BE62: Goiás | BF62: 5561984560550 | BG62: QUADRA 49 - A LOTE 49 | BH62: 72880000 | BI62: RESIDENCIAL MORADA DAS GARCAS | BJ62: Ymatheus179@gmail.com | BL62: 2086.95 | BM62: 45490 | BQ62: 3057 | BR62: 5433 | BS62: Auxiliar | BT62: 45324 | BU62: 367.7 | BV62: 45337 | BW62: sim | BX62: 45336 | BY62: MP129689 | BZ62: 45324 | CA62: 45342 | CC62: 45328 | CD62: Sim | CF62: 45324 | CG62: 45327 | CJ62: 45344 | CL62: 45328 | CM62: 45345 | CN62: 45328 | CO62: 45352 | CP62: 45342 | CR62: 45329 | CS62: 45328 | CU62: 45342 | CV62: 45363 | CW62: 45328 | CY62: Sim | DD62: 45322 | DF62: 45355 | DI62: 45357 | DJ62: 45323 | DK62: 45364 | DL62: 45367 | DM62: 45386 | DN62: 45624 | DO62: 45327 | DP62: 45624 | EE62: 4105.32
A63: 3242 | B63: PROCESSO FINALIZADO | C63: 3821 | D63: FSA009 - VILA DOS IPÊS | E63: Única | F63: BLOCO A | G63: 1 | H63: FORMOSA | I63: JANAINA LOPES DOS SANTOS | J63: "05772812165" | K63: EQUIPE PRÓPRIA |FSA | L63: KÁLITA CRISTINE MARTINS FRADE - CLT | M63: Não | N63: Não | O63: Não | P63: Não | Q63: Não | R63: Não | S63: Não | T63: 157000 | U63: 600 | V63: 0 | W63: 121627 | X63: 35373 | Y63: 0 | Z63: 157000 | AA63: 0 | AB63: 0 | AD63: 8787719157815 | AE63: Contrato Adimplente | AF63: 73962 | AG63: 45357 | AH63: 3568.17 | AI63: 45344 | AJ63: 2004 | AK63: 45328 | AP63: Endy Carvalho Consultoria imobiliária | AT63: 45503 | AU63: 45503 | AV63: VENDA FINALIZADA | AW63: 45322 | AX63: 20816 | AY63: 202800 | BA63: FSA09 | BB63: 20816 | BD63: Formosa | BE63: Goiás | BF63: 556191300185 | BG63: RUA 18 | BH63: 73805241 | BI63: JARDIM OLIVEIRA | BJ63: janaiina_lopes@hotmail.com | BL63: 2000 | BM63: 45486 | BQ63: 3025 | BR63: 5435 | BS63: Gerente comercial | BT63: 45322 | BW63: sim | BY63: MP134472 | BZ63: 45322 | CA63: 45342 | CC63: 45329 | CD63: Sim | CF63: 45322 | CL63: 45328 | CM63: 45344 | CN63: 45329 | CO63: 45352 | CR63: 45330 | CS63: 45336 | CT63: 45486 | CV63: 45364 | CW63: 45336 | CY63: Sim | DD63: 45343 | DF63: 45357 | DI63: 45358 | DJ63: 45329 | DK63: 45364 | DL63: 45370 | DM63: 45379 | DN63: 45383 | DO63: 45336 | DP63: OK
A64: 3243 | B64: PROCESSO FINALIZADO | C64: 3813 | D64: FSA007 - VILA DAS HORTÊNSIAS | E64: Etapa | F64: BLOCO I | G64: 204 | H64: FORMOSA | I64: HIGOR DE MOURA SILVA | J64: "03971668690" | K64: CANAL VIRTUAL | L64: JÉSSICA NOGUEIRA DE SOUSA - CLT | M64: Não | N64: Não | O64: Não | P64: Não | Q64: Não | R64: Não | S64: Não | T64: 166112.97 | U64: 900 | V64: 0 | W64: 159401.97 | X64: 6711 | Y64: 0 | Z64: 166112.97 | AA64: 0 | AB64: 0 | AD64: 8787719162053 | AE64: Contrato Adimplente | AF64: 72778 | AG64: 45369 | AH64: 3233.84 | AI64: 45351 | AJ64: 2004 | AK64: 45328 | AP64: Endy Carvalho Consultoria imobiliária | AT64: 46098 | AU64: 46098 | AV64: VENDA FINALIZADA | AW64: 45321 | AX64: 20815 | AY64: 215000 | BA64: FSA07 | BB64: 20815 | BD64: Formosa | BE64: Goiás | BF64: 5561999950202 | BG64: RUA VISCONDE DE PORTO SEGURO | BH64: 73801010 | BI64: CENTRO | BJ64: higormoura@gmail.com | BL64: 3000 | BQ64: 979 | BR64: 5434 | BS64: Auxiliar | BT64: 45321 | BW64: sim | BY64: MP139501 | BZ64: 45321 | CA64: 45345 | CC64: 45329 | CD64: Sim | CF64: 45321 | CL64: 45328 | CM64: 45351 | CN64: 45330 | CO64: 45352 | CP64: 45356 | CR64: 45330 | CS64: 45337 | CT64: 45411 | CU64: 45364 | CV64: 45364 | CW64: 45337 | CY64: Sim | DD64: 45351 | DF64: 45369 | DI64: 45370 | DJ64: 45329 | DK64: 45364 | DL64: 45383 | DM64: 45502 | DN64: 46057 | DO64: 45336 | DP64: 46057 | EE64: 1794.61
A65: 3244 | B65: PROCESSO FINALIZADO | C65: 3764 | D65: AGL029 - VILA FLAMBOYANT | E65: Etapa Unica | F65: BLOCO F | G65: 104 | H65: ÁGUAS LINDAS | I65: INGRID LORRANE BARCELAR DOS REIS | J65: "09863402192" | K65: IMOBILIÁRIAS | AGL | L65: DIEGO REIS IMOBILIÁRIA | M65: Não | N65: Não | O65: Não | P65: Sim | Q65: Sim | R65: Não | S65: Não | T65: 132612.69 | U65: 642.54 | V65: 74698.47 | W65: 115184.55 | X65: 17430 | Y65: 0 | Z65: 132614.55 | AA65: 0 | AB65: 0 | AD65: 8787719026966 | AE65: Contrato Adimplente | AF65: 105307 | AG65: 45373 | AH65: 2740.25 | AI65: 45351 | AJ65: 2004 | AK65: 45329 | AP65: Endy Carvalho Consultoria imobiliária | AT65: 45736 | AU65: 45736 | AV65: VENDA FINALIZADA | AW65: 45306 | AX65: 20964 | AY65: 190000.49 | BA65: AGL29 | BB65: 20964 | BC65: CIDCLAY MENDES MATOS - 71146529171,LIDIANA BARCELAR RODRIGUES - 03868637176 | BD65: Águas Lindas de Goiás | BE65: Goiás | BF65: 5561981275781 | BG65: Q 08 | BH65: 72910000 | BI65: JARDIM SANTA LUCIA | BJ65: LORRANEI417@GMAIL.COM | BL65: 1470.19 | BO65: Denise Batista da Silva Nunes (Gestor): Exigência: 1. Apresentar procuração referente a alienante, incorporadora e entidade organizadora e fiadora. Obs.: a procuração citada não corresponde. Deverá também fazer ressalva no contrato quanto aos dados. 2. Apresentar procuração referente a construtora e fiadora. Obs.: a procuração citada não corresponde. Deverá também fazer ressalva no contrato quanto aos dados. | BP65: 20/03/2024 às 15h48 | BQ65: 3408 | BR65: 5437 | BS65: Faxineiro | BT65: 45345 | BU65: 486.31 | BV65: 45365 | BW65: sim | BX65: 45359 | BY65: MP140255 | BZ65: 45345 | CA65: 45355 | CC65: 45329 | CD65: Sim | CF65: 45345 | CJ65: 45359 | CL65: 45348 | CM65: 45364 | CN65: 45330 | CO65: 45414 | CP65: 45355 | CR65: 45330 | CS65: 45327 | CU65: 45357 | CV65: 45450 | CW65: 45327 | CX65: 45366 | CY65: Sim | CZ65: 45371 | DC65: 45372 | DD65: 45316 | DF65: 45376 | DI65: 45377 | DJ65: 45322 | DK65: 45450 | DL65: 45606 | DM65: 45693 | DN65: 45712 | DO65: 45327 | DP65: 45712 | EE65: 3805.32
A66: 3245 | B66: PROCESSO FINALIZADO | C66: 3765 | D66: FSA009 - VILA DOS IPÊS | E66: Única | F66: BLOCO O | G66: 201 | H66: FORMOSA | I66: VANESA PEREIRA DOS SANTOS | J66: "04399301112" | K66: AUTÔNOMOS | FSA | L66: LAYNNE KAMYLLA OLIVEIRA BORGES FONSECA | M66: Não | N66: Não | O66: Não | P66: Não | Q66: Não | R66: Não | S66: Não | T66: 164200 | U66: 787.22 | V66: 0 | W66: 150201 | X66: 13999 | Y66: 0 | Z66: 164200 | AA66: 0 | AB66: 0 | AD66: 8787719174442 | AE66: Contrato Adimplente | AF66: 74194 | AG66: 45370 | AH66: 3225.6 | AI66: 45351 | AJ66: 2004 | AK66: 45329 | AP66: Endy Carvalho Consultoria imobiliária | AT66: 45503 | AU66: 45503 | AV66: VENDA FINALIZADA | AW66: 45306 | AX66: 20913 | AY66: 218000 | BA66: FSA09 | BB66: 20913 | BD66: Formosa | BE66: Goiás | BF66: 5562999089886 | BG66: Via 11-A L.09 | BH66: 73804060 | BI66: Chácaras Setor Abreu | BJ66: vanesapersonal09@gmail.com | BL66: 2624.07 | BM66: 45485 | BQ66: 3257 | BR66: 5439 | BS66: Assistente | BT66: 45316 | BW66: sim | BY66: MP134473 | BZ66: 45316 | CA66: 45345 | CC66: 45330 | CD66: Sim | CF66: 45316 | CJ66: 45359 | CL66: 45330 | CM66: 45351 | CN66: 45330 | CO66: 45352 | CP66: 45356 | CR66: 45338 | CS66: 45342 | CT66: 45483 | CV66: 45364 | CW66: 45342 | CY66: Sim | DD66: 45351 | DF66: 45371 | DI66: 45372 | DJ66: 45330 | DK66: 45364 | DL66: 45369 | DM66: 45371 | DN66: 45383 | DO66: 45342 | DP66: OK
A67: 3246 | B67: DISTRATO | C67: 3786 | D67: AGL029 - VILA FLAMBOYANT | E67: Etapa Unica | F67: BLOCO E | G67: 203 | H67: ÁGUAS LINDAS | I67: LUIMAR LOPES DA SILVA | J67: "94159750320" | K67: CANAL VIRTUAL | L67: JÉSSICA NOGUEIRA DE SOUSA - CLT | M67: Não | N67: Não | O67: Não | P67: Não | Q67: Não | R67: Não | S67: Não | T67: 121431.64 | U67: 729.99 | V67: 0 | W67: 118777.64 | X67: 2897 | Y67: 0 | Z67: 121674.64 | AA67: 0 | AB67: 0 | AE67: Contrato Adimplente | AH67: 0 | AK67: 45329 | AP67: Endy Carvalho Consultoria imobiliária | AT67: 45357 | AU67: 45357 | AV67: DISTRATO | AW67: 45314 | AX67: 20997 | AY67: 185000.44 | BA67: AGL29 | BB67: 20997 | BE67: Goiás | BF67: 5561986087685 | BG67: RUA SEM NOME, Q. 33 | BH67: 72910000 | BI67: PARQUE AGUAS BONITAS I | BJ67: luimarlopes65@gmail.com | BL67: 3436.08 | BM67: 45488 | BQ67: 3385 | BR67: 5440 | BS67: Eletricista | BT67: 44985 | BY67: MP140256 | CC67: 45330 | CN67: 45330 | CR67: 45337 | CS67: 45327 | CW67: 45327 | CY67: Sim | DD67: 45329 | DJ67: 45323 | DO67: 45327
A68: 3247 | B68: PROCESSO FINALIZADO | C68: 3789 | D68: FSA009 - VILA DOS IPÊS | E68: Única | F68: BLOCO E | G68: 204 | H68: FORMOSA | I68: JOYCE PEREIRA DA SILVA | J68: "07584934102" | K68: AUTÔNOMOS | FSA | L68: MILENA BOTELHO DE PAIVA DIAS | M68: Não | N68: Não | O68: Não | P68: Não | Q68: Não | R68: Não | S68: Não | T68: 151635.28 | U68: 471.38 | V68: 0 | W68: 97935.28 | X68: 53702 | Y68: 0 | Z68: 151637.28 | AA68: 0 | AB68: 0 | AD68: 8787719162487 | AE68: Contrato Adimplente | AF68: 74037 | AG68: 45357 | AH68: 3559.94 | AI68: 45344 | AJ68: 2004 | AK68: 45329 | AP68: Endy Carvalho Consultoria imobiliária | AT68: 45503 | AU68: 45503 | AV68: VENDA FINALIZADA | AW68: 45330 | AX68: 20914 | AY68: 205435.28 | BA68: FSA09 | BB68: 20914 | BD68: Formosa | BE68: Goiás | BF68: 5561996390459 | BG68: Rua 5 Q 52 L 10-A | BH68: 73813832 | BI68: Parque Lago | BJ68: jhoycesilva07@gmail.com | BL68: 1600 | BM68: 45492 | BQ68: 3093 | BR68: 5441 | BS68: Secretária | BT68: 45325 | BW68: sim | BY68: MP134474 | BZ68: 45325 | CA68: 45342 | CC68: 45330 | CD68: Sim | CF68: 45325 | CL68: 45330 | CM68: 45344 | CN68: 45330 | CO68: 45352 | CR68: 45338 | CS68: 45337 | CT68: 45488 | CV68: 45364 | CW68: 45337 | CY68: Sim | DD68: 45343 | DF68: 45357 | DI68: 45358 | DJ68: 45329 | DK68: 45364 | DL68: 45366 | DM68: 45371 | DN68: 45383 | DO68: 45337 | DP68: OK
A69: 3248 | B69: PROCESSO FINALIZADO | C69: 3820 | D69: FSA009 - VILA DOS IPÊS | E69: Única | F69: BLOCO R | G69: 203 | H69: FORMOSA | I69: PÂMELA CONCEIÇÃO EVANGELISTA | J69: "04453343124" | K69: EQUIPE PRÓPRIA |FSA | L69: KÁLITA CRISTINE MARTINS FRADE - CLT | M69: Não | N69: Não | O69: Não | P69: Não | Q69: Não | R69: Não | S69: Não | T69: 151587.93 | U69: 0 | V69: 0 | W69: 116972.93 | X69: 34617 | Y69: 0 | Z69: 151589.93 | AA69: 0 | AB69: 0 | AD69: 8787719174620 | AE69: Contrato Adimplente | AF69: 74244 | AG69: 45359 | AH69: 3559.94 | AI69: 45348 | AJ69: 2004 | AK69: 45329 | AP69: Endy Carvalho Consultoria imobiliária | AT69: 45503 | AU69: 45503 | AV69: VENDA FINALIZADA | AW69: 45322 | AX69: 20930 | AY69: 205387.98 | BA69: FSA09 | BB69: 20930 | BD69: Formosa | BE69: Goiás | BF69: 5561996982846 | BG69: AVENIDA FORMOSA Q 53 L 0 | BH69: 73813250 | BI69: FORMOSINHA | BJ69: pamelalemos134@gmail.com | BL69: 2000 | BQ69: 3310 | BR69: 281 | BS69: Tecnico em Enfermagem | BT69: 45322 | BW69: sim | BY69: MP134479 | BZ69: 45322 | CA69: 45344 | CC69: 45330 | CD69: Sim | CF69: 45322 | CL69: 45330 | CM69: 45348 | CN69: 45330 | CO69: 45352 | CR69: 45338 | CS69: 45341 | CT69: 45437 | CV69: 45364 | CW69: 45339 | CY69: Sim | DD69: 45344 | DF69: 45360 | DI69: 45363 | DJ69: 45330 | DK69: 45364 | DL69: 45366 | DM69: 45371 | DN69: 45383 | DO69: 45338 | DP69: OK
A70: 3249 | B70: PROCESSO FINALIZADO | C70: 3804 | D70: FSA009 - VILA DOS IPÊS | E70: Única | F70: BLOCO E | G70: 202 | H70: FORMOSA | I70: MARIA VICTORYA FERREIRA DA SILVA | J70: "07067805155" | K70: CANAL VIRTUAL | L70: JÉSSICA NOGUEIRA DE SOUSA - CLT | M70: Não | N70: Não | O70: Não | P70: Não | Q70: Não | R70: Não | S70: Não | T70: 158822.65 | U70: 632.99 | V70: 0 | W70: 128375.17 | X70: 30335 | Y70: 0 | Z70: 158710.17 | AA70: 0 | AB70: 0 | AD70: 8787719160611 | AE70: Contrato Adimplente | AF70: 74035 | AG70: 45419 | AH70: 2794.99 | AI70: 45350 | AJ70: 2004 | AK70: 45329 | AP70: Endy Carvalho Consultoria imobiliária | AT70: 45484 | AU70: 45484 | AV70: VENDA FINALIZADA | AW70: 45318 | AX70: 20915 | AY70: 215000.25 | BA70: FSA09 | BB70: 20915 | BD70: Formosa | BE70: Goiás | BF70: 5561999441341 | BG70: RUA 01 Q 16 L 8 | BH70: 73805365 | BI70: SETOR PAMPULHA | BJ70: victorya.maria@hotmail.com | BL70: 2109.96 | BM70: 45495 | BQ70: 3090 | BR70: 5442 | BS70: Assistente | BT70: 45321 | BW70: sim | BY70: MP134475 | BZ70: 45321 | CA70: 45345 | CC70: 45330 | CD70: Sim | CF70: 45321 | CL70: 45330 | CM70: 45384 | CN70: 45330 | CO70: 45352 | CR70: 45338 | CS70: 45337 | CT70: 45495 | CV70: 45364 | CW70: 45336 | CY70: Sim | DD70: 45387 | DF70: 45420 | DI70: 45421 | DJ70: 45329 | DK70: 45364 | DL70: 45365 | DM70: 45371 | DN70: 45383 | DO70: 45336 | DP70: OK
A71: 3250 | B71: PROCESSO FINALIZADO | C71: 3826 | D71: FSA009 - VILA DOS IPÊS | E71: Única | F71: BLOCO K | G71: 303 | H71: FORMOSA | I71: ERIKA GONZAGA DOS SANTOS | J71: "09425537135" | K71: AUTÔNOMOS | FSA | L71: JE EMPREENDIMENTOS IMOBILIÁRIOS | M71: Não | N71: Não | O71: Não | P71: Não | Q71: Não | R71: Não | S71: Não | T71: 149870.93 | U71: 486.65 | V71: 0 | W71: 94906.81 | X71: 53091 | Y71: 0 | Z71: 147997.81 | AA71: 0 | AB71: 0 | AD71: 8787719163297 | AE71: Contrato Adimplente | AF71: 74136 | AG71: 45387 | AH71: 3559.97 | AI71: 45369 | AJ71: 2004 | AK71: 45329 | AP71: Endy Carvalho Consultoria imobiliária | AT71: 45743 | AU71: 45743 | AV71: VENDA FINALIZADA | AW71: 45330 | AX71: 20912 | AY71: 205000.08 | BA71: FSA09 | BB71: 20912 | BC71: MARIANA GONZAGA DOS SANTOS - 07323842140 | BD71: Formosa | BE71: Goiás | BF71: 5561998442550 | BG71: Rua 9 Q 44 L 23-A | BH71: 73808330 | BI71: Parque Vila Verde | BJ71: erikagonzaga678@gmail.com | BL71: 1622.17 | BM71: 45501 | BQ71: 3199 | BR71: 5436 | BS71: Caixa | BT71: 45357 | BW71: sim | BY71: MP134476 | BZ71: 45358 | CA71: 45364 | CC71: 45330 | CD71: Sim | CF71: 45358 | CL71: 45366 | CM71: 45369 | CN71: 45330 | CO71: 45366 | CR71: 45338 | CS71: 45337 | CT71: 45501 | CV71: 45366 | CW71: 45337 | CY71: Sim | DD71: 45369 | DF71: 45388 | DI71: 45387 | DJ71: 45329 | DK71: 45387 | DL71: 45460 | DM71: 45504 | DN71: 45728 | DO71: 45336 | DP71: 45728
A72: 3251 | B72: PROCESSO FINALIZADO | C72: 3805 | D72: FSA009 - VILA DOS IPÊS | E72: Única | F72: BLOCO Q | G72: 202 | H72: FORMOSA | I72: VIRGINIA MELO SILVA | J72: "04966001170" | K72: AUTÔNOMOS | FSA | L72: ERAF CORRETORA DE IMÓVEIS EIRELI | M72: Não | N72: Não | O72: Não | P72: Não | Q72: Não | R72: Não | S72: Não | T72: 155428.31 | U72: 543.58 | V72: 0 | W72: 112796.31 | X72: 43255 | Y72: 0 | Z72: 156051.31 | AA72: 0 | AB72: 0 | AD72: 8787719162134 | AE72: Contrato Adimplente | AF72: 74227 | AG72: 45370 | AH72: 2849 | AI72: 45350 | AJ72: 2004 | AK72: 45329 | AP72: Endy Carvalho Consultoria imobiliária | AT72: 45503 | AU72: 45503 | AV72: VENDA FINALIZADA | AW72: 45318 | AX72: 21017 | AY72: 215000.31 | BA72: FSA09 | BB72: 21017 | BC72: FATIMA SOARES DA SILVA - 75925770110 | BD72: Formosa | BE72: Goiás | BF72: 5561999444667 | BG72: Avenida João de Barro Q 7 | BH72: 73813772 | BI72: Parque Lago | BJ72: virginiassmelo@gmail.com | BL72: 1811.98 | BM72: 45493 | BQ72: 3290 | BR72: 1146 | BS72: Operador de Loja | BT72: 45341 | BW72: sim | BY72: MP134477 | BZ72: 45341 | CA72: 45345 | CC72: 45330 | CD72: Sim | CF72: 45341 | CL72: 45342 | CM72: 45350 | CN72: 45330 | CO72: 45352 | CP72: 45356 | CR72: 45338 | CS72: 45337 | CT72: 45493 | CU72: 45364 | CV72: 45364 | CW72: 45337 | CY72: Sim | DD72: 45350 | DF72: 45370 | DI72: 45387 | DJ72: 45329 | DK72: 45364 | DL72: 45371 | DM72: 45379 | DN72: 45383 | DO72: 45337 | DP72: OK | EE72: 2541.17
A73: 3252 | B73: DISTRATO | C73: 3734 | D73: AGL028 - VILA DO CERRADO | E73: ETAPA 01 | F73: BLOCO A | G73: 1 | H73: ÁGUAS LINDAS | I73: YAN MATHEW ARAUJO COSTA | J73: "06796670167" | K73: EQUIPE PRÓPRIA | AGL | L73: MICHELE RODRIGUES DA SILVA | M73: Não | N73: Não | O73: Não | P73: Não | Q73: Não | R73: Não | S73: Não | T73: 162598.05 | U73: 634.4 | V73: 0 | W73: 127904.05 | X73: 34694 | Y73: 0 | Z73: 162598.05 | AA73: 0 | AB73: 0 | AE73: Contrato Adimplente | AH73: 0 | AK73: 45330 | AP73: Endy Carvalho Consultoria imobiliária | AT73: 45344 | AU73: 45344 | AV73: DISTRATO | AW73: 45297 | AX73: 21015 | AY73: 218774.85 | BA73: AGL28 | BB73: 21015 | BD73: Brasília | BE73: Distrito Federal | BF73: 5561995306290 | BG73: QSD 53 LOTE 29 | BH73: 72020053 | BI73: Taguatinga Sul (Taguatinga) | BJ73: YANMATHEW73@GMAIL.COM | BL73: 2114.69 | BM73: 45475 | BQ73: 2697 | BR73: 5445 | BS73: Tecnico em tecnologia da informação | BT73: 45336 | BW73: sim | BY73: MP129696 | BZ73: 45336 | CC73: 45337 | CF73: 45336 | CN73: 45337 | CR73: 45341 | CW73: 45336 | DD73: 45328 | DJ73: 45329 | DO73: 45336
A74: 3253 | B74: DISTRATO | C74: 3775 | D74: AGL029 - VILA FLAMBOYANT | E74: Etapa Unica | F74: BLOCO E | G74: 103 | H74: ÁGUAS LINDAS | I74: JAQUELANE DA CRUZ | J74: "05861672342" | K74: EQUIPE PRÓPRIA | AGL | L74: MICHELE RODRIGUES DA SILVA | M74: Não | N74: Não | O74: Não | P74: Não | Q74: Não | R74: Não | S74: Não | T74: 135336.29 | U74: 450 | V74: 0 | W74: 81741.46 | X74: 50831 | Y74: 0 | Z74: 132572.46 | AA74: 0 | AB74: 0 | AE74: Contrato Adimplente | AH74: 0 | AK74: 45330 | AP74: Endy Carvalho Consultoria imobiliária | AT74: 45349 | AU74: 45349 | AV74: DISTRATO | AW74: 45310 | AX74: 21023 | AY74: 190000.09 | BA74: AGL29 | BB74: 21023 | BD74: Taguatinga | BE74: Distrito Federal | BF74: 5561995282359 | BG74: CA V. PIRES CH 330 | BH74: 72005551 | BI74: VICENTE PIRES | BJ74: JAQUELANE1234@HOTMAIL.COM | BL74: 1800 | BM74: 45491 | BO74: Endy Carvalho (Correspondente): Cliente cancelou todas as avaliações que tinha conosco e rodou análise em outro cca. Caso a mesma deseje dar andamento no nosso processo, precisamos rodar nova avaliação e gerar novos formulários. Att | BP74: 19/02/2024 às 14h50 | BQ74: 3380 | BR74: 5450 | BS74: Atendente | CF74: 45310 | CL74: 45331 | DD74: 45329
A75: 3254 | B75: PROCESSO FINALIZADO | C75: 3790 | D75: FSA009 - VILA DOS IPÊS | E75: Única | F75: BLOCO D | G75: 101 | H75: FORMOSA | I75: SARA MIRANDA DOS SANTOS | J75: "02229029142" | K75: AUTÔNOMOS | FSA | L75: MILENA BOTELHO DE PAIVA DIAS | M75: Não | N75: Não | O75: Não | P75: Não | Q75: Não | R75: Não | S75: Não | T75: 152325.98 | U75: 600 | V75: 0 | W75: 117710.98 | X75: 35128 | Y75: 0 | Z75: 152838.98 | AA75: 0 | AB75: 0 | AD75: 8787719174094 | AE75: Contrato Adimplente | AF75: 74014 | AG75: 45397 | AH75: 3203.81 | AI75: 45373 | AJ75: 2004 | AK75: 45330 | AP75: Endy Carvalho Consultoria imobiliária | AT75: 45743 | AU75: 45743 | AV75: VENDA FINALIZADA | AW75: 45331 | AX75: 21016 | AY75: 216800 | BA75: FSA09 | BB75: 21016 | BC75: Rejilene Miranda De Oliveira - 88112284172 | BD75: Formosa | BE75: Goiás | BF75: 5561999244338 | BG75: Rua 7 Q 135 L 02 | BH75: 73813420 | BI75: Formosinha | BJ75: sarasantosmiranda2004@gmail.com | BL75: 2000 | BM75: 45486 | BQ75: 3077 | BR75: 5446 | BS75: Auxiliar | BT75: 45344 | BW75: sim | BY75: MP134478 | BZ75: 45345 | CA75: 45364 | CC75: 45330 | CD75: Sim | CF75: 45345 | CL75: 45350 | CM75: 45373 | CN75: 45330 | CO75: 45366 | CR75: 45338 | CS75: 45341 | CT75: 45486 | CV75: 45387 | CW75: 45339 | CY75: Sim | DD75: 45373 | DF75: 45397 | DI75: 45399 | DJ75: 45330 | DK75: 45387 | DL75: 45461 | DM75: 45504 | DN75: 45728 | DO75: 45338 | DP75: 45728
A76: 3255 | B76: PROCESSO FINALIZADO | C76: 3815 | D76: AGL 23 - VILA DO SOL | E76: Etapa Única | F76: RETOMADO | G76: BLC APT302 | H76: ÁGUAS LINDAS | I76: DANIEL SILVA BENICIO | J76: "70338409181" | K76: IMOBILIÁRIAS | AGL | L76: DIEGO REIS IMOBILIÁRIA | M76: Não | N76: Não | O76: Não | P76: Sim | Q76: Não | R76: Não | S76: Não | T76: 161801 | U76: 1080.23 | V76: 0 | W76: 160800 | X76: 1004 | Y76: 0 | Z76: 161804 | AA76: 0 | AB76: 0 | AD76: 8444433176904 | AE76: Contrato Adimplente | AF76: 90241 | AG76: 45376 | AH76: 3080.76 | AI76: 45359 | AJ76: 2004 | AK76: 45330 | AP76: Endy Carvalho Consultoria imobiliária | AT76: 45398 | AU76: 45398 | AV76: VENDA FINALIZADA | AW76: 45321 | AY76: 173000 | BA76: AGL23 | BC76: ANA LUIZA DE FREITAS SOUSA BENICIO - 70464404177 | BD76: Águas Lindas de Goiás | BE76: Goiás | BF76: 5561995420530 | BG76: QUADRA 72 | BH76: 72911120 | BI76: Cidade Jardim | BJ76: daniel1993.com@gmail.com | BK76: 5561993946988 | BL76: 4246.94 | BM76: 45459 | BO76: Thiago Ribeiro (Gestor): Obs: do valor que o cliente financiou ficou a parte da construtora ressarcir ao Diego o valor de R$1.801,00 apos assinatura do cliente pois como foi acordado o valor de venda de R$ 160.000,00 seria do Marco, como o cliente financiou 161.801,00 e o restante junto ao sinal ficou como comissão para o Diego. | BP76: 15/02/2024 às 11h25 | BS76: Soldado do Exército | BT76: 45321 | BU76: 500 | BV76: 45365 | BW76: sim | BX76: 45366 | BZ76: 45321 | CA76: 45364 | CD76: Sim | CF76: 45321 | CG76: 45355 | CI76: 45355 | CJ76: 45366 | CL76: 45321 | CM76: 45370 | CP76: 45362 | CS76: 45356 | CU76: 45364 | CW76: 45356 | CX76: 45372 | CY76: Sim | DD76: 45353 | DI76: 45378 | DJ76: 45349 | DO76: 45356 | EE76: 4025.32
A77: 3256 | B77: PROCESSO FINALIZADO | C77: 3796 | D77: AGL029 - VILA FLAMBOYANT | E77: Etapa Unica | F77: BLOCO G | G77: 103 | H77: ÁGUAS LINDAS | I77: KELLY CAMARGO LEMOS | J77: "71318459141" | K77: EQUIPE PRÓPRIA | AGL | L77: JOSUÉ GOMES DE SOUZA | M77: Não | N77: Não | O77: Não | P77: Sim | Q77: Sim | R77: Não | S77: Não | T77: 132280.02 | U77: 426.5 | V77: 0 | W77: 77707.33 | X77: 54333 | Y77: 0 | Z77: 132040.33 | AA77: 0 | AB77: 0 | AD77: 878771922323400 | AE77: Contrato Adimplente | AG77: 45373 | AH77: 2371.12 | AI77: 45351 | AJ77: 2004 | AK77: 45330 | AP77: Endy Carvalho Consultoria imobiliária | AT77: 45736 | AU77: 45736 | AV77: VENDA FINALIZADA | AW77: 45316 | AX77: 21022 | AY77: 189760.53 | BA77: AGL29 | BB77: 21022 | BD77: Águas Lindas de Goiás | BE77: Goiás | BF77: 5561991649292 | BG77: RUA MINAS GERAIS QUADRA 11 | BH77: 72910000 | BI77: JARDIM DOS PINHEIROS | BJ77: Keyllacamargo@hotmail.com | BL77: 1706 | BM77: 45490 | BO77: Denise Batista da Silva Nunes (Gestor): 1. Em análise, verifica-se que a procuração citada no item A (qualificação das partes) não possui a ALIENANTE, INCORPORADA E ENTIDADE ORGANIZADORA E FIADORA como outorgante, bem como os dados do imóvel objeto do contrato. Desta forma, faz-se necessário apresentar a procuração correspondente. Devendo ainda, fazer ressalva quanto aos dados da procuração. 2. No campo CONSTRUTORA E FIADORA (item A) a procuração citada não possui os dados do imóvel objeto do contrato. Desta forma, faz-se necessário apresentar a procuração correspondente. Devendo ainda, fazer ressalva quanto aos dados da procuração. | BP77: 20/03/2024 às 15h51 | BQ77: 3412 | BR77: 5449 | BS77: Auxiliar | BT77: 45316 | BU77: 486.31 | BV77: 45365 | BW77: sim | BX77: 45369 | BY77: MP140257 | BZ77: 45316 | CA77: 45355 | CC77: 45330 | CD77: Sim | CF77: 45316 | CJ77: 45359 | CL77: 45331 | CM77: 45364 | CN77: 45330 | CO77: 45414 | CP77: 45355 | CR77: 45331 | CS77: 45344 | CU77: 45357 | CV77: 45414 | CW77: 45344 | CX77: 45366 | CY77: Sim | CZ77: 45371 | DC77: 45372 | DD77: 45328 | DF77: 45376 | DI77: 45377 | DJ77: 45341 | DK77: 45453 | DL77: 45482 | DM77: 45629 | DN77: 45712 | DO77: 45343 | DP77: 45712 | EE77: 3805.32
A78: 3257 | B78: PROCESSO FINALIZADO | C78: 3825 | D78: FSA009 - VILA DOS IPÊS | E78: Única | F78: BLOCO A | G78: 3 | H78: FORMOSA | I78: ISADORA MARIA SILVA DE OLIVEIRA | J78: "04627443102" | K78: EQUIPE PRÓPRIA |FSA | L78: TAKADA IMOB | M78: Não | N78: Não | O78: Não | P78: Não | Q78: Não | R78: Não | S78: Não | T78: 164200 | U78: 750 | V78: 0 | W78: 146555 | X78: 17645 | Y78: 0 | Z78: 164200 | AA78: 0 | AB78: 0 | AD78: 8787719179053 | AE78: Contrato Adimplente | AF78: 73964 | AG78: 45449 | AH78: 6268.57 | AI78: 45365 | AJ78: 2004 | AK78: 45330 | AP78: Endy Carvalho Consultoria imobiliária | AT78: 45743 | AU78: 45743 | AV78: VENDA FINALIZADA | AW78: 45322 | AX78: 21012 | AY78: 225000 | BA78: FSA09 | BB78: 21012 | BC78: ANA CLARA MAGALHÃES LEMOS SALDANHA - 06863298139 | BD78: Formosa | BE78: Goiás | BF78: 5561999915413 | BG78: RUA 4 Q 1 L 02 - A | BH78: 73813150 | BI78: FORMOSINHA | BJ78: isadoraoliveira67@gmail.com | BL78: 2500 | BM78: 45501 | BQ78: 3027 | BR78: 276 | BS78: Analista | BT78: 45352 | BW78: sim | BY78: MP134480 | BZ78: 45352 | CA78: 45364 | CC78: 45330 | CD78: Sim | CF78: 45352 | CL78: 45357 | CM78: 45379 | CN78: 45330 | CO78: 45366 | CR78: 45338 | CS78: 45342 | CT78: 45590 | CV78: 45414 | CW78: 45342 | CY78: Sim | DD78: 45366 | DF78: 45450 | DI78: 45453 | DJ78: 45331 | DK78: 45387 | DL78: 45474 | DM78: 45504 | DN78: 45728 | DO78: 45342 | DP78: 45728
A79: 3258 | B79: PROCESSO FINALIZADO | C79: 3814 | D79: AGL028 - VILA DO CERRADO | E79: ETAPA 01 | F79: BLOCO G | G79: 301 | H79: ÁGUAS LINDAS | I79: FERNANDO LUIS ARAUJO RODRIGUES | J79: "03136316380" | K79: EQUIPE PRÓPRIA | AGL | L79: MAYSA GABRIELA GONÇALVES OLIVEIRA - CLT | M79: Não | N79: Não | O79: Não | P79: Sim | Q79: Sim | R79: Não | S79: Não | T79: 162112.82 | U79: 585 | V79: 0 | W79: 120406.18 | X79: 41332 | Y79: 0 | Z79: 161738.18 | AA79: 0 | AB79: 0 | AD79: 8787719158560 | AE79: Contrato Adimplente | AF79: 96115 | AG79: 45376 | AH79: 2740.25 | AI79: 45359 | AJ79: 2004 | AK79: 45330 | AP79: Endy Carvalho Consultoria imobiliária | AT79: 45653 | AU79: 45744 | AV79: VENDA FINALIZADA | AW79: 45321 | AX79: 21018 | AY79: 210000.32 | BA79: AGL28 | BB79: 21018 | BD79: Águas Lindas de Goiás | BE79: Goiás | BF79: 5561999938586 | BG79: QUADRA 13 LOTE 14 | BH79: 72910000 | BI79: JARDIM QUERENCIA | BJ79: Fernandoluizaraujo4@gmail.com | BL79: 1950 | BM79: 45493 | BQ79: 2812 | BR79: 5447 | BS79: Produtor Rural | BT79: 45321 | BU79: 500 | BV79: 45364 | BX79: 45364 | BY79: MP129691 | BZ79: 45321 | CA79: 45364 | CC79: 45330 | CD79: Sim | CF79: 45322 | CG79: 45336 | CJ79: 45364 | CL79: 45331 | CM79: 45371 | CN79: 45330 | CO79: 45366 | CP79: 45359 | CR79: 45331 | CS79: 45336 | CU79: 45362 | CV79: 45406 | CW79: 45336 | CX79: 45376 | CY79: Sim | DD79: 45329 | DF79: 45377 | DI79: 45378 | DJ79: 45329 | DK79: 45406 | DL79: 45455 | DM79: 45504 | DN79: 45624 | DO79: 45336 | DP79: 45624 | EE79: 4205.32
A80: 3259 | B80: PROCESSO FINALIZADO | C80: 3809 | D80: FSA010 - VILA JARDINS | E80: Etapa Unica | F80: BLOCO J | G80: APTO 102 | H80: FORMOSA | I80: DIEIMISON DA SILVA GONÇALVES | J80: "03765120162" | K80: EQUIPE PRÓPRIA |FSA | L80: NAUANE MARTINS DA SILVA OLIVEIRA - CLT | M80: Não | N80: Não | O80: Não | P80: Não | Q80: Não | R80: Não | S80: Não | T80: 167000 | U80: 905.92 | V80: 0 | W80: 168000 | X80: 543 | Y80: 0 | Z80: 168543 | AA80: 0 | AB80: 0 | AD80: 8787719414397 | AE80: Contrato Adimplente | AF80: 75616 | AG80: 45470 | AH80: 3919.94 | AI80: 45443 | AJ80: 2004 | AK80: 45330 | AP80: Endy Carvalho Consultoria imobiliária | AT80: 45887 | AU80: 45887 | AV80: VENDA FINALIZADA | AW80: 45320 | AX80: 21071 | AY80: 175000 | BA80: FSA010 | BB80: 21071 | BD80: Formosa | BE80: Goiás | BF80: 5561999855920 | BG80: RUA 4A, QUADRA 94 | BH80: 73808410 | BI80: PARQUE VILA VERDE | BJ80: dieimisong@gmail.com | BL80: 4131.48 | BM80: 45489 | BQ80: 3743 | BR80: 5453 | BS80: Supervisor | BT80: 45533 | BW80: sim | BZ80: 45533 | CA80: 45433 | CD80: Sim | CF80: 45533 | CL80: 45535 | CM80: 45460 | CS80: 45365 | CT80: 45489 | CW80: 45365 | CY80: Sim | DB80: 45422 | DD80: 45470 | DE80: 45433 | DF80: 45470 | DI80: 45474 | DJ80: 45364 | DO80: 45365
A81: 3260 | B81: PROCESSO FINALIZADO | C81: 3818 | D81: FSA007 - VILA DAS HORTÊNSIAS | E81: Etapa | F81: BLOCO F | G81: 2 (PCD) | H81: FORMOSA | I81: LAYANA LACHER DE SOUSA | J81: "04637668140" | K81: EQUIPE PRÓPRIA |FSA | L81: TAKADA IMOB | M81: Não | N81: Não | O81: Não | P81: Não | Q81: Não | R81: Não | S81: Não | T81: 129305.87 | U81: 945.07 | V81: 40232.03 | W81: 124313.87 | X81: 4992 | Y81: 0 | Z81: 129305.87 | AA81: 0 | AB81: 0 | AD81: 8787719173845 | AE81: Contrato Adimplente | AF81: 72720 | AG81: 45448 | AH81: 5515.43 | AI81: 45345 | AJ81: 2004 | AK81: 45330 | AP81: Endy Carvalho Consultoria imobiliária | AT81: 46098 | AU81: 46098 | AV81: VENDA FINALIZADA | AW81: 45321 | AX81: 21019 | AY81: 215000 | BA81: FSA07 | BB81: 21019 | BD81: Formosa | BE81: Goiás | BF81: 5561996397133 | BG81: VIA 12, Q. 69 | BH81: 73802442 | BI81: SETOR SUL | BJ81: layanalacher@hotmail.com | BL81: 3150.26 | BM81: 45459 | BQ81: 917 | BR81: 5448 | BS81: Analista | BT81: 45322 | BW81: sim | BY81: MP139502 | BZ81: 45322 | CA81: 45344 | CC81: 45331 | CD81: Sim | CF81: 45322 | CL81: 45331 | CM81: 45376 | CN81: 45331 | CO81: 45352 | CP81: 45356 | CR81: 45331 | CS81: 45338 | CT81: 45459 | CU81: 45364 | CV81: 45364 | CW81: 45338 | CY81: Sim | DD81: 45376 | DF81: 45450 | DI81: 45453 | DJ81: 45330 | DK81: 45364 | DL81: 45383 | DM81: 45502 | DN81: 46057 | DO81: 45338 | DP81: 46057 | EE81: 2325.59
A82: 3261 | B82: PROCESSO FINALIZADO | C82: 3829 | D82: FSA009 - VILA DOS IPÊS | E82: Única | F82: BLOCO H | G82: 202 | H82: FORMOSA | I82: GISLENE ALVARES DE OLIVEIRA | J82: "95376801187" | K82: AUTÔNOMOS | FSA | L82: MATEUS VITOR DIAS - DESLIGADO | M82: Não | N82: Não | O82: Não | P82: Não | Q82: Não | R82: Não | S82: Não | T82: 148548.93 | U82: 532.75 | V82: 0 | W82: 104139.81 | X82: 45056 | Y82: 0 | Z82: 149195.81 | AA82: 0 | AB82: 0 | AD82: 8787719167365 | AE82: Contrato Adimplente | AF82: 74083 | AG82: 45455 | AH82: 5647.58 | AI82: 45352 | AJ82: 2004 | AK82: 45330 | AP82: Endy Carvalho Consultoria imobiliária | AT82: 45484 | AU82: 45484 | AV82: VENDA FINALIZADA | AW82: 45331 | AX82: 21013 | AY82: 215000.08 | BA82: FSA09 | BB82: 21013 | BC82: FABIO ALVARES PEREIRA - 82726850197,RODRIGO ALVARES DE OLIVEIRA - 09008092131 | BD82: Formosa | BE82: Goiás | BF82: 5561996990021 | BG82: Avenida Goiás | BH82: 73813260 | BI82: Formosinha | BJ82: gislenealves2325@gmail.com | BL82: 1775.82 | BM82: 45502 | BQ82: 3138 | BR82: 5443 | BS82: Motoboy | BT82: 45331 | BW82: sim | BY82: MP134481 | BZ82: 45331 | CA82: 45352 | CC82: 45330 | CD82: Sim | CF82: 45331 | CL82: 45336 | CM82: 45372 | CN82: 45331 | CO82: 45352 | CP82: 45356 | CR82: 45338 | CS82: 45337 | CT82: 45502 | CV82: 45362 | CW82: 45337 | CY82: Sim | DB82: 45338 | DD82: 45356 | DE82: 45352 | DF82: 45455 | DI82: 45455 | DJ82: 45330 | DK82: 45362 | DL82: 45365 | DM82: 45371 | DN82: 45383 | DO82: 45337 | DP82: OK
A83: 3262 | B83: PROCESSO FINALIZADO | C83: 3793 | D83: AGL028 - VILA DO CERRADO | E83: ETAPA 01 | F83: BLOCO F | G83: 203 | H83: ÁGUAS LINDAS | I83: THIAGO DOS SANTOS VIEIRA | J83: "01220458155" | K83: EQUIPE PRÓPRIA | AGL | L83: TAYNAH MONTEIRO - CLT | M83: Não | N83: Não | O83: Não | P83: Sim | Q83: Sim | R83: Não | S83: Não | T83: 150957.28 | U83: 467.04 | V83: 0 | W83: 95489.45 | X83: 55000 | Y83: 0 | Z83: 150489.45 | AA83: 0 | AB83: 0 | AD83: 8787719171664 | AE83: Contrato Adimplente | AF83: 96097 | AG83: 45362 | AH83: 2740.25 | AI83: 45344 | AJ83: 2004 | AK83: 45330 | AP83: Endy Carvalho Consultoria imobiliária | AT83: 45653 | AU83: 45744 | AV83: VENDA FINALIZADA | AW83: 45330 | AX83: 21080 | AY83: 198000.05 | BA83: AGL28 | BB83: 21080 | BD83: Águas Lindas de Goiás | BE83: Goiás | BF83: 5561995780603 | BG83: QQUADRA 09. LOTE 09 | BH83: 72910001 | BI83: MANSOES AGUAS LINDAS | BJ83: thiagodsvieira902@gmail.com | BL83: 1556.81 | BM83: 45495 | BQ83: 2785 | BR83: 5462 | BS83: Auxiliar | BT83: 45316 | BU83: 500 | BV83: 45348 | BW83: sim | BX83: 45351 | BY83: MP129692 | BZ83: 45316 | CA83: 45350 | CC83: 45331 | CD83: Sim | CF83: 45316 | CG83: 45338 | CI83: 45338 | CJ83: 45356 | CL83: 45336 | CM83: 45357 | CN83: 45331 | CO83: 45352 | CP83: 45350 | CR83: 45341 | CS83: 45341 | CU83: 45351 | CV83: 45363 | CW83: 45341 | CX83: 45362 | CY83: Sim | DD83: 45329 | DF83: 45363 | DI83: 45364 | DJ83: 45330 | DK83: 45364 | DL83: 45397 | DM83: 45504 | DN83: 45624 | DO83: 45341 | DP83: 45624 | EE83: 3905.32
A84: 3263 | B84: PROCESSO FINALIZADO | C84: 3819 | D84: AGL028 - VILA DO CERRADO | E84: ETAPA 02 | F84: BLOCO P | G84: 104 | H84: ÁGUAS LINDAS | I84: SERGIO HENRIQUE DE SOUZA FERREIRA | J84: "04869151154" | K84: EQUIPE PRÓPRIA | AGL | L84: MAYSA GABRIELA GONÇALVES OLIVEIRA - CLT | M84: Não | N84: Não | O84: Não | P84: Sim | Q84: Sim | R84: Não | S84: Não | T84: 155999.07 | U84: 583.76 | V84: 0 | W84: 114143.59 | X84: 41482 | Y84: 0 | Z84: 155625.59 | AA84: 0 | AB84: 0 | AD84: 8787719190570 | AE84: Contrato Adimplente | AF84: 96254 | AG84: 45362 | AH84: 2740.25 | AI84: 45343 | AJ84: 2004 | AK84: 45331 | AP84: Endy Carvalho Consultoria imobiliária | AT84: 45741 | AU84: 45741 | AV84: VENDA FINALIZADA | AW84: 45322 | AX84: 21075 | AY84: 200019.19 | BA84: AGL28 | BB84: 21075 | BD84: Águas Lindas de Goiás | BE84: Goiás | BF84: 5561981358963 | BG84: BL H Q 00 L 83 A | BH84: 72910000 | BI84: MANSOES CENTRO OESTE | BJ84: sergiohenriquesf94@gmail.com | BL84: 1945.86 | BM84: 45500 | BQ84: 2960 | BR84: 5457 | BS84: Cobrador | BT84: 45322 | BU84: 500 | BV84: 45345 | BW84: sim | BX84: 45350 | BY84: MP129812 | BZ84: 45322 | CA84: 45349 | CC84: 45331 | CD84: Sim | CF84: 45322 | CJ84: 45356 | CL84: 45336 | CM84: 45357 | CN84: 45331 | CO84: 45352 | CP84: 45349 | CR84: 45338 | CS84: 45341 | CU84: 45349 | CV84: 45363 | CW84: 45341 | CX84: 45359 | CY84: Sim | DD84: 45330 | DF84: 45363 | DI84: 45364 | DJ84: 45336 | DK84: 45364 | DL84: 45370 | DM84: 45386 | DN84: 45548 | DO84: 45341 | DP84: 45548 | EE84: 4005.32
A85: 3264 | B85: PROCESSO FINALIZADO | C85: 3834 | D85: AGL028 - VILA DO CERRADO | E85: ETAPA 01 | F85: BLOCO B | G85: 102 | H85: ÁGUAS LINDAS | I85: RODRIGO BEZERRA DA COSTA | J85: "60460770365" | K85: EQUIPE PRÓPRIA | AGL | L85: JOSUÉ GOMES DE SOUZA | M85: Não | N85: Não | O85: Não | P85: Sim | Q85: Sim | R85: Não | S85: Não | T85: 156323.77 | U85: 575.57 | V85: 0 | W85: 110806 | X85: 43453 | Y85: 0 | Z85: 154259 | AA85: 0 | AB85: 0 | AD85: 8787719243274 | AE85: Contrato Adimplente | AF85: 96028 | AG85: 45362 | AH85: 2740.25 | AI85: 45350 | AJ85: 2004 | AK85: 45331 | AP85: Endy Carvalho Consultoria imobiliária | AT85: 45653 | AU85: 45744 | AV85: VENDA FINALIZADA | AW85: 45322 | AX85: 21050 | AY85: 207938 | BA85: AGL28 | BB85: 21050 | BD85: Taguatinga | BE85: Distrito Federal | BF85: 5588981736736 | BG85: QNF 21 LOTE | BH85: 72225571 | BI85: Taguatinga Norte (Taguatinga) | BJ85: rodrigobezerra780@gmail.com | BL85: 1918.59 | BM85: 45502 | BQ85: 2723 | BR85: 5451 | BS85: Ajudante | BT85: 45336 | BU85: 500 | BV85: 45352 | BW85: sim | BX85: 45357 | BY85: MP129694 | BZ85: 45336 | CA85: 45350 | CC85: 45336 | CD85: Sim | CF85: 45336 | CG85: 45348 | CJ85: 45356 | CL85: 45344 | CM85: 45357 | CN85: 45336 | CO85: 45352 | CP85: 45350 | CR85: 45341 | CS85: 45349 | CU85: 45351 | CV85: 45363 | CW85: 45348 | CX85: 45359 | CY85: Sim | DD85: 45329 | DF85: 45363 | DI85: 45364 | DJ85: 45343 | DK85: 45364 | DL85: 45367 | DM85: 45386 | DN85: 45624 | DO85: 45348 | DP85: 45624 | EE85: 4165.32
A86: 3265 | B86: PROCESSO FINALIZADO | C86: 3827 | D86: AGL028 - VILA DO CERRADO | E86: ETAPA 02 | F86: BLOCO J | G86: 1 | H86: ÁGUAS LINDAS | I86: ISMAEL NASCIMENTO OLIVEIRA | J86: "63226167308" | K86: EQUIPE PRÓPRIA | AGL | L86: JOSUÉ GOMES DE SOUZA | M86: Não | N86: Não | O86: Não | P86: Sim | Q86: Sim | R86: Não | S86: Não | T86: 162644.69 | U86: 540 | V86: 0 | W86: 112353.11 | X86: 50031 | Y86: 0 | Z86: 162384.11 | AA86: 0 | AB86: 0 | AD86: 8787719206158 | AE86: Contrato Adimplente | AF86: 96151 | AG86: 45362 | AH86: 2740.25 | AI86: 45344 | AJ86: 2004 | AK86: 45331 | AP86: Endy Carvalho Consultoria imobiliária | AT86: 45741 | AU86: 45741 | AV86: VENDA FINALIZADA | AW86: 45322 | AX86: 21076 | AY86: 207999.87 | BA86: AGL28 | BB86: 21076 | BD86: Águas Lindas de Goiás | BE86: Goiás | BF86: 556186278360 | BG86: Quadra 16 LOTE 13B CONJUNTO A | BH86: 72910648 | BI86: Parque da Barragem Setor 04 | BJ86: Yzmaell29@gmail.com | BL86: 1800 | BM86: 45502 | BO86: Endy Carvalho (Correspondente): Bom dia. A unidade do cliente está com o valor de avaliação desatualizado no Siopi. Necessário aguardar atualização, já solicitada, para o envio do mesmo à conformidade. att | BP86: 14/02/2024 às 09h43 | BQ86: 2851 | BR86: 5458 | BS86: Auxiliar | BT86: 45322 | BU86: 500 | BV86: 45380 | BW86: sim | BX86: 45380 | BY86: MP129811 | BZ86: 45322 | CA86: 45350 | CC86: 45331 | CD86: Sim | CF86: 45322 | CG86: 45343 | CJ86: 45356 | CL86: 45336 | CM86: 45357 | CN86: 45331 | CO86: 45352 | CP86: 45350 | CR86: 45338 | CS86: 45343 | CU86: 45351 | CV86: 45363 | CW86: 45343 | CX86: 45359 | CY86: Sim | DD86: 45331 | DF86: 45363 | DI86: 45364 | DJ86: 45338 | DK86: 45364 | DL86: 45407 | DM86: 45386 | DN86: 45538 | DO86: 45343 | DP86: 45538 | EE86: 4105.32
A87: 3266 | B87: PROCESSO FINALIZADO | C87: 3832 | D87: FSA009 - VILA DOS IPÊS | E87: Única | F87: BLOCO H | G87: 1 | H87: FORMOSA | I87: EDUARDO KENDY SHIMIZU | J87: "05913635183" | K87: AUTÔNOMOS | FSA | L87: AMANDA SOUZA PEREIRA | M87: Não | N87: Não | O87: Não | P87: Não | Q87: Não | R87: Não | S87: Não | T87: 164200 | U87: 990 | V87: 0 | W87: 163147 | X87: 1053 | Y87: 0 | Z87: 164200 | AA87: 0 | AB87: 0 | AD87: 8787719181180 | AE87: Contrato Adimplente | AF87: 74074 | AG87: 45369 | AH87: 3225.57 | AI87: 45350 | AJ87: 2004 | AK87: 45331 | AP87: Endy Carvalho Consultoria imobiliária | AT87: 45503 | AU87: 45503 | AV87: VENDA FINALIZADA | AW87: 45336 | AX87: 21077 | AY87: 218000 | BA87: FSA09 | BB87: 21077 | BD87: Formosa | BE87: Goiás | BF87: 5561985123189 | BG87: Via 9 Q. 120-A | BH87: 73804050 | BI87: Chácaras Setor Abreu | BJ87: eduardoshimizu1@gmail.com | BL87: 3300 | BM87: 45502 | BQ87: 3146 | BR87: 5459 | BS87: Assistente | BT87: 45325 | BW87: sim | BY87: MP134482 | BZ87: 45325 | CA87: 45345 | CC87: 45331 | CD87: Sim | CF87: 45325 | CL87: 45336 | CM87: 45350 | CN87: 45331 | CO87: 45352 | CP87: 45356 | CR87: 45341 | CS87: 45341 | CT87: 45502 | CU87: 45364 | CV87: 45364 | CW87: 45339 | CY87: Sim | DD87: 45350 | DF87: 45369 | DI87: 45370 | DJ87: 45331 | DK87: 45364 | DL87: 45366 | DM87: 45371 | DN87: 45383 | DO87: 45338 | DP87: OK | EE87: 1775.94
A88: 3267 | B88: DISTRATO | C88: 3816 | D88: AGL028 - VILA DO CERRADO | E88: ETAPA 01 | F88: BLOCO U | G88: 303 | H88: ÁGUAS LINDAS | I88: JOELIAS HENRIQUE SILVA DE SOUZA | J88: "05238156111" | K88: EQUIPE PRÓPRIA | AGL | L88: TAYNAH MONTEIRO - CLT | M88: Não | N88: Não | O88: Não | P88: Não | Q88: Não | R88: Não | S88: Não | T88: 142803.53 | U88: 423.6 | V88: 0 | W88: 87657.73 | X88: 55000 | Y88: 0 | Z88: 142657.73 | AA88: 0 | AB88: 0 | AE88: Contrato Adimplente | AH88: 0 | AK88: 45331 | AP88: Endy Carvalho Consultoria imobiliária | AT88: 45344 | AU88: 45344 | AV88: DISTRATO | AW88: 45321 | AX88: 21073 | AY88: 198000.11 | BA88: AGL28 | BB88: 21073 | BD88: Águas Lindas de Goiás | BE88: Goiás | BF88: 556199575819 | BG88: Quadra 67 | BH88: 72920169 | BI88: Jardim da Barragem II | BJ88: joelias95henrique20@gmail.com | BL88: 1412 | BM88: 45498 | BO88: Endy Carvalho (Correspondente): Bom dia. Ao tentarmos enviar o processo do cliente para conformidade, foi identificado que o mesmo cancelou todas as avaliações e rodou análise em outro cca. Aguardando posicionamento do comercial para rodarmos nova análise e darmos andamento no processo. att | BP88: 14/02/2024 às 09h58 | BQ88: 3052 | BR88: 5456 | BS88: Motoboy | BY88: MP129697 | CC88: 45337 | CN88: 45337 | CR88: 45341 | DD88: 45329
A89: 3268 | B89: PROCESSO FINALIZADO | C89: 3838 | D89: AGL028 - VILA DO CERRADO | E89: ETAPA 02 | F89: BLOCO I | G89: 4 | H89: ÁGUAS LINDAS | I89: ADRIANA DOS SANTOS | J89: "74100076134" | K89: EQUIPE PRÓPRIA | AGL | L89: CHRISLANE COSTA FÉLIX-DESLIGADA | M89: Não | N89: Não | O89: Não | P89: Sim | Q89: Sim | R89: Não | S89: Não | T89: 157571.5 | U89: 494.95 | V89: 0 | W89: 102115.88 | X89: 55000 | Y89: 1601.91 | Z89: 158717.79 | AA89: 0 | AB89: 0 | AD89: 8787719150470 | AE89: Contrato Adimplente | AF89: 96138 | AG89: 45362 | AH89: 2740.25 | AI89: 45343 | AJ89: 2004 | AK89: 45331 | AP89: Endy Carvalho Consultoria imobiliária | AT89: 46077 | AU89: 46077 | AV89: VENDA FINALIZADA | AW89: 45336 | AX89: 21051 | AY89: 205000.17 | BA89: AGL28 | BB89: 21051 | BD89: Águas Lindas de Goiás | BE89: Goiás | BF89: 5561991601624 | BG89: Quadra 11 Conjunto B LT 14 | BH89: 72910600 | BI89: Parque da Barragem Setor 05 | BJ89: drikinhacastros@gmail.com | BL89: 1649.82 | BM89: 45504 | BQ89: 2837 | BR89: 3938 | BS89: Auxiliar | BT89: 45325 | BU89: 500 | BV89: 45345 | BW89: sim | BX89: 45350 | BY89: MP129810 | BZ89: 45325 | CA89: 45349 | CC89: 45331 | CD89: Sim | CF89: 45325 | CG89: 45338 | CI89: 45338 | CJ89: 45356 | CL89: 45336 | CM89: 45357 | CN89: 45331 | CO89: 45352 | CP89: 45349 | CR89: 45338 | CS89: 45342 | CU89: 45349 | CV89: 45363 | CW89: 45342 | CX89: 45359 | CY89: Sim | DD89: 45329 | DF89: 45363 | DI89: 45364 | DJ89: 45330 | DK89: 45364 | DL89: 45708 | DM89: 45708 | DN89: 46059 | DO89: 45342 | DP89: 46059 | EE89: 4019.68
A90: 3269 | B90: PROCESSO FINALIZADO | C90: 3808 | D90: FSA009 - VILA DOS IPÊS | E90: Única | F90: BLOCO G | G90: 1 | H90: FORMOSA | I90: GABRIEL MARQUES DE ROMAS | J90: "07069628188" | K90: AUTÔNOMOS | FSA | L90: ALANA RABELO DA COSTA | M90: Não | N90: Não | O90: Não | P90: Não | Q90: Não | R90: Não | S90: Não | T90: 164155.73 | U90: 822.59 | V90: 0 | W90: 152374 | X90: 11826 | Y90: 0 | Z90: 164200 | AA90: 0 | AB90: 0 | AD90: 8787719168523 | AE90: Contrato Adimplente | AF90: 74058 | AG90: 45365 | AH90: 3431.93 | AI90: 45348 | AJ90: 2004 | AK90: 45331 | AP90: Endy Carvalho Consultoria imobiliária | AT90: 45503 | AU90: 45503 | AV90: VENDA FINALIZADA | AW90: 45320 | AX90: 21054 | AY90: 218000 | BA90: FSA09 | BB90: 21054 | BD90: Formosa | BE90: Goiás | BF90: 5561999575066 | BG90: Rua 1 Q 13B | BH90: 73813804 | BI90: Parque Lago | BJ90: gabrielbelletem@gmail.com | BL90: 2742 | BM90: 45489 | BQ90: 3130 | BR90: 5452 | BS90: Contador | BT90: 45320 | BW90: sim | BY90: MP134483 | BZ90: 45320 | CA90: 45344 | CC90: 45331 | CD90: Sim | CF90: 45320 | CL90: 45336 | CM90: 45349 | CN90: 45336 | CO90: 45352 | CR90: 45338 | CS90: 45341 | CT90: 45489 | CV90: 45364 | CW90: 45339 | CY90: Sim | DB90: 45342 | DD90: 45344 | DE90: 45344 | DF90: 45365 | DI90: 45372 | DJ90: 45330 | DK90: 45364 | DL90: 45366 | DM90: 45371 | DN90: 45383 | DO90: 45338 | DP90: OK
A91: 3270 | B91: PROCESSO FINALIZADO | C91: 3810 | D91: FSA009 - VILA DOS IPÊS | E91: Única | F91: BLOCO I | G91: 303 | H91: FORMOSA | I91: MARCOS FILIPE DE SOUSA GOMES | J91: "05580693125" | K91: AUTÔNOMOS | FSA | L91: ALANA RABELO DA COSTA | M91: Não | N91: Não | O91: Não | P91: Não | Q91: Não | R91: Não | S91: Não | T91: 151701.43 | U91: 639.18 | V91: 0 | W91: 121716.86 | X91: 29544 | Y91: 0 | Z91: 151260.86 | AA91: 0 | AB91: 0 | AD91: 8787719158820 | AE91: Contrato Adimplente | AF91: 74104 | AG91: 45372 | AH91: 2884.46 | AI91: 45355 | AJ91: 2004 | AK91: 45331 | AP91: Endy Carvalho Consultoria imobiliária | AT91: 45503 | AU91: 45503 | AV91: VENDA FINALIZADA | AW91: 45336 | AX91: 21072 | AY91: 206000.62 | BA91: FSA09 | BB91: 21072 | BC91: SARA IZABEL BORGES - 07777309102 | BD91: Formosa | BE91: Goiás | BF91: 5561998097579 | BG91: Rua Coronel Pedro Q 55 | BH91: 73807680 | BI91: Jardim Califórnia | BJ91: marcosfilipedesousagomes@gmail.com | BL91: 2130.61 | BM91: 45489 | BQ91: 3168 | BR91: 5454 | BS91: Auxiliar | BT91: 45320 | BW91: sim | BY91: MP134484 | BZ91: 45320 | CA91: 45352 | CC91: 45336 | CD91: Sim | CF91: 45320 | CL91: 45336 | CM91: 45355 | CN91: 45336 | CO91: 45352 | CP91: 45363 | CR91: 45338 | CS91: 45336 | CT91: 45489 | CV91: 45362 | CW91: 45336 | CY91: Sim | DB91: 45337 | DD91: 45355 | DE91: 45352 | DF91: 45377 | DI91: 45378 | DJ91: 45329 | DK91: 45362 | DL91: 45365 | DM91: 45371 | DN91: 45383 | DO91: 45336 | DP91: OK
A92: 3271 | B92: PROCESSO FINALIZADO | C92: 3780 | D92: FSA009 - VILA DOS IPÊS | E92: Única | F92: BLOCO G | G92: 202 | H92: FORMOSA | I92: LUCIANO SILVA MARTINS | J92: "69952051115" | K92: EQUIPE PRÓPRIA |FSA | L92: FERNANDO FONSECA DE DEUS GALVÃO - CLT- DESLIGADO | M92: Não | N92: Não | O92: Não | P92: Não | Q92: Não | R92: Não | S92: Não | T92: 159848 | U92: 1182.42 | V92: 0 | W92: 154946 | X92: 4902 | Y92: 0 | Z92: 159848 | AA92: 0 | AB92: 0 | AD92: 8787719220517 | AE92: Contrato Adimplente | AF92: 74067 | AG92: 45386 | AH92: 3936.52 | AI92: 45362 | AJ92: 2004 | AK92: 45331 | AP92: Endy Carvalho Consultoria imobiliária | AT92: 45743 | AU92: 45743 | AV92: VENDA FINALIZADA | AW92: 45336 | AX92: 21078 | AY92: 215000 | BA92: FSA09 | BB92: 21078 | BD92: Formosa | BE92: Goiás | BF92: 5561996984289 | BG92: CONJ PADRE JOSE Q 44 L 03 | BH92: 73809711 | BI92: Conjunto Padre José | BJ92: lucianosilvagomesmartins@gmail.com | BL92: 4164.03 | BM92: 45489 | BQ92: 3122 | BR92: 5460 | BS92: Motorista | BT92: 45311 | BW92: sim | BY92: MP134485 | BZ92: 45311 | CA92: 45357 | CC92: 45336 | CD92: Sim | CF92: 45311 | CI92: 45348 | CL92: 45336 | CM92: 45373 | CN92: 45336 | CO92: 45366 | CP92: 45365 | CR92: 45338 | CS92: 45350 | CT92: 45489 | CV92: 45366 | CW92: 45350 | CY92: Sim | DB92: 45350 | DD92: 45336 | DE92: 45357 | DF92: 45386 | DI92: 45387 | DJ92: 45341 | DK92: 45387 | DL92: 45461 | DM92: 45504 | DN92: 45728 | DO92: 45350 | DP92: 45728
A93: 3272 | B93: DISTRATO | C93: 3788 | D93: AGL028 - VILA DO CERRADO | E93: ETAPA 02 | F93: BLOCO I | G93: 1 | H93: ÁGUAS LINDAS | I93: LUCAS ALVES FERREIRA | J93: "61925746348" | K93: EQUIPE PRÓPRIA | AGL | L93: JOSUÉ GOMES DE SOUZA | M93: Não | N93: Não | O93: Não | P93: Não | Q93: Não | R93: Não | S93: Não | T93: 172105.18 | U93: 744.25 | V93: 0 | W93: 151514.97 | X93: 6177 | Y93: 0 | Z93: 157691.97 | AA93: 0 | AB93: 0 | AE93: Contrato Adimplente | AH93: 0 | AK93: 45331 | AP93: Endy Carvalho Consultoria imobiliária | AT93: 45398 | AU93: 45398 | AV93: DISTRATO | AW93: 45315 | AX93: 21079 | AY93: 214105.18 | BA93: AGL28 | BB93: 21079 | BD93: Águas Lindas de Goiás | BE93: Goiás | BF93: 5589981448374 | BG93: QUADRA 09 CASA 02 | BH93: 72910000 | BI93: CONDOMINIO BELA VISTA | BJ93: Lukasalveslima123@gmail.com | BL93: 2480.83 | BM93: 45494 | BQ93: 2834 | BR93: 5461 | BS93: Operador de Loja | BT93: 45370 | BW93: sim | BY93: MP129813 | BZ93: 45370 | CC93: 45336 | CF93: 45370 | CG93: 45333 | CI93: 45369 | CN93: 45336 | CR93: 45338 | CS93: 45370 | CW93: 45370 | CY93: Sim | DD93: 45330 | DJ93: 45330 | DO93: 45341
A94: 3273 | B94: DISTRATO | C94: 3686 | D94: AGL028 - VILA DO CERRADO | E94: ETAPA 01 | F94: BLOCO G | G94: 4 | H94: ÁGUAS LINDAS | I94: RAIMUNDO NONATO ROCHA DA SILVA | J94: "00175511101" | K94: EQUIPE PRÓPRIA | AGL | L94: CHRISLANE COSTA FÉLIX-DESLIGADA | M94: Não | N94: Não | O94: Não | P94: Não | Q94: Não | R94: Não | S94: Não | T94: 157103.14 | U94: 603.33 | V94: 0 | W94: 110823.88 | X94: 40014 | Y94: 0 | Z94: 150837.88 | AA94: 0 | AB94: 0 | AE94: Contrato Adimplente | AH94: 0 | AK94: 45336 | AP94: Endy Carvalho Consultoria imobiliária | AT94: 45374 | AU94: 45374 | AV94: DISTRATO | AW94: 45322 | AX94: 21124 | AY94: 205000 | BA94: AGL28 | BB94: 21124 | BD94: Águas Lindas de Goiás | BE94: Goiás | BF94: 5561993482803 | BG94: SETOR COIMBRA NR 00 CHAC B MOD C QUADRA 19-A | BH94: 72910000 | BI94: CHACARAS COIMBRA | BJ94: rochadede2022@gmail.com | BL94: 2011.13 | BM94: 45444 | BQ94: 2803 | BR94: 5463 | BS94: Zelador | BT94: 45271 | BW94: sim | BZ94: 45271 | CF94: 45271 | CL94: 45336 | DD94: 45331
A95: 3274 | B95: DISTRATO | C95: 3806 | D95: AGL028 - VILA DO CERRADO | E95: ETAPA 01 | F95: BLOCO B | G95: 201 | H95: ÁGUAS LINDAS | I95: KARLA MOREIRA ARAUJO | J95: "07149436145" | K95: EQUIPE PRÓPRIA | AGL | L95: TAYNAH MONTEIRO - CLT | M95: Não | N95: Não | O95: Não | P95: Não | Q95: Não | R95: Não | S95: Não | T95: 161163.83 | U95: 511.63 | V95: 0 | W95: 99962.7 | X95: 55000 | Y95: 0 | Z95: 154962.7 | AA95: 0 | AB95: 0 | AE95: Contrato Adimplente | AH95: 0 | AK95: 45336 | AP95: Endy Carvalho Consultoria imobiliária | AT95: 45373 | AU95: 45373 | AV95: DISTRATO | AW95: 45318 | AX95: 21125 | AY95: 214174.49 | BA95: AGL28 | BB95: 21125 | BD95: Águas Lindas de Goiás | BE95: Goiás | BF95: 5561998653785 | BG95: QUADRA 06 CONJ - B | BH95: 72910000 | BI95: MANSOES ODISSEIA | BJ95: karlamoreiraaraujo013@gmail.com | BL95: 1705.47 | BM95: 45494 | BQ95: 2727 | BR95: 5464 | BS95: Auxiliar | BT95: 45331 | BY95: MP129695 | BZ95: 45331 | CC95: 45337 | CF95: 45331 | CG95: 45343 | CL95: 45336 | CN95: 45337 | CR95: 45341 | CS95: 45343 | CW95: 45343 | CY95: Sim | DD95: 45331 | DJ95: 45341 | DO95: 45343
A96: 3275 | B96: PROCESSO FINALIZADO | C96: 3754 | D96: FSA009 - VILA DOS IPÊS | E96: Única | F96: BLOCO J | G96: 304 | H96: FORMOSA | I96: ELIANE ALVES DA PENA | J96: "00571736130" | K96: EQUIPE PRÓPRIA |FSA | L96: RYAN GOMES CALAZANS - CLT | M96: Não | N96: Não | O96: Não | P96: Não | Q96: Não | R96: Não | S96: Não | T96: 149839.34 | U96: 680.08 | V96: 0 | W96: 125285.34 | X96: 24555 | Y96: 0 | Z96: 149840.34 | AA96: 0 | AB96: 0 | AD96: 8787719202977 | AE96: Contrato Adimplente | AF96: 74121 | AG96: 45372 | AH96: 2868.86 | AI96: 45351 | AJ96: 2004 | AK96: 45338 | AP96: Endy Carvalho Consultoria imobiliária | AT96: 45503 | AU96: 45503 | AV96: VENDA FINALIZADA | AW96: 45338 | AX96: 21175 | AY96: 205000.14 | BA96: FSA09 | BB96: 21175 | BD96: Formosa | BE96: Goiás | BF96: 5561998662451 | BG96: RUA 08 Q 25 | BH96: 73805680 | BI96: PARQUE DAS LARANJEIRAS | BJ96: elianealvespena11@gmail.com | BK96: 5561998662451 | BL96: 2266.95 | BM96: 45482 | BQ96: 3171 | BR96: 5466 | BS96: Tecnico em Enfermagem | BT96: 45304 | BW96: sim | BY96: MP134486 | BZ96: 45304 | CA96: 45345 | CC96: 45341 | CD96: Sim | CF96: 45304 | CJ96: 45366 | CL96: 45338 | CM96: 45342 | CN96: 45341 | CO96: 45352 | CP96: 45363 | CR96: 45343 | CS96: 45344 | CT96: 45482 | CV96: 45363 | CW96: 45343 | CY96: Sim | DD96: 45338 | DF96: 45372 | DI96: 45372 | DJ96: 45338 | DK96: 45364 | DL96: 45370 | DM96: 45371 | DN96: 45383 | DO96: 45343 | DP96: OK
A97: 3276 | B97: PROCESSO FINALIZADO | C97: 3817 | D97: FSA009 - VILA DOS IPÊS | E97: Única | F97: BLOCO M | G97: 2 | H97: FORMOSA | I97: BRUNA FERREIRA DA LUZ COSTA | J97: "06554242104" | K97: AUTÔNOMOS | FSA | L97: ROMÁRIO AUGUSTO NEGÓCIOS IMOBILIÁRIOS LTDA. | M97: Não | N97: Não | O97: Não | P97: Não | Q97: Não | R97: Não | S97: Não | T97: 157526.28 | U97: 718.49 | V97: 0 | W97: 137182.23 | X97: 20971 | Y97: 0 | Z97: 158153.23 | AA97: 0 | AB97: 0 | AD97: 8787719185924 | AE97: Contrato Adimplente | AF97: 74155 | AG97: 45386 | AH97: 3559.94 | AI97: 45363 | AJ97: 2004 | AK97: 45338 | AP97: Endy Carvalho Consultoria imobiliária | AT97: 45743 | AU97: 45743 | AV97: VENDA FINALIZADA | AW97: 45338 | AX97: 21174 | AY97: 215000.68 | BA97: FSA09 | BB97: 21174 | BC97: WELLITON ALMEIDA FERREIRA - 04721242182 | BD97: Formosa | BE97: Goiás | BF97: 5561996917430 | BG97: Rua 16 | BH97: 73813230 | BI97: Formosinha | BJ97: fbrunacosta@gmail.com | BL97: 2395.91 | BM97: 45498 | BQ97: 3232 | BR97: 5465 | BS97: Autônomo(a) | BT97: 45351 | BW97: sim | BY97: MP134487 | BZ97: 45351 | CA97: 45358 | CC97: 45341 | CD97: Sim | CF97: 45351 | CL97: 45355 | CM97: 45363 | CN97: 45341 | CO97: 45366 | CP97: 45365 | CR97: 45343 | CS97: 45355 | CT97: 45498 | CV97: 45387 | CW97: 45355 | CY97: Sim | DB97: 45356 | DD97: 45358 | DE97: 45358 | DF97: 45386 | DI97: 45387 | DJ97: 45332 | DK97: 45387 | DL97: 45467 | DM97: 45504 | DN97: 45728 | DO97: 45341 | DP97: 45728
A98: 3277 | B98: PROCESSO FINALIZADO | C98: 3839 | D98: FSA009 - VILA DOS IPÊS | E98: Única | F98: BLOCO Q | G98: 101 | H98: FORMOSA | I98: IGOR BORGES PINHEIRO RODRIGUES | J98: "05701105130" | K98: AUTÔNOMOS | FSA | L98: ROMÁRIO AUGUSTO NEGÓCIOS IMOBILIÁRIOS LTDA. | M98: Não | N98: Não | O98: Não | P98: Não | Q98: Não | R98: Não | S98: Não | T98: 148989.56 | U98: 527.2 | V98: 0 | W98: 103062.83 | X98: 46586 | Y98: 0 | Z98: 149648.83 | AA98: 0 | AB98: 0 | AD98: 8787719210872 | AE98: Contrato Adimplente | AF98: 74222 | AG98: 45386 | AH98: 3559.97 | AI98: 45363 | AJ98: 2004 | AK98: 45338 | AP98: Endy Carvalho Consultoria imobiliária | AT98: 45743 | AU98: 45743 | AV98: VENDA FINALIZADA | AW98: 45338 | AX98: 21178 | AY98: 215000 | BA98: FSA09 | BB98: 21178 | BC98: LIRIA BORGES DE JESUS - 96804882172 | BD98: Formosa | BE98: Goiás | BF98: 5561998118802 | BG98: Avenida Circular, Q. 48 | BH98: 73805207 | BI98: Jardim Oliveira | BJ98: IGORBORGES1610@GMAIL.COM | BL98: 1757.33 | BM98: 45501 | BQ98: 3285 | BR98: 5467 | BS98: Auxiliar | BT98: 45348 | BW98: sim | BY98: MP134488 | BZ98: 45348 | CA98: 45359 | CC98: 45341 | CD98: Sim | CF98: 45348 | CI98: 45348 | CL98: 45348 | CM98: 45363 | CN98: 45341 | CO98: 45366 | CP98: 45365 | CR98: 45343 | CS98: 45350 | CT98: 45501 | CV98: 45366 | CW98: 45350 | CY98: Sim | DD98: 45363 | DF98: 45386 | DI98: 45387 | DJ98: 45338 | DK98: 45387 | DL98: 45461 | DM98: 45504 | DN98: 45728 | DO98: 45350 | DP98: 45728
A99: 3278 | B99: PROCESSO FINALIZADO | C99: 3843 | D99: FSA009 - VILA DOS IPÊS | E99: Única | F99: BLOCO I | G99: 202 | H99: FORMOSA | I99: THAIS DANIELLE BRAGA GREGORIO | J99: "01355761131" | K99: AUTÔNOMOS | FSA | L99: ANA CAROLINA FERREIRA DE ANDRADE - CARLOS ANDRADE IMOBILIÁRIA | M99: Não | N99: Não | O99: Não | P99: Não | Q99: Não | R99: Não | S99: Não | T99: 155909.8 | U99: 568.18 | V99: 0 | W99: 117145.5 | X99: 39339 | Y99: 0 | Z99: 156484.5 | AA99: 0 | AB99: 0 | AD99: 8787719203388 | AE99: Contrato Adimplente | AF99: 74099 | AG99: 45372 | AH99: 3884.43 | AI99: 45356 | AJ99: 2004 | AK99: 45338 | AP99: Endy Carvalho Consultoria imobiliária | AT99: 45503 | AU99: 45503 | AV99: VENDA FINALIZADA | AW99: 45341 | AX99: 21198 | AY99: 215000.3 | BA99: FSA09 | BB99: 21198 | BC99: EVERALDO GONÇALVES DE SIQUEIRA - 48586455172 | BD99: Formosa | BE99: Goiás | BF99: 5561996865226 | BG99: RUA DO PRAIM | BH99: 73817000 | BI99: Centro | BJ99: thainnamgp@gmail.com | BL99: 1893.94 | BM99: 45507 | BQ99: 3154 | BR99: 5469 | BS99: Servidor Público | BT99: 45344 | BW99: sim | BY99: MP134490 | BZ99: 45344 | CA99: 45352 | CC99: 45341 | CD99: Sim | CF99: 45344 | CL99: 45345 | CM99: 45357 | CN99: 45342 | CO99: 45352 | CP99: 45363 | CR99: 45343 | CS99: 45344 | CT99: 45507 | CV99: 45362 | CW99: 45343 | CY99: Sim | DB99: 45345 | DD99: 45356 | DE99: 45352 | DF99: 45372 | DI99: 45387 | DJ99: 45338 | DK99: 45362 | DL99: 45366 | DM99: 45371 | DN99: 45383 | DO99: 45343 | DP99: OK
A100: 3279 | B100: DISTRATO | C100: 3847 | D100: FSA003 - AURIUM HOME | E100: ETAPA 01 | F100: TOWNHOUSE | G100: 6 | H100: FORMOSA | I100: ELZA MARIANO DE DEUS | J100: "56047177115" | K100: NOVKA| DF | L100: LUCIANO DE OLIVEIRA NASCIMENTO | M100: Não | N100: Não | O100: Não | P100: Não | Q100: Não | R100: Não | S100: Não | T100: 0 | U100: 0 | V100: 0 | W100: 0 | X100: 0 | Y100: 0 | Z100: 0 | AA100: 0 | AB100: 0 | AE100: Contrato Adimplente | AH100: 0 | AK100: 45338 | AP100: Real prime negócios imobiliários | AT100: 45498 | AU100: 45498 | AV100: DISTRATO | AW100: 45331 | AX100: 21181 | AY100: 850000 | BA100: FSA 03 | BB100: 21181 | BD100: Formosa | BE100: Goiás | BF100: 5561999363391 | BG100: Rua 27 Q 21 | BH100: 73802030 | BI100: Setor Bosque | BJ100: elza.deus@hotmail.com | BL100: 13183.69 | BQ100: 1974 | BR100: 5468 | BS100: Aposentado
...

Sheet Analise.IPC
E1: 46111 | G1: Repasses
C2: Imobiliária | D2: Consultores | E2: Data Início | F2: Qts Meses? | G2: 2024 | H2: 2025 | I2: 2026 | K2: IPC 2024 | L2: IPC 2025 | M2: IPC 2026 | N2: Meta | P2: Situação ? | R2: Gradadivo
A3: 1 | B3: 1 | C3: =VLOOKUP(D3,dinamica!A:B,2,0) -> AUTÔNOMOS | FSA | D3: CLEIDE ALVES DE OLIVEIRA | E3: =VLOOKUP(D3,[1]Colaboradores!$A$2:$D$65,4,0) -> 45769 | F3: =_xlfn.DAYS($E$1,E3)/30 -> 11.4 | H3: 8 | I3: 8 | K3: =G3/12 -> 0 | L3: =H3/12 -> 0.66666667 | M3: =I3/3 -> 2.6666667 | N3: =VLOOKUP(F3,$U$8:$V$93,2) -> 2 | P3: =IF(M3>=N3,"OK","Analisar") -> OK | Q3: Meta Gerente | U3: 0-3 meses: 2 repasses ou IPC 0,66;
A4: =A3+1 -> 2 | B4: =B3+1 -> 2 | C4: =VLOOKUP(D4,dinamica!A:B,2,0) -> AUTÔNOMOS | FSA | D4: ISABELLA PEREIRA FELICIANO | E4: =VLOOKUP(D4,[1]Colaboradores!$A$2:$D$65,4,0) -> 45156 | F4: =_xlfn.DAYS($E$1,E4)/30 -> 31.833333 | G4: 15 | H4: 34 | I4: 8 | K4: =G4/12 -> 1.25 | L4: =H4/12 -> 2.8333333 | M4: =I4/3 -> 2.6666667 | N4: =VLOOKUP(F4,$U$8:$V$93,2) -> 2 | P4: =IF(M4>=N4,"OK","Analisar") -> OK | Q4: =SUM(N3:N10) -> 12.98 | U4: 3-6 meses: 4 repasses ou IPC 1,33;
A5: =A4+1 -> 3 | B5: =B4+1 -> 3 | C5: =VLOOKUP(D5,dinamica!A:B,2,0) -> AUTÔNOMOS | FSA | D5: ANNA LUIZA PEREIRA DE SOUSA | E5: =VLOOKUP(D5,[1]Colaboradores!$A$2:$D$65,4,0) -> 45791 | F5: =_xlfn.DAYS($E$1,E5)/30 -> 10.666667 | H5: 20 | I5: 7 | K5: =G5/12 -> 0 | L5: =H5/12 -> 1.6666667 | M5: =I5/3 -> 2.3333333 | N5: =VLOOKUP(F5,$U$8:$V$93,2) -> 2 | P5: =IF(M5>=N5,"OK","Analisar") -> OK | Q5: =12/7 -> 1.7142857 | R5: Desenvolvimento | U5: 6-9 meses: 5 repasses ou IPC 1,66;
A6: =A5+1 -> 4 | B6: =B5+1 -> 4 | C6: =VLOOKUP(D6,dinamica!A:B,2,0) -> AUTÔNOMOS | FSA | D6: STEFFANY SILVA PINTO | E6: =VLOOKUP(D6,[1]Colaboradores!$A$2:$D$65,4,0) -> 45931 | F6: =_xlfn.DAYS($E$1,E6)/30 -> 6 | H6: 2 | I6: 4 | K6: =G6/12 -> 0 | L6: =H6/12 -> 0.16666667 | M6: =I6/3 -> 1.3333333 | N6: =VLOOKUP(F6,$U$8:$V$93,2) -> 1.33 | P6: =IF(M6>=N6,"OK","Analisar") -> OK | R6: Reposição | U6: Após 9 meses: 6 repasses ou IPC 2;
A7: =A6+1 -> 5 | B7: =B6+1 -> 5 | C7: =VLOOKUP(D7,dinamica!A:B,2,0) -> AUTÔNOMOS | FSA | D7: CAMILA FERNANDES DA SILVA | E7: =VLOOKUP(D7,[1]Colaboradores!$A$2:$D$65,4,0) -> 45261 | F7: =_xlfn.DAYS($E$1,E7)/30 -> 28.333333 | G7: 15 | H7: 19 | I7: 4 | K7: =G7/12 -> 1.25 | L7: =H7/12 -> 1.5833333 | M7: =I7/3 -> 1.3333333 | N7: =VLOOKUP(F7,$U$8:$V$93,2) -> 2 | P7: =IF(M7>=N7,"OK","Analisar") -> Analisar | R7: Críterios Definido
A8: =A7+1 -> 6 | B8: =B7+1 -> 6 | C8: =VLOOKUP(D8,dinamica!A:B,2,0) -> AUTÔNOMOS | FSA | D8: ANIBAL HAMU NETO | E8: =VLOOKUP(D8,[1]Colaboradores!$A$2:$D$65,4,0) -> 45931 | F8: =_xlfn.DAYS($E$1,E8)/30 -> 6 | H8: 1 | I8: 1 | K8: =G8/12 -> 0 | L8: =H8/12 -> 0.083333333 | M8: =I8/3 -> 0.33333333 | N8: =VLOOKUP(F8,$U$8:$V$93,2) -> 1.33 | P8: =IF(M8>=N8,"OK","Analisar") -> Analisar | Q8: tentar | U8: 0 | V8: 0.66
A9: =A8+1 -> 7 | B9: =B8+1 -> 7 | C9: =VLOOKUP(D9,dinamica!A:B,2,0) -> AUTÔNOMOS | FSA | D9: EMMANUELY FERNANDA DO NASCIMENTO | E9: =VLOOKUP(D9,[1]Colaboradores!$A$2:$D$65,4,0) -> 45882 | F9: =_xlfn.DAYS($E$1,E9)/30 -> 7.6333333 | H9: 3 | I9: 1 | K9: =G9/12 -> 0 | L9: =H9/12 -> 0.25 | M9: =I9/3 -> 0.33333333 | N9: =VLOOKUP(F9,$U$8:$V$93,2) -> 1.66 | P9: =IF(M9>=N9,"OK","Analisar") -> Analisar | Q9: desligou 22/4 | R9: Racional crescimento Gradativo | U9: =1+U8 -> 1 | V9: 0.66
A10: =A9+1 -> 8 | B10: =B9+1 -> 8 | C10: AUTÔNOMOS | FSA | D10: Thâmara Rafaella de Melo Santos | E10: =VLOOKUP(D10,[1]Colaboradores!$A$2:$D$65,4,0) -> 24/03/2026 | F10: =_xlfn.DAYS($E$1,E10)/30 -> 0.2 | N10: =VLOOKUP(F10,$U$8:$V$93,2) -> 0.66 | P10: =IF(M10>=N10,"OK","Analisar") -> Analisar | U10: =1+U9 -> 2 | V10: 0.66
A11: =A10+1 -> 9 | B11: 1 | C11: AUTÔNOMOS 2 | FSA | D11: KEULLY DE SOUSA BRAGA | E11: =VLOOKUP(D11,[1]Colaboradores!$A$2:$D$65,4,0) -> 46050 | F11: =_xlfn.DAYS($E$1,E11)/30 -> 2.0333333 | I11: 5 | K11: =G11/12 -> 0 | L11: =H11/12 -> 0 | M11: =I11/3 -> 1.6666667 | N11: =VLOOKUP(F11,$U$8:$V$93,2) -> 0.66 | P11: =IF(M11>=N11,"OK","Analisar") -> OK | Q11: Meta Gerente | U11: =1+U10 -> 3 | V11: 0.66
A12: =A11+1 -> 10 | B12: =B11+1 -> 2 | C12: =VLOOKUP(D12,dinamica!A:B,2,0) -> AUTÔNOMOS 2 | FSA | D12: GYOVANA FERNANDES ALMEIDA CASTRO | E12: =VLOOKUP(D12,[1]Colaboradores!$A$2:$D$65,4,0) -> 45868 | F12: =_xlfn.DAYS($E$1,E12)/30 -> 8.1 | H12: 4 | I12: 5 | K12: =G12/12 -> 0 | L12: =H12/12 -> 0.33333333 | M12: =I12/3 -> 1.6666667 | N12: =VLOOKUP(F12,$U$8:$V$93,2) -> 1.66 | P12: =IF(M12>=N12,"OK","Analisar") -> OK | Q12: =SUM(N11:N18) -> 9.62 | R12: Replicar Gerentes | U12: =1+U11 -> 4 | V12: 1.33
A13: =A12+1 -> 11 | B13: =B12+1 -> 3 | C13: =VLOOKUP(D13,dinamica!A:B,2,0) -> AUTÔNOMOS 2 | FSA | D13: THAIRINE STEFANNI RODRIGUES DA SILVA | E13: =VLOOKUP(D13,[1]Colaboradores!$A$2:$D$65,4,0) -> 45868 | F13: =_xlfn.DAYS($E$1,E13)/30 -> 8.1 | H13: 4 | I13: 3 | K13: =G13/12 -> 0 | L13: =H13/12 -> 0.33333333 | M13: =I13/3 -> 1 | N13: =VLOOKUP(F13,$U$8:$V$93,2) -> 1.66 | P13: =IF(M13>=N13,"OK","Analisar") -> Analisar | U13: =1+U12 -> 5 | V13: 1.33
A14: =A13+1 -> 12 | B14: =B13+1 -> 4 | C14: AUTÔNOMOS 2 | FSA | D14: MARCILENE DOS REIS CARVALHO | E14: =VLOOKUP(D14,[1]Colaboradores!$A$2:$D$65,4,0) -> 45531 | F14: =_xlfn.DAYS($E$1,E14)/30 -> 19.333333 | G14: 1 | H14: 9 | I14: 2 | K14: =G14/12 -> 0.083333333 | L14: =H14/12 -> 0.75 | M14: =I14/3 -> 0.66666667 | N14: =VLOOKUP(F14,$U$8:$V$93,2) -> 2 | P14: =IF(M14>=N14,"OK","Analisar") -> Analisar | R14: Rever Remunneração | U14: =1+U13 -> 6 | V14: 1.33
A15: =A14+1 -> 13 | B15: =B14+1 -> 5 | C15: AUTÔNOMOS 2 | FSA | D15: LETÍCIA LORRANNY SANTOS DOURADO | E15: =VLOOKUP(D15,[1]Colaboradores!$A$2:$D$65,4,0) -> 45868 | F15: =_xlfn.DAYS($E$1,E15)/30 -> 8.1 | H15: 2 | I15: 2 | K15: =G15/12 -> 0 | L15: =H15/12 -> 0.16666667 | M15: =I15/3 -> 0.66666667 | N15: =VLOOKUP(F15,$U$8:$V$93,2) -> 1.66 | P15: =IF(M15>=N15,"OK","Analisar") -> Analisar | U15: =1+U14 -> 7 | V15: 1.66
A16: =A15+1 -> 14 | B16: =B15+1 -> 6 | C16: AUTÔNOMOS 2 | FSA | D16: Erika Alves Gomes | E16: =VLOOKUP(D16,[1]Colaboradores!$A$2:$D$65,4,0) -> 46099 | F16: =_xlfn.DAYS($E$1,E16)/30 -> 0.4 | N16: =VLOOKUP(F16,$U$8:$V$93,2) -> 0.66 | P16: =IF(M16>=N16,"OK","Analisar") -> Analisar | U16: =1+U15 -> 8 | V16: 1.66
A17: =A16+1 -> 15 | B17: =B16+1 -> 7 | C17: AUTÔNOMOS 2 | FSA | D17: Pabline Micheli Oliveira da Silva | E17: =VLOOKUP(D17,[1]Colaboradores!$A$2:$D$65,4,0) -> 46099 | F17: =_xlfn.DAYS($E$1,E17)/30 -> 0.4 | N17: =VLOOKUP(F17,$U$8:$V$93,2) -> 0.66 | P17: =IF(M17>=N17,"OK","Analisar") -> Analisar | U17: =1+U16 -> 9 | V17: 1.66
A18: =A17+1 -> 16 | B18: =B17+1 -> 8 | C18: AUTÔNOMOS 2 | FSA | D18: JOCICLEIDE FERREIRA DA PAIXÃO | E18: =VLOOKUP(D18,[1]Colaboradores!$A$2:$D$65,4,0) -> 46125 | F18: =_xlfn.DAYS($E$1,E18)/30 -> -0.46666667 | N18: 0.66 | P18: =IF(M18>=N18,"OK","Analisar") -> Analisar | U18: =1+U17 -> 10 | V18: 2
A19: =A18+1 -> 17 | B19: 1 | C19: EQUIPE PRÓPRIA |FSA | D19: Gabriel do Nascimento Dias | E19: =VLOOKUP(D19,[1]Colaboradores!$A$2:$D$65,4,0) -> 45231 | F19: =_xlfn.DAYS($E$1,E19)/30 -> 29.333333 | G19: 27 | H19: 27 | I19: 7 | K19: =G19/12 -> 2.25 | L19: =H19/12 -> 2.25 | M19: =I19/3 -> 2.3333333 | N19: =VLOOKUP(F19,$U$8:$V$93,2) -> 2 | P19: =IF(M19>=N19,"OK","Analisar") -> OK | Q19: Meta Gerente | U19: =1+U18 -> 11 | V19: 2
A20: =A19+1 -> 18 | B20: =B19+1 -> 2 | C20: EQUIPE PRÓPRIA |FSA | D20: Lucas Paulo Marques Pinto | E20: =VLOOKUP(D20,[1]Colaboradores!$A$2:$D$65,4,0) -> 45880 | F20: =_xlfn.DAYS($E$1,E20)/30 -> 7.7 | H20: 6 | I20: 6 | K20: =G20/12 -> 0 | L20: =H20/12 -> 0.5 | M20: =I20/3 -> 2 | N20: =VLOOKUP(F20,$U$8:$V$93,2) -> 1.66 | P20: =IF(M20>=N20,"OK","Analisar") -> OK | Q20: =SUM(N19:N28) -> 12.31 | U20: =1+U19 -> 12 | V20: 2
A21: =A20+1 -> 19 | B21: =B20+1 -> 3 | C21: EQUIPE PRÓPRIA |FSA | D21: Maria Eugenia Martins alves | E21: =VLOOKUP(D21,[1]Colaboradores!$A$2:$D$65,4,0) -> 45902 | F21: =_xlfn.DAYS($E$1,E21)/30 -> 6.9666667 | H21: 8 | I21: 5 | K21: =G21/12 -> 0 | L21: =H21/12 -> 0.66666667 | M21: =I21/3 -> 1.6666667 | N21: =VLOOKUP(F21,$U$8:$V$93,2) -> 1.33 | P21: =IF(M21>=N21,"OK","Analisar") -> OK | U21: =1+U20 -> 13 | V21: 2
A22: =A21+1 -> 20 | B22: =B21+1 -> 4 | C22: EQUIPE PRÓPRIA |FSA | D22: INGRID ALVES DAPARECIDA | E22: =VLOOKUP(D22,[1]Colaboradores!$A$2:$D$65,4,0) -> 45267 | F22: =_xlfn.DAYS($E$1,E22)/30 -> 28.133333 | G22: 21 | H22: 27 | I22: 4 | K22: =G22/12 -> 1.75 | L22: =H22/12 -> 2.25 | M22: =I22/3 -> 1.3333333 | N22: =VLOOKUP(F22,$U$8:$V$93,2) -> 2 | P22: =IF(M22>=N22,"OK","Analisar") -> Analisar | U22: =1+U21 -> 14 | V22: 2
A23: =A22+1 -> 21 | B23: =B22+1 -> 5 | C23: EQUIPE PRÓPRIA |FSA | D23: Nauane Martins Da Silva Oliveira | E23: =VLOOKUP(D23,[1]Colaboradores!$A$2:$D$65,4,0) -> 23/08/2023 | F23: =_xlfn.DAYS($E$1,E23)/30 -> 31.666667 | G23: 16 | H23: 26 | I23: 4 | K23: =G23/12 -> 1.3333333 | L23: =H23/12 -> 2.1666667 | M23: =I23/3 -> 1.3333333 | N23: =VLOOKUP(F23,$U$8:$V$93,2) -> 2 | P23: =IF(M23>=N23,"OK","Analisar") -> Analisar | U23: =1+U22 -> 15 | V23: 2
A24: =A23+1 -> 22 | B24: =B23+1 -> 6 | C24: EQUIPE PRÓPRIA |FSA | D24: Ryan Gomes Calazans | E24: =VLOOKUP(D24,[1]Colaboradores!$A$2:$D$65,4,0) -> 45231 | F24: =_xlfn.DAYS($E$1,E24)/30 -> 29.333333 | G24: 23 | H24: 21 | I24: 3 | K24: =G24/12 -> 1.9166667 | L24: =H24/12 -> 1.75 | M24: =I24/3 -> 1 | N24: =VLOOKUP(F24,$U$8:$V$93,2) -> 2 | P24: =IF(M24>=N24,"OK","Analisar") -> Analisar | U24: =1+U23 -> 16 | V24: 2
A25: =A24+1 -> 23 | C25: EQUIPE PRÓPRIA |FSA | D25: MARIA DAIANA DA SILVA BRANDAO | E25: =VLOOKUP(D25,[1]Colaboradores!$A$2:$D$65,4,0) -> 45902 | F25: =_xlfn.DAYS($E$1,E25)/30 -> 6.9666667 | H25: 4 | I25: 2 | K25: =G25/12 -> 0 | L25: =H25/12 -> 0.33333333 | M25: =I25/3 -> 0.66666667 | P25: =IF(M25>=N25,"OK","Analisar") -> OK | U25: =1+U24 -> 17 | V25: 2
A26: =A25+1 -> 24 | C26: EQUIPE PRÓPRIA |FSA | D26: SAMARA FEITOSA VALADARES GENEROSO | E26: =VLOOKUP(D26,[1]Colaboradores!$A$2:$D$65,4,0) -> 21/05/2025 | F26: =_xlfn.DAYS($E$1,E26)/30 -> 10.433333 | H26: 8 | K26: =G26/12 -> 0 | L26: =H26/12 -> 0.66666667 | M26: =I26/3 -> 0 | P26: =IF(M26>=N26,"OK","Analisar") -> OK | U26: =1+U25 -> 18 | V26: 2
A27: =A26+1 -> 25 | B27: =B24+1 -> 7 | C27: EQUIPE PRÓPRIA |FSA | D27: Valmir Santana dos Santos | E27: =VLOOKUP(D27,[1]Colaboradores!$A$2:$D$65,4,0) -> 18/03/2026 | F27: =_xlfn.DAYS($E$1,E27)/30 -> 0.4 | N27: =VLOOKUP(F27,$U$8:$V$93,2) -> 0.66 | P27: =IF(M27>=N27,"OK","Analisar") -> Analisar | U27: =1+U26 -> 19 | V27: 2
A28: =A27+1 -> 26 | B28: =B27+1 -> 8 | C28: EQUIPE PRÓPRIA |FSA | D28: MURIELLY DE SOUSA SANTOS | E28: =VLOOKUP(D28,[1]Colaboradores!$A$2:$D$65,4,0) -> 18/03/2026 | F28: =_xlfn.DAYS($E$1,E28)/30 -> 0.4 | N28: =VLOOKUP(F28,$U$8:$V$93,2) -> 0.66 | P28: =IF(M28>=N28,"OK","Analisar") -> Analisar | U28: =1+U27 -> 20 | V28: 2
A29: =A28+1 -> 27 | B29: =B28+1 -> 9 | C29: EQUIPE PRÓPRIA |FSA | D29: NATÁLIA NOGUEIRA AGUIAR | E29: =VLOOKUP(D29,[1]Colaboradores!$A$2:$D$65,4,0) -> 46118 | F29: =_xlfn.DAYS($E$1,E29)/30 -> -0.23333333 | N29: =VLOOKUP(F29,$U$8:$V$93,2) -> #N/A | P29: =IF(M29>=N29,"OK","Analisar") -> #N/A | U29: =1+U28 -> 21 | V29: 2
C30: EQUIPE PRÓPRIA |FSA | D30: LEONARD LUIS MOGENA PEREZ | E30: =VLOOKUP(D30,[1]Colaboradores!$A$2:$D$65,4,0) -> 25/02/2025 | F30: =_xlfn.DAYS($E$1,E30)/30 -> 13.266667 | H30: 9 | I30: 1 | K30: =G30/12 -> 0 | L30: =H30/12 -> 0.75 | M30: =I30/3 -> 0.33333333 | N30: =VLOOKUP(F30,$U$8:$V$93,2) -> 2 | P30: Desligado | U30: =1+U29 -> 22 | V30: 2
A31: =A29+1 -> 28 | B31: 1 | C31: CANAL VIRTUAL 1 | D31: MARIA EDUARDA VIEIRA DAMASCENO | E31: =VLOOKUP(D31,[1]Colaboradores!$A$2:$D$65,4,0) -> 45384 | F31: =_xlfn.DAYS($E$1,E31)/30 -> 24.233333 | H31: 15 | I31: 7 | K31: =G31/12 -> 0 | L31: =H31/12 -> 1.25 | M31: =I31/3 -> 2.3333333 | N31: =VLOOKUP(F31,$U$8:$V$93,2) -> 2 | P31: =IF(M31>=N31,"OK","Analisar") -> OK | Q31: Meta Gerente | U31: =1+U30 -> 23 | V31: 2
A32: =A31+1 -> 29 | B32: =B31+1 -> 2 | C32: CANAL VIRTUAL 1 | D32: Daniel Andrade dos Santos | E32: =VLOOKUP(D32,[1]Colaboradores!$A$2:$D$65,4,0) -> 45566 | F32: =_xlfn.DAYS($E$1,E32)/30 -> 18.166667 | G32: 2 | H32: 28 | I32: 3 | K32: =G32/12 -> 0.16666667 | L32: =H32/12 -> 2.3333333 | M32: =I32/3 -> 1 | N32: =VLOOKUP(F32,$U$8:$V$93,2) -> 2 | P32: =IF(M32>=N32,"OK","Analisar") -> Analisar | Q32: =SUM(N31:N37) -> 9.02 | U32: =1+U31 -> 24 | V32: 2
A33: =A32+1 -> 30 | B33: =B32+1 -> 3 | C33: CANAL VIRTUAL 1 | D33: LUCAS DE SOUZA RODRIGUES | E33: =VLOOKUP(D33,[1]Colaboradores!$A$2:$D$65,4,0) -> 46028 | F33: =_xlfn.DAYS($E$1,E33)/30 -> 2.7666667 | I33: 2 | K33: =G33/12 -> 0 | L33: =H33/12 -> 0 | M33: =I33/3 -> 0.66666667 | N33: =VLOOKUP(F33,$U$8:$V$93,2) -> 0.66 | P33: =IF(M33>=N33,"OK","Analisar") -> OK | U33: =1+U32 -> 25 | V33: 2
A34: =A33+1 -> 31 | B34: =B33+1 -> 4 | C34: CANAL VIRTUAL 1 | D34: CAIO BRENDON LOPES MARTINS | E34: =VLOOKUP(D34,[1]Colaboradores!$A$2:$D$65,4,0) -> 21/07/2025 | F34: =_xlfn.DAYS($E$1,E34)/30 -> 8.4 | H34: 2 | I34: 1 | K34: =G34/12 -> 0 | L34: =H34/12 -> 0.16666667 | M34: =I34/3 -> 0.33333333 | N34: =VLOOKUP(F34,$U$8:$V$93,2) -> 1.66 | P34: =IF(M34>=N34,"OK","Analisar") -> Analisar | U34: =1+U33 -> 26 | V34: 2
A35: =A34+1 -> 32 | B35: =B34+1 -> 5 | C35: CANAL VIRTUAL 1 | D35: LUCAS RAMOS DA VICTÓRIA | E35: =VLOOKUP(D35,[1]Colaboradores!$A$2:$D$65,4,0) -> 46118 | F35: =_xlfn.DAYS($E$1,E35)/30 -> -0.23333333 | N35: 0.7 | P35: =IF(M35>=N35,"OK","Analisar") -> Analisar | U35: =1+U34 -> 27 | V35: 2
A36: =A35+1 -> 33 | B36: =B35+1 -> 6 | C36: CANAL VIRTUAL 1 | D36: MARTA ANASTACIO NERES | E36: =VLOOKUP(D36,[1]Colaboradores!$A$2:$D$65,4,0) -> 21/12/2023 | F36: =_xlfn.DAYS($E$1,E36)/30 -> 27.666667 | N36: =VLOOKUP(F36,$U$8:$V$93,2) -> 2 | P36: =IF(M36>=N36,"OK","Analisar") -> Analisar | U36: =1+U35 -> 28 | V36: 2
A37: =A36+1 -> 34 | B37: =B36+1 -> 7 | C37: CANAL VIRTUAL 1 | D37: LUIS RAFAEL DO ROSARIO | E37: =VLOOKUP(D37,[1]Colaboradores!$A$2:$D$65,4,0) -> 23/06/2025 | F37: =_xlfn.DAYS($E$1,E37)/30 -> 9.3333333 | H37: 3 | K37: =G37/12 -> 0 | L37: =H37/12 -> 0.25 | M37: =I37/3 -> 0 | P37: Afastado | U37: =1+U36 -> 29 | V37: 2
A38: =A37+1 -> 35 | B38: 1 | C38: =VLOOKUP(D44,dinamica!A:B,2,0) -> CANAL VIRTUAL 2 | D38: LETICIA SANTOS DA SILVA | E38: =VLOOKUP(D38,[1]Colaboradores!$A$2:$D$65,4,0) -> 18/11/2025 | F38: =_xlfn.DAYS($E$1,E38)/30 -> 4.4 | I38: 4 | K38: =G38/12 -> 0 | L38: =H38/12 -> 0 | M38: =I38/3 -> 1.3333333 | N38: =VLOOKUP(F38,$U$8:$V$93,2) -> 1.33 | P38: =IF(M38>=N38,"OK","Analisar") -> OK | Q38: Meta Gerente | U38: =1+U37 -> 30 | V38: 2
A39: =A38+1 -> 36 | B39: =B38+1 -> 2 | C39: CANAL VIRTUAL 2 | D39: SANDRA SANTANA DOS SANTOS | E39: =VLOOKUP(D39,[1]Colaboradores!$A$2:$D$65,4,0) -> 45141 | F39: =_xlfn.DAYS($E$1,E39)/30 -> 32.333333 | G39: 1 | H39: 16 | I39: 2 | K39: =G39/12 -> 0.083333333 | L39: =H39/12 -> 1.3333333 | M39: =I39/3 -> 0.66666667 | N39: =VLOOKUP(F39,$U$8:$V$93,2) -> 2 | P39: =IF(M39>=N39,"OK","Analisar") -> Analisar | Q39: =SUM(N38:N43) -> 7.31 | U39: =1+U38 -> 31 | V39: 2
A40: =A39+1 -> 37 | B40: =B39+1 -> 3 | C40: CANAL VIRTUAL 2 | D40: Lucas Braga de Souza Oliveira | E40: =VLOOKUP(D40,[1]Colaboradores!$A$2:$D$65,4,0) -> 46076 | F40: =_xlfn.DAYS($E$1,E40)/30 -> 1.1666667 | I40: 1 | K40: =G40/12 -> 0 | L40: =H40/12 -> 0 | M40: =I40/3 -> 0.33333333 | N40: =VLOOKUP(F40,$U$8:$V$93,2) -> 0.66 | P40: =IF(M40>=N40,"OK","Analisar") -> Analisar | U40: =1+U39 -> 32 | V40: 2
A41: =A40+1 -> 38 | B41: =B40+1 -> 4 | C41: CANAL VIRTUAL 2 | D41: ALEXANDRE RABELLO BARBOSA | E41: =VLOOKUP(D41,[1]Colaboradores!$A$2:$D$65,4,0) -> 18/03/2026 | F41: =_xlfn.DAYS($E$1,E41)/30 -> 0.4 | N41: =VLOOKUP(F41,$U$8:$V$93,2) -> 0.66 | P41: =IF(M41>=N41,"OK","Analisar") -> Analisar | U41: =1+U40 -> 33 | V41: 2
A42: =A41+1 -> 39 | B42: =B41+1 -> 5 | C42: CANAL VIRTUAL 2 | D42: BRENDA MONICA DOS SANTOS | E42: =VLOOKUP(D42,[1]Colaboradores!$A$2:$D$65,4,0) -> 46043 | F42: =_xlfn.DAYS($E$1,E42)/30 -> 2.2666667 | N42: =VLOOKUP(F42,$U$8:$V$93,2) -> 0.66 | P42: =IF(M42>=N42,"OK","Analisar") -> Analisar | U42: =1+U41 -> 34 | V42: 2
A43: =A42+1 -> 40 | B43: =B42+1 -> 6 | C43: CANAL VIRTUAL 2 | D43: LUANA SANTANA DOS SANTOS | E43: =VLOOKUP(D43,[1]Colaboradores!$A$2:$D$65,4,0) -> 45294 | F43: =_xlfn.DAYS($E$1,E43)/30 -> 27.233333 | N43: =VLOOKUP(F43,$U$8:$V$93,2) -> 2 | P43: =IF(M43>=N43,"OK","Analisar") -> Analisar | U43: =1+U42 -> 35 | V43: 2
C44: CANAL VIRTUAL 2 | D44: LUCIANO PONTES SILVA JUNIOR - CLT | E44: =VLOOKUP(D44,[1]Colaboradores!$A$2:$D$65,4,0) -> #N/A | F44: Desligados | H44: 1 | I44: 6 | K44: =G44/12 -> 0 | L44: =H44/12 -> 0.083333333 | P44: Desligado | U44: =1+U43 -> 36 | V44: 2
A45: =A43+1 -> 41 | B45: 1 | C45: EQUIPE PRÓPRIA | AGL | D45: MAYSA GABRIELA GONCALVES OLIVEIRA | E45: =VLOOKUP(D45,[1]Colaboradores!$A$2:$D$65,4,0) -> 44904 | F45: =_xlfn.DAYS($E$1,E45)/30 -> 40.233333 | G45: 13 | H45: 9 | I45: 4 | K45: =G45/12 -> 1.0833333 | L45: =H45/12 -> 0.75 | M45: =I45/3 -> 1.3333333 | N45: =VLOOKUP(F45,$U$8:$V$93,2) -> 2 | P45: =IF(M45>=N45,"OK","Analisar") -> Analisar | Q45: Meta Gerente | U45: =1+U44 -> 37 | V45: 2
A46: =A45+1 -> 42 | B46: =B45+1 -> 2 | C46: EQUIPE PRÓPRIA | AGL | D46: MILENE DE ALMEIDA LIMA | E46: =VLOOKUP(D46,[1]Colaboradores!$A$2:$D$65,4,0) -> 21/07/2025 | F46: =_xlfn.DAYS($E$1,E46)/30 -> 8.4 | H46: 3 | I46: 4 | K46: =G46/12 -> 0 | L46: =H46/12 -> 0.25 | M46: =I46/3 -> 1.3333333 | N46: =VLOOKUP(F46,$U$8:$V$93,2) -> 1.66 | P46: =IF(M46>=N46,"OK","Analisar") -> Analisar | Q46: =SUM(N45:N51) -> 7.98 | U46: =1+U45 -> 38 | V46: 2
A47: =A46+1 -> 43 | B47: =B46+1 -> 3 | C47: EQUIPE PRÓPRIA | AGL | D47: JONATAN CASTRO DA SILVA | E47: =VLOOKUP(D47,[1]Colaboradores!$A$2:$D$65,4,0) -> 45298 | F47: =_xlfn.DAYS($E$1,E47)/30 -> 27.1 | G47: 8 | H47: 16 | I47: 3 | K47: =G47/12 -> 0.66666667 | L47: =H47/12 -> 1.3333333 | M47: =I47/3 -> 1 | N47: =VLOOKUP(F47,$U$8:$V$93,2) -> 2 | P47: =IF(M47>=N47,"OK","Analisar") -> Analisar | U47: =1+U46 -> 39 | V47: 2
A48: =A47+1 -> 44 | B48: =B47+1 -> 4 | C48: EQUIPE PRÓPRIA | AGL | D48: ARIANI MORAIS DE SOUSA PEREIRA | E48: =VLOOKUP(D48,[1]Colaboradores!$A$2:$D$65,4,0) -> 21/07/2025 | F48: =_xlfn.DAYS($E$1,E48)/30 -> 8.4 | H48: 10 | I48: 3 | K48: =G48/12 -> 0 | L48: =H48/12 -> 0.83333333 | M48: =I48/3 -> 1 | N48: =VLOOKUP(F48,$U$8:$V$93,2) -> 1.66 | P48: =IF(M48>=N48,"OK","Analisar") -> Analisar | U48: =1+U47 -> 40 | V48: 2
A49: =A48+1 -> 45 | B49: =B48+1 -> 5 | C49: EQUIPE PRÓPRIA | AGL | D49: YVELISE FERREIRA PINHEIRO | E49: =VLOOKUP(D49,[1]Colaboradores!$A$2:$D$65,4,0) -> 46056 | F49: =_xlfn.DAYS($E$1,E49)/30 -> 1.8333333 | H49: 3 | I49: 1 | K49: =G49/12 -> 0 | L49: =H49/12 -> 0.25 | P49: =IF(M49>=N49,"OK","Analisar") -> OK | U49: =1+U48 -> 41 | V49: 2
A50: =A49+1 -> 46 | B50: =B49+1 -> 6 | C50: EQUIPE PRÓPRIA | AGL | D50: REBECA DO ESPIRITO SANTO SOUZA CARVALHO | E50: =VLOOKUP(D50,[1]Colaboradores!$A$2:$D$65,4,0) -> 46056 | F50: =_xlfn.DAYS($E$1,E50)/30 -> 1.8333333 | H50: 7 | K50: =G50/12 -> 0 | L50: =H50/12 -> 0.58333333 | P50: =IF(M50>=N50,"OK","Analisar") -> OK | U50: =1+U49 -> 42 | V50: 2
A51: =A50+1 -> 47 | B51: =B50+1 -> 7 | C51: EQUIPE PRÓPRIA | AGL | D51: NATASHA LUCILIA BARBOSA | E51: =VLOOKUP(D51,[1]Colaboradores!$A$2:$D$65,4,0) -> 45994 | F51: =_xlfn.DAYS($E$1,E51)/30 -> 3.9 | H51: 1 | I51: 4 | K51: =G51/12 -> 0 | L51: =H51/12 -> 0.083333333 | M51: =I51/3 -> 1.3333333 | N51: =VLOOKUP(F51,$U$8:$V$93,2) -> 0.66 | P51: =IF(M51>=N51,"OK","Analisar") -> OK | U51: =1+U50 -> 43 | V51: 2
B52: 1 | C52: EQUIPE PRÓPRIA 2 | AGL | D52: FABIANE BEZERRA MOREIRA DOS SANTOS | E52: =VLOOKUP(D52,[1]Colaboradores!$A$2:$D$65,4,0) -> 45937 | F52: =_xlfn.DAYS($E$1,E52)/30 -> 5.8 | H52: 1 | I52: 5 | K52: =G52/12 -> 0 | L52: =H52/12 -> 0.083333333 | M52: =I52/3 -> 1.6666667 | N52: =VLOOKUP(F52,$U$8:$V$93,2) -> 1.33 | P52: =IF(M52>=N52,"OK","Analisar") -> OK | Q52: Meta Gerente | U52: =1+U51 -> 44 | V52: 2
A53: =+A51+1 -> 48 | B53: =B52+1 -> 2 | C53: EQUIPE PRÓPRIA 2 | AGL | D53: JOAO VITOR BRITO DE ANDRADE | E53: =VLOOKUP(D53,[1]Colaboradores!$A$2:$D$65,4,0) -> 45937 | F53: =_xlfn.DAYS($E$1,E53)/30 -> 5.8 | H53: 2 | I53: 4 | K53: =G53/12 -> 0 | L53: =H53/12 -> 0.16666667 | M53: =I53/3 -> 1.3333333 | N53: =VLOOKUP(F53,$U$8:$V$93,2) -> 1.33 | P53: =IF(M53>=N53,"OK","Analisar") -> OK | Q53: =SUM(N52:N58) -> 8.64 | U53: =1+U52 -> 45 | V53: 2
A54: =A53+1 -> 49 | B54: =B53+1 -> 3 | C54: EQUIPE PRÓPRIA 2 | AGL | D54: WANDERSON ROMERO COELHO DA SILVA | E54: =VLOOKUP(D54,[1]Colaboradores!$A$2:$D$65,4,0) -> 46056 | F54: =_xlfn.DAYS($E$1,E54)/30 -> 1.8333333 | H54: 8 | I54: 4 | K54: =G54/12 -> 0 | L54: =H54/12 -> 0.66666667 | M54: =I54/3 -> 1.3333333 | N54: =VLOOKUP(F54,$U$8:$V$93,2) -> 0.66 | P54: =IF(M54>=N54,"OK","Analisar") -> OK | U54: =1+U53 -> 46 | V54: 2
A55: =A54+1 -> 50 | B55: =B54+1 -> 4 | C55: EQUIPE PRÓPRIA 2 | AGL | D55: JULIANA MARIA DE SOUZA | E55: =VLOOKUP(D55,[1]Colaboradores!$A$2:$D$65,4,0) -> 45965 | F55: =_xlfn.DAYS($E$1,E55)/30 -> 4.8666667 | I55: 4 | K55: =G55/12 -> 0 | L55: =H55/12 -> 0 | M55: =I55/3 -> 1.3333333 | N55: =VLOOKUP(F55,$U$8:$V$93,2) -> 1.33 | P55: =IF(M55>=N55,"OK","Analisar") -> OK | U55: =1+U54 -> 47 | V55: 2
A56: =A55+1 -> 51 | B56: =B55+1 -> 5 | C56: EQUIPE PRÓPRIA 2 | AGL | D56: REBECA CRISTHINA PIRES DIAS | E56: =VLOOKUP(D56,[1]Colaboradores!$A$2:$D$65,4,0) -> 45965 | F56: =_xlfn.DAYS($E$1,E56)/30 -> 4.8666667 | I56: 2 | K56: =G56/12 -> 0 | L56: =H56/12 -> 0 | M56: =I56/3 -> 0.66666667 | N56: =VLOOKUP(F56,$U$8:$V$93,2) -> 1.33 | P56: =IF(M56>=N56,"OK","Analisar") -> Analisar | U56: =1+U55 -> 48 | V56: 2
A57: =A56+1 -> 52 | B57: =B56+1 -> 6 | C57: EQUIPE PRÓPRIA 2 | AGL | D57: LUIS ALVES DOS SANTOS DA SILVA ROCHA | E57: =VLOOKUP(D57,[1]Colaboradores!$A$2:$D$65,4,0) -> 23/08/2023 | F57: =_xlfn.DAYS($E$1,E57)/30 -> 31.666667 | G57: 13 | H57: 14 | I57: 1 | K57: =G57/12 -> 1.0833333 | L57: =H57/12 -> 1.1666667 | M57: =I57/3 -> 0.33333333 | N57: =VLOOKUP(F57,$U$8:$V$93,2) -> 2 | P57: =IF(M57>=N57,"OK","Analisar") -> Analisar | U57: =1+U56 -> 49 | V57: 2
A58: =A57+1 -> 53 | B58: =B57+1 -> 7 | C58: EQUIPE PRÓPRIA 2 | AGL | D58: ANA LUIZA ENTREPORTES DA COSTA | E58: =VLOOKUP(D58,[1]Colaboradores!$A$2:$D$65,4,0) -> 46099 | F58: =_xlfn.DAYS($E$1,E58)/30 -> 0.4 | N58: =VLOOKUP(F58,$U$8:$V$93,2) -> 0.66 | P58: =IF(M58>=N58,"OK","Analisar") -> Analisar | U58: =1+U57 -> 50 | V58: 2
U59: =1+U58 -> 51 | V59: 2
U60: =1+#REF! -> #REF! | V60: 2
U61: =1+U60 -> #REF! | V61: 2
U62: =1+U61 -> #REF! | V62: 2
U63: =1+U62 -> #REF! | V63: 2
U64: =1+U63 -> #REF! | V64: 2
U65: =1+U64 -> #REF! | V65: 2
U66: =1+U65 -> #REF! | V66: 2
U67: =1+U66 -> #REF! | V67: 2
U68: =1+U67 -> #REF! | V68: 2
U69: =1+U68 -> #REF! | V69: 2
U70: =1+U69 -> #REF! | V70: 2
U71: =1+U70 -> #REF! | V71: 2
U72: =1+U71 -> #REF! | V72: 2
... U93: =1+U92 -> #REF! | V93: 2

Sheet Analise.IPC.ajuste.maio
B1: =B59+B70+B88+B99+B109 -> 40 | D1: =COUNTA(D52:D109)-1 -> 22 | T1: =SUM(T6:T102) -> 49 | U1: Meta FSA | V1: =SUM(U6:U46) -> 35 | W1: Meta AGL | Z1: =SUM(U52:U115) -> 32
B2: =B15+B26+B38+B47 -> 36 | D2: =COUNTA(D6:D43) -> 26
F3: 46111 | H3: Repasses | Z3: =SUM(U52:U110) -> 32
C4: Imobiliária | D4: Imobiliária Maio | E4: Consultores | F4: Data Início | G4: Qts Meses? | H4: 2024 | I4: 2025 | J4: 2026 | L4: IPC 2024 | M4: IPC 2025 | N4: IPC 2026 | O4: Meta | Q4: Situação ? | R4: Prod. Time | S4: Gradadivo | T4: Qtd Consoultores | U4: Meta Maio | V4: Parâmetros | AF4: nome
T5: Alana | AB5: Validar? | AF5: Isabella Pereira Feliciano
B6: 1 | C6: =VLOOKUP(E6,dinamica!A:B,2,0) -> AUTÔNOMOS | FSA | D6: AUTÔNOMOS | FSA | E6: CLEIDE ALVES DE OLIVEIRA | F6: =VLOOKUP(E6,[1]Colaboradores!$A$2:$D$65,4,0) -> 45769 | G6: =_xlfn.DAYS($F$3,F6)/30 -> 11.4 | I6: 8 | J6: 8 | L6: =H6/12 -> 0 | M6: =I6/12 -> 0.66666667 | N6: =J6/3 -> 2.6666667 | O6: =VLOOKUP(G6,$X$11:$Y$95,2) -> 2 | Q6: =IF(N6>=O6,"OK","Analisar") -> OK | R6: =SUM(O6:O15) -> 11.98 | T6: =COUNT(O6:O15) -> 7 | U6: 12 | V6: 0-3 meses: 2 repasses ou IPC 0,66; | AB6: ALAN FLAVIO VIEIRA | AF6: Camila Fernandes da Silva
B7: =B6+1 -> 2 | C7: =VLOOKUP(E7,dinamica!A:B,2,0) -> AUTÔNOMOS | FSA | D7: AUTÔNOMOS | FSA | E7: ISABELLA PEREIRA FELICIANO | F7: =VLOOKUP(E7,[1]Colaboradores!$A$2:$D$65,4,0) -> 45156 | G7: =_xlfn.DAYS($F$3,F7)/30 -> 31.833333 | H7: 15 | I7: 34 | J7: 8 | L7: =H7/12 -> 1.25 | M7: =I7/12 -> 2.8333333 | N7: =J7/3 -> 2.6666667 | O7: =VLOOKUP(G7,$X$11:$Y$95,2) -> 2 | Q7: =IF(N7>=O7,"OK","Analisar") -> OK | V7: 3-6 meses: 4 repasses ou IPC 1,33; | AB7: EMMANUELY FERNANDA DO NASCIMENTO | AF7: CLEIDE ALVES DE OLIVEIRA
B8: =B7+1 -> 3 | C8: =VLOOKUP(E8,dinamica!A:B,2,0) -> AUTÔNOMOS | FSA | D8: AUTÔNOMOS | FSA | E8: ANNA LUIZA PEREIRA DE SOUSA | F8: =VLOOKUP(E8,[1]Colaboradores!$A$2:$D$65,4,0) -> 45791 | G8: =_xlfn.DAYS($F$3,F8)/30 -> 10.666667 | I8: 20 | J8: 7 | L8: =H8/12 -> 0 | M8: =I8/12 -> 1.6666667 | N8: =J8/3 -> 2.3333333 | O8: =VLOOKUP(G8,$X$11:$Y$95,2) -> 2 | Q8: =IF(N8>=O8,"OK","Analisar") -> OK | S8: Desenvolvimento | V8: 6-9 meses: 5 repasses ou IPC 1,66; | AF8: ANNA LUIZA PEREIRA DE SOUSA
B9: =B8+1 -> 4 | C9: =VLOOKUP(E9,dinamica!A:B,2,0) -> AUTÔNOMOS | FSA | D9: AUTÔNOMOS | FSA | E9: STEFFANY SILVA PINTO | F9: =VLOOKUP(E9,[1]Colaboradores!$A$2:$D$65,4,0) -> 45931 | G9: =_xlfn.DAYS($F$3,F9)/30 -> 6 | I9: 2 | J9: 4 | L9: =H9/12 -> 0 | M9: =I9/12 -> 0.16666667 | N9: =J9/3 -> 1.3333333 | O9: =VLOOKUP(G9,$X$11:$Y$95,2) -> 1.66 | Q9: =IF(N9>=O9,"OK","Analisar") -> Analisar | S9: Reposição | V9: Após 9 meses: 6 repasses ou IPC 2; | AF9: JHENNEFE HORRARA SILVA DE OLIVEIRA
